{
  "count": 112,
  "data": [
    {
      "title": "Italy",
      "title_en": null,
      "source": "www.ansa.it",
      "url": "https://www.ansa.it/toscana/notizie/2026/05/27/fisco-gdf-scopre-21-badanti-evasori-totali-nel-fiorentino_339faaef-d195-4d2f-859b-41a95183991c.html",
      "published_at": "",
      "language": null,
      "source_lang": null,
      "provider": "gdelt_gkg_geojson",
      "themes": [
        "TAX_FNCACT_EMPLOYEES",
        "ECON_TAXATION",
        "USPEC_POLICY1",
        "EPU_POLICY_TAX",
        "EPU_CATS_TAXES",
        "ECON_TAXATION",
        "USPEC_POLICY1",
        "EPU_POLICY_TAX",
        "EPU_CATS_TAXES",
        "TAX_FNCACT_CAREGIVERS",
        "TAX_FNCACT_WORKERS",
        "TAX_FNCACT_WORKERS",
        "TAX_FNCACT_GUARD",
        "TAX_ETHNICITY_ITALIAN",
        "TAX_WORLDLANGUAGES_ITALIAN"
      ]
    },
    {
      "title": "Finland",
      "title_en": null,
      "source": "www.kbear102.com",
      "url": "https://www.kbear102.com/2026/05/27/hancocks-designation-as-the-2026-finno-ugric-capital-of-culture-explores-heritage-beyond-finland/",
      "published_at": "",
      "language": null,
      "source_lang": null,
      "provider": "gdelt_gkg_geojson",
      "themes": [
        "TAX_ETHNICITY_FINNOUGRIC",
        "WB_2670_JOBS",
        "WB_1467_EDUCATION_FOR_ALL",
        "WB_470_EDUCATION",
        "WB_2131_EMPLOYABILITY_SKILLS_AND_JOBS",
        "WB_1484_EDUCATION_SKILLS_DEVELOPMENT_AND_LABOR_MARKET",
        "ENV_MINING",
        "WB_507_ENERGY_AND_EXTRACTIVES",
        "WB_895_MINING_SYSTEMS",
        "WB_2934_COPPER",
        "WB_1699_METAL_ORE_MINING",
        "TAX_WORLDLANGUAGES_FINNISH",
        "TAX_WORLDLANGUAGES_FINNISH",
        "WB_1979_NATURAL_RESOURCE_MANAGEMENT",
        "WB_435_AGRICULTURE_AND_FOOD_SECURITY",
        "WB_1986_MOUNTAINS",
        "IMMIGRATION",
        "TAX_FNCACT_IMMIGRANTS",
        "EPU_ECONOMY_HISTORIC",
        "TAX_WORLDLANGUAGES_RUSSIA"
      ]
    },
    {
      "title": "Michigan, United States",
      "title_en": null,
      "source": "www.kbear102.com",
      "url": "https://www.kbear102.com/2026/05/27/hancocks-designation-as-the-2026-finno-ugric-capital-of-culture-explores-heritage-beyond-finland/",
      "published_at": "",
      "language": null,
      "source_lang": null,
      "provider": "gdelt_gkg_geojson",
      "themes": [
        "TAX_ETHNICITY_FINNOUGRIC",
        "WB_2670_JOBS",
        "WB_1467_EDUCATION_FOR_ALL",
        "WB_470_EDUCATION",
        "WB_2131_EMPLOYABILITY_SKILLS_AND_JOBS",
        "WB_1484_EDUCATION_SKILLS_DEVELOPMENT_AND_LABOR_MARKET",
        "ENV_MINING",
        "WB_507_ENERGY_AND_EXTRACTIVES",
        "WB_895_MINING_SYSTEMS",
        "WB_2934_COPPER",
        "WB_1699_METAL_ORE_MINING",
        "TAX_WORLDLANGUAGES_FINNISH",
        "IMMIGRATION",
        "TAX_FNCACT_IMMIGRANTS",
        "EPU_ECONOMY_HISTORIC"
      ]
    },
    {
      "title": "India",
      "title_en": null,
      "source": "www.heute.at",
      "url": "https://www.heute.at/s/bei-diesen-vorwahlen-nie-auf-whatsapp-rangehen-120201109",
      "published_at": "",
      "language": null,
      "source_lang": null,
      "provider": "gdelt_gkg_geojson",
      "themes": [
        "CRISISLEX_CRISISLEXREC",
        "TAX_ECON_PRICE",
        "TAX_FNCACT_VICTIM",
        "TAX_ETHNICITY_GERMAN",
        "TAX_WORLDLANGUAGES_GERMAN"
      ]
    },
    {
      "title": "Mexico",
      "title_en": null,
      "source": "www.heute.at",
      "url": "https://www.heute.at/s/bei-diesen-vorwahlen-nie-auf-whatsapp-rangehen-120201109",
      "published_at": "",
      "language": null,
      "source_lang": null,
      "provider": "gdelt_gkg_geojson",
      "themes": [
        "CRISISLEX_CRISISLEXREC",
        "TAX_ECON_PRICE",
        "TAX_FNCACT_VICTIM",
        "TAX_ETHNICITY_GERMAN",
        "TAX_WORLDLANGUAGES_GERMAN"
      ]
    },
    {
      "title": "Germany",
      "title_en": null,
      "source": "www.heute.at",
      "url": "https://www.heute.at/s/bei-diesen-vorwahlen-nie-auf-whatsapp-rangehen-120201109",
      "published_at": "",
      "language": null,
      "source_lang": null,
      "provider": "gdelt_gkg_geojson",
      "themes": [
        "TAX_ECON_PRICE",
        "TAX_FNCACT_VICTIM",
        "TAX_ETHNICITY_GERMAN",
        "TAX_WORLDLANGUAGES_GERMAN"
      ]
    },
    {
      "title": "Moscow, Moskva, Russia",
      "title_en": null,
      "source": "aif.ru",
      "url": "https://aif.ru/society/hersonskaya-oblast-poluchit-110-mln-rubley-na-razvitie-turizma",
      "published_at": "",
      "language": null,
      "source_lang": null,
      "provider": "gdelt_gkg_geojson",
      "themes": [
        "TOURISM",
        "WB_825_TOURISM",
        "WB_1921_PRIVATE_SECTOR_DEVELOPMENT",
        "WB_346_COMPETITIVE_INDUSTRIES",
        "WB_818_INDUSTRY_POLICY_AND_REAL_SECTORS",
        "TOURISM",
        "WB_825_TOURISM",
        "WB_1921_PRIVATE_SECTOR_DEVELOPMENT",
        "WB_346_COMPETITIVE_INDUSTRIES",
        "WB_818_INDUSTRY_POLICY_AND_REAL_SECTORS",
        "TOURISM",
        "WB_825_TOURISM",
        "WB_1921_PRIVATE_SECTOR_DEVELOPMENT",
        "WB_346_COMPETITIVE_INDUSTRIES",
        "WB_818_INDUSTRY_POLICY_AND_REAL_SECTORS",
        "ECON_SUBSIDIES",
        "WB_1948_SUBSIDIES",
        "WB_695_POVERTY",
        "WB_706_EVIDENCE_BASED_POLICY"
      ]
    },
    {
      "title": "Russia",
      "title_en": null,
      "source": "www.bankingnews.gr",
      "url": "https://www.bankingnews.gr/diethni/articles/877933/oi-ipa-ekplissoun-to-rosiko-su-35-exei-14-anepanalipta-pleonektimata-enanti-tou-neoterou-f-35%20title=",
      "published_at": "",
      "language": null,
      "source_lang": null,
      "provider": "gdelt_gkg_geojson",
      "themes": [
        "EPU_ECONOMY_HISTORIC",
        "EPU_CATS_NATIONAL_SECURITY",
        "EPU_CATS_NATIONAL_SECURITY",
        "MEDIA_MSM",
        "TAX_ETHNICITY_RUSSIAN",
        "TAX_WORLDLANGUAGES_RUSSIAN",
        "TAX_ETHNICITY_RUSSIAN",
        "TAX_WORLDLANGUAGES_RUSSIAN",
        "TAX_ETHNICITY_RUSSIAN",
        "TAX_WORLDLANGUAGES_RUSSIAN",
        "ARMEDCONFLICT"
      ]
    },
    {
      "title": "Warsaw, (Pl67), Poland",
      "title_en": null,
      "source": "www.dziennikwschodni.pl:443",
      "url": "https://www.dziennikwschodni.pl:443/artykul/389257,zolnierz-strzelal-przy-granicy-z-bialorusia-sad-w-lublinie-wydal-wyrok",
      "published_at": "",
      "language": null,
      "source_lang": null,
      "provider": "gdelt_gkg_geojson",
      "themes": [
        "TAX_RELIGION_ORTHODOX",
        "TAX_FNCACT_GUARD",
        "CRISISLEX_C07_SAFETY",
        "BORDER",
        "TAX_WEAPONS_ARMORED",
        "EPU_CATS_REGULATION",
        "EPU_CATS_FINANCIAL_REGULATION",
        "TAX_MILITARY_TITLE_OFFICERS",
        "TAX_FNCACT_OFFICERS",
        "MILITARY",
        "TAX_MILITARY_TITLE_SOLDIER",
        "TAX_FNCACT_SOLDIER",
        "EPU_ECONOMY_HISTORIC",
        "WB_696_PUBLIC_SECTOR_MANAGEMENT",
        "WB_840_JUSTICE",
        "WB_1014_CRIMINAL_JUSTICE",
        "WB_696_PUBLIC_SECTOR_MANAGEMENT",
        "WB_840_JUSTICE",
        "WB_1014_CRIMINAL_JUSTICE"
      ]
    },
    {
      "title": "Shaanxi, Shaanxi, China",
      "title_en": null,
      "source": "k.sina.com.cn",
      "url": "https://k.sina.com.cn/article_7857141524_1d452771401902uo02.html",
      "published_at": "",
      "language": null,
      "source_lang": null,
      "provider": "gdelt_gkg_geojson",
      "themes": [
        "CRISISLEX_C07_SAFETY",
        "EPU_ECONOMY",
        "MANMADE_DISASTER_IMPLIED",
        "MANMADE_DISASTER_IMPLIED"
      ]
    },
    {
      "title": "Yutong, Hainan, China",
      "title_en": null,
      "source": "k.sina.com.cn",
      "url": "https://k.sina.com.cn/article_7857141524_1d452771401902uo02.html",
      "published_at": "",
      "language": null,
      "source_lang": null,
      "provider": "gdelt_gkg_geojson",
      "themes": [
        "CRISISLEX_C07_SAFETY",
        "EPU_ECONOMY",
        "MANMADE_DISASTER_IMPLIED",
        "PUBLIC_TRANSPORT"
      ]
    },
    {
      "title": "Chile",
      "title_en": null,
      "source": "k.sina.com.cn",
      "url": "https://k.sina.com.cn/article_7857141524_1d452771401902uo02.html",
      "published_at": "",
      "language": null,
      "source_lang": null,
      "provider": "gdelt_gkg_geojson",
      "themes": [
        "EPU_ECONOMY_HISTORIC",
        "TAX_ECON_PRICE",
        "TAX_ECON_PRICE",
        "TAX_ECON_PRICE",
        "TAX_ECON_PRICE",
        "TAX_ECON_PRICE"
      ]
    },
    {
      "title": "Beijing, Beijing, China",
      "title_en": null,
      "source": "k.sina.com.cn",
      "url": "https://k.sina.com.cn/article_7857141524_1d452771401902uo02.html",
      "published_at": "",
      "language": null,
      "source_lang": null,
      "provider": "gdelt_gkg_geojson",
      "themes": [
        "EPU_ECONOMY_HISTORIC",
        "SCIENCE",
        "SCIENCE",
        "MANMADE_DISASTER_IMPLIED"
      ]
    },
    {
      "title": "Capodichino, Campania, Italy",
      "title_en": null,
      "source": "www.ansa.it",
      "url": "https://www.ansa.it/pressrelease/campania/2026/05/27/nuova-apertura-sole-365-a-napoli_1e0e1fbb-8c76-448f-878f-9111c53064d3.html",
      "published_at": "",
      "language": null,
      "source_lang": null,
      "provider": "gdelt_gkg_geojson",
      "themes": [
        "TAX_ECON_PRICE",
        "TAX_FNCACT_CITIZENS"
      ]
    },
    {
      "title": "Jakarta, Jakarta Raya, Indonesia",
      "title_en": null,
      "source": "lampung.tribunnews.com",
      "url": "https://lampung.tribunnews.com/news/1210241/rupiah-ambruk-hingga-rp17800-reaksi-purbaya-disorot",
      "published_at": "",
      "language": null,
      "source_lang": null,
      "provider": "gdelt_gkg_geojson",
      "themes": [
        "ECON_CURRENCY_EXCHANGE_RATE",
        "EPU_CATS_SOVEREIGN_DEBT_CURRENCY_CRISES",
        "ECON_CURRENCY_EXCHANGE_RATE",
        "EPU_CATS_SOVEREIGN_DEBT_CURRENCY_CRISES",
        "TAX_RELIGION_MOSQUE",
        "ECON_WORLDCURRENCIES_DOLLARS",
        "ECON_WORLDCURRENCIES_DOLLARS",
        "ECON_WORLDCURRENCIES_DOLLARS",
        "ECON_WORLDCURRENCIES_DOLLARS",
        "ECON_WORLDCURRENCIES_DOLLARS",
        "ECON_WORLDCURRENCIES_DOLLARS",
        "ECON_WORLDCURRENCIES_DOLLARS",
        "USPEC_POLICY1",
        "EPU_CATS_TAXES",
        "GENERAL_GOVERNMENT",
        "EPU_POLICY_GOVERNMENT",
        "TAX_FNCACT_MINISTER_OF_FINANCE",
        "TAX_FNCACT_MINISTER_OF_FINANCE",
        "LEADER",
        "LEADER",
        "TAX_FNCACT_MINISTER",
        "TAX_FNCACT_MINISTER"
      ]
    },
    {
      "title": "Indonesia",
      "title_en": null,
      "source": "lampung.tribunnews.com",
      "url": "https://lampung.tribunnews.com/news/1210241/rupiah-ambruk-hingga-rp17800-reaksi-purbaya-disorot",
      "published_at": "",
      "language": null,
      "source_lang": null,
      "provider": "gdelt_gkg_geojson",
      "themes": [
        "ECON_CURRENCY_EXCHANGE_RATE",
        "EPU_CATS_SOVEREIGN_DEBT_CURRENCY_CRISES",
        "ECON_CURRENCY_EXCHANGE_RATE",
        "EPU_CATS_SOVEREIGN_DEBT_CURRENCY_CRISES",
        "TAX_RELIGION_MOSQUE",
        "ECON_WORLDCURRENCIES_DOLLARS",
        "ECON_WORLDCURRENCIES_DOLLARS",
        "ECON_WORLDCURRENCIES_DOLLARS",
        "ECON_WORLDCURRENCIES_DOLLARS",
        "ECON_WORLDCURRENCIES_DOLLARS",
        "ECON_WORLDCURRENCIES_DOLLARS",
        "USPEC_POLICY1",
        "EPU_CATS_TAXES",
        "GENERAL_GOVERNMENT",
        "EPU_POLICY_GOVERNMENT",
        "TAX_FNCACT_MINISTER_OF_FINANCE",
        "TAX_FNCACT_MINISTER_OF_FINANCE",
        "LEADER",
        "LEADER",
        "TAX_FNCACT_MINISTER",
        "TAX_FNCACT_MINISTER"
      ]
    },
    {
      "title": "Jordan",
      "title_en": null,
      "source": "alanbatnews.net",
      "url": "https://alanbatnews.net/article/477860",
      "published_at": "",
      "language": null,
      "source_lang": null,
      "provider": "gdelt_gkg_geojson",
      "themes": [
        "TAX_FNCACT_MINISTER",
        "TAX_FNCACT_MINISTER",
        "EPU_ECONOMY",
        "EPU_ECONOMY_HISTORIC",
        "EPU_ECONOMY",
        "EPU_ECONOMY_HISTORIC",
        "WB_698_TRADE",
        "TAX_FNCACT_EXECUTIVE",
        "TAX_WORLDLANGUAGES_AZERBAIJAN",
        "TAX_WORLDLANGUAGES_AZERBAIJAN",
        "TAX_WORLDLANGUAGES_AZERBAIJAN",
        "SOC_ECONCOOP"
      ]
    },
    {
      "title": "Baku, Baki*, Azerbaijan",
      "title_en": null,
      "source": "alanbatnews.net",
      "url": "https://alanbatnews.net/article/477860",
      "published_at": "",
      "language": null,
      "source_lang": null,
      "provider": "gdelt_gkg_geojson",
      "themes": [
        "TAX_FNCACT_MINISTER",
        "TAX_FNCACT_MINISTER",
        "EPU_ECONOMY",
        "EPU_ECONOMY_HISTORIC",
        "EPU_ECONOMY",
        "EPU_ECONOMY_HISTORIC",
        "WB_698_TRADE",
        "WB_698_TRADE",
        "TAX_FNCACT_EXECUTIVE",
        "TAX_WORLDLANGUAGES_AZERBAIJAN",
        "TAX_WORLDLANGUAGES_AZERBAIJAN",
        "TAX_WORLDLANGUAGES_AZERBAIJAN",
        "TAX_ETHNICITY_AZERBAIJANI",
        "TAX_WORLDLANGUAGES_AZERBAIJANI",
        "SOC_ECONCOOP"
      ]
    },
    {
      "title": "Azerbaijan",
      "title_en": null,
      "source": "alanbatnews.net",
      "url": "https://alanbatnews.net/article/477860",
      "published_at": "",
      "language": null,
      "source_lang": null,
      "provider": "gdelt_gkg_geojson",
      "themes": [
        "TAX_FNCACT_MINISTER",
        "TAX_FNCACT_MINISTER",
        "EPU_ECONOMY",
        "EPU_ECONOMY_HISTORIC",
        "EPU_ECONOMY",
        "EPU_ECONOMY_HISTORIC",
        "WB_698_TRADE",
        "TAX_FNCACT_EXECUTIVE",
        "TAX_WORLDLANGUAGES_AZERBAIJAN",
        "TAX_WORLDLANGUAGES_AZERBAIJAN",
        "TAX_WORLDLANGUAGES_AZERBAIJAN",
        "SOC_ECONCOOP"
      ]
    },
    {
      "title": "Oman",
      "title_en": null,
      "source": "alanbatnews.net",
      "url": "https://alanbatnews.net/article/477860",
      "published_at": "",
      "language": null,
      "source_lang": null,
      "provider": "gdelt_gkg_geojson",
      "themes": [
        "MOVEMENT_GENERAL",
        "TOURISM",
        "WB_825_TOURISM",
        "WB_1921_PRIVATE_SECTOR_DEVELOPMENT",
        "WB_346_COMPETITIVE_INDUSTRIES",
        "WB_818_INDUSTRY_POLICY_AND_REAL_SECTORS",
        "TOURISM",
        "WB_825_TOURISM",
        "WB_1921_PRIVATE_SECTOR_DEVELOPMENT",
        "WB_346_COMPETITIVE_INDUSTRIES",
        "WB_818_INDUSTRY_POLICY_AND_REAL_SECTORS",
        "TOURISM",
        "WB_825_TOURISM",
        "WB_1921_PRIVATE_SECTOR_DEVELOPMENT",
        "WB_346_COMPETITIVE_INDUSTRIES",
        "WB_818_INDUSTRY_POLICY_AND_REAL_SECTORS",
        "MANMADE_DISASTER_IMPLIED",
        "MANMADE_DISASTER_IMPLIED",
        "EPU_ECONOMY",
        "EPU_ECONOMY_HISTORIC",
        "TAX_WORLDLANGUAGES_AZERBAIJAN",
        "TAX_WORLDLANGUAGES_AZERBAIJAN",
        "TAX_FNCACT_TOURIST",
        "TAX_FNCACT_AMBASSADOR",
        "WB_165_AIR_TRANSPORT",
        "WB_135_TRANSPORT",
        "WB_164_MODES_OF_TRANSPORT"
      ]
    },
    {
      "title": "France",
      "title_en": null,
      "source": "wartakota.tribunnews.com",
      "url": "https://wartakota.tribunnews.com/news/891020/menlu-ungkap-alasan-prabowo-kunjungi-perancis-di-momen-idul-adha",
      "published_at": "",
      "language": null,
      "source_lang": null,
      "provider": "gdelt_gkg_geojson",
      "themes": [
        "UNGP_FORESTS_RIVERS_OCEANS",
        "LEADER",
        "TAX_FNCACT_PRESIDENT",
        "USPEC_POLITICS_GENERAL1",
        "LEADER",
        "TAX_FNCACT_PRESIDENT",
        "USPEC_POLITICS_GENERAL1",
        "USPEC_POLICY1",
        "EPU_ECONOMY",
        "EPU_ECONOMY_HISTORIC",
        "MANMADE_DISASTER_IMPLIED",
        "WB_168_ROADS_AND_HIGHWAYS",
        "WB_135_TRANSPORT",
        "WB_1809_HIGHWAYS",
        "WB_1803_TRANSPORT_INFRASTRUCTURE",
        "TAX_FNCACT_SECRETARY",
        "GENERAL_GOVERNMENT",
        "EPU_POLICY_GOVERNMENT"
      ]
    },
    {
      "title": "Kristianstad, Skane Lan, Sweden",
      "title_en": null,
      "source": "www.nsk.se",
      "url": "https://www.nsk.se/kristianstad/nedskarningar-inom-skolan-vantar-besked-efter-valet/",
      "published_at": "",
      "language": null,
      "source_lang": null,
      "provider": "gdelt_gkg_geojson",
      "themes": [
        "CRISISLEX_CRISISLEXREC",
        "EPU_ECONOMY",
        "EPU_ECONOMY_HISTORIC",
        "ELECTION",
        "ELECTION",
        "WB_1979_NATURAL_RESOURCE_MANAGEMENT",
        "WB_435_AGRICULTURE_AND_FOOD_SECURITY",
        "WB_1986_MOUNTAINS",
        "EDUCATION",
        "SOC_POINTSOFINTEREST_SCHOOL",
        "EDUCATION",
        "SOC_POINTSOFINTEREST_SCHOOL",
        "TAX_FNCACT_CHILD"
      ]
    },
    {
      "title": "New York, United States",
      "title_en": null,
      "source": "wsau.com",
      "url": "https://wsau.com/2026/05/27/ny-fed-finds-remarkable-increase-in-food-insecurity-for-many-americans/",
      "published_at": "",
      "language": null,
      "source_lang": null,
      "provider": "gdelt_gkg_geojson",
      "themes": [
        "EPU_POLICY_FEDERAL_RESERVE",
        "EPU_CATS_MONETARY_POLICY",
        "USPEC_POLICY1",
        "EPU_ECONOMY",
        "EPU_ECONOMY_HISTORIC"
      ]
    },
    {
      "title": "Tokyo, Tokyo, Japan",
      "title_en": null,
      "source": "www.whathifi.com",
      "url": "https://www.whathifi.com/tv-home-cinema/televisions/i-spent-an-hour-testing-sonys-bravia-9-ii-true-rgb-tv-and-its-pretty-awesome-but-my-oled-isnt-going-in-the-bin-yet",
      "published_at": "",
      "language": null,
      "source_lang": null,
      "provider": "gdelt_gkg_geojson",
      "themes": [
        "EPU_ECONOMY_HISTORIC",
        "USPEC_POLICY1",
        "EPU_POLICY_SPENDING",
        "MEDIA_MSM",
        "MEDIA_MSM"
      ]
    },
    {
      "title": "Thailand",
      "title_en": null,
      "source": "www.asahi.com",
      "url": "https://www.asahi.com/articles/ASV5W54WHV5WUHBI026M.html",
      "published_at": "",
      "language": null,
      "source_lang": null,
      "provider": "gdelt_gkg_geojson",
      "themes": [
        "SANCTIONS",
        "TAX_WORLDLANGUAGES_RUSSIA",
        "TAX_WORLDLANGUAGES_RUSSIA",
        "USPEC_POLICY1",
        "EPU_ECONOMY",
        "EPU_ECONOMY_HISTORIC",
        "USPEC_POLICY1",
        "EPU_ECONOMY",
        "EPU_ECONOMY_HISTORIC",
        "TAX_ETHNICITY_JAPANESE",
        "TAX_WORLDLANGUAGES_JAPANESE",
        "TAX_DISEASE_COUGH"
      ]
    },
    {
      "title": "Japan",
      "title_en": null,
      "source": "www.asahi.com",
      "url": "https://www.asahi.com/articles/ASV5W54WHV5WUHBI026M.html",
      "published_at": "",
      "language": null,
      "source_lang": null,
      "provider": "gdelt_gkg_geojson",
      "themes": [
        "SANCTIONS",
        "TAX_WORLDLANGUAGES_RUSSIA",
        "TAX_WORLDLANGUAGES_RUSSIA",
        "TAX_WORLDLANGUAGES_RUSSIA",
        "TAX_WORLDLANGUAGES_RUSSIA",
        "USPEC_POLICY1",
        "EPU_ECONOMY",
        "EPU_ECONOMY_HISTORIC",
        "USPEC_POLICY1",
        "EPU_ECONOMY",
        "EPU_ECONOMY_HISTORIC",
        "TAX_ETHNICITY_JAPANESE",
        "TAX_WORLDLANGUAGES_JAPANESE",
        "TAX_DISEASE_COUGH"
      ]
    },
    {
      "title": "Ukraine",
      "title_en": null,
      "source": "www.asahi.com",
      "url": "https://www.asahi.com/articles/ASV5W54WHV5WUHBI026M.html",
      "published_at": "",
      "language": null,
      "source_lang": null,
      "provider": "gdelt_gkg_geojson",
      "themes": [
        "SANCTIONS",
        "TAX_WORLDLANGUAGES_RUSSIA",
        "TAX_WORLDLANGUAGES_RUSSIA",
        "TAX_WORLDLANGUAGES_RUSSIA",
        "TAX_WORLDLANGUAGES_RUSSIA",
        "USPEC_POLICY1",
        "EPU_ECONOMY",
        "EPU_ECONOMY_HISTORIC",
        "USPEC_POLICY1",
        "EPU_ECONOMY",
        "EPU_ECONOMY_HISTORIC",
        "TAX_ETHNICITY_JAPANESE",
        "TAX_WORLDLANGUAGES_JAPANESE",
        "TAX_DISEASE_COUGH"
      ]
    },
    {
      "title": "Egypt",
      "title_en": null,
      "source": "gr.euronews.com",
      "url": "https://gr.euronews.com/business/2026/05/27/egypt-is-experiencing-a-significant-year-for-gas-discoveries-but-faces-challenges-in-meeti",
      "published_at": "",
      "language": null,
      "source_lang": null,
      "provider": "gdelt_gkg_geojson",
      "themes": [
        "EPU_POLICY_REFORM",
        "CRISISLEX_T11_UPDATESSYMPATHY",
        "ARMEDCONFLICT",
        "EPU_CATS_NATIONAL_SECURITY",
        "ENV_NATURALGAS",
        "ECON_ELECTRICALDEMAND"
      ]
    },
    {
      "title": "Mumbai, Maharashtra, India",
      "title_en": null,
      "source": "www.punjabkesari.com",
      "url": "https://www.punjabkesari.com/india-news/mumbai-satellite-garden-society-controversy/",
      "published_at": "",
      "language": null,
      "source_lang": null,
      "provider": "gdelt_gkg_geojson",
      "themes": [
        "TAX_FNCACT_POLICE_COMMISSIONER",
        "TAX_FNCACT_COMMISSIONER",
        "TAX_FNCACT_POLICE_COMMISSIONER",
        "TAX_FNCACT_COMMISSIONER",
        "LEGISLATION",
        "EPU_POLICY_LAW",
        "TAX_FNCACT_POLICE_OFFICER",
        "CRISISLEX_CRISISLEXREC",
        "TAX_FNCACT_OFFICER",
        "SECURITY_SERVICES",
        "TAX_FNCACT_POLICE",
        "CRISISLEX_C07_SAFETY",
        "SECURITY_SERVICES",
        "TAX_FNCACT_POLICE",
        "CRISISLEX_C07_SAFETY",
        "SECURITY_SERVICES",
        "TAX_FNCACT_POLICE",
        "CRISISLEX_C07_SAFETY",
        "SECURITY_SERVICES",
        "TAX_FNCACT_POLICE",
        "CRISISLEX_C07_SAFETY",
        "SECURITY_SERVICES",
        "TAX_FNCACT_POLICE",
        "CRISISLEX_C07_SAFETY",
        "SECURITY_SERVICES",
        "TAX_FNCACT_POLICE",
        "CRISISLEX_C07_SAFETY",
        "SECURITY_SERVICES",
        "TAX_FNCACT_POLICE",
        "CRISISLEX_C07_SAFETY",
        "SECURITY_SERVICES",
        "TAX_FNCACT_POLICE",
        "CRISISLEX_C07_SAFETY",
        "TAX_FNCACT_ASSISTANT",
        "ECON_TAXATION",
        "EPU_POLICY_TAX",
        "EPU_CATS_TAXES",
        "TAX_FNCACT_COMMISSIONER"
      ]
    },
    {
      "title": "Washington, Washington, United States",
      "title_en": null,
      "source": "www.bankingnews.gr",
      "url": "https://www.bankingnews.gr/diethni/articles/877922/tromero-oi-ipa-etoimes-na-aposyroun-aeroskafi-apo-m-anatoli-entos-72-oron-thriamvos-iran-me-mnimonio-6-simeion",
      "published_at": "",
      "language": null,
      "source_lang": null,
      "provider": "gdelt_gkg_geojson",
      "themes": [
        "SOC_POINTSOFINTEREST_AIRPORT",
        "WB_135_TRANSPORT",
        "WB_1803_TRANSPORT_INFRASTRUCTURE",
        "WB_1804_AIRPORTS",
        "UNGP_FORESTS_RIVERS_OCEANS",
        "WB_2433_CONFLICT_AND_VIOLENCE",
        "WB_2432_FRAGILITY_CONFLICT_AND_VIOLENCE",
        "EPU_ECONOMY_HISTORIC"
      ]
    },
    {
      "title": "Israel",
      "title_en": null,
      "source": "www.bankingnews.gr",
      "url": "https://www.bankingnews.gr/diethni/articles/877922/tromero-oi-ipa-etoimes-na-aposyroun-aeroskafi-apo-m-anatoli-entos-72-oron-thriamvos-iran-me-mnimonio-6-simeion",
      "published_at": "",
      "language": null,
      "source_lang": null,
      "provider": "gdelt_gkg_geojson",
      "themes": [
        "SOC_POINTSOFINTEREST_AIRPORT",
        "WB_135_TRANSPORT",
        "WB_1803_TRANSPORT_INFRASTRUCTURE",
        "WB_1804_AIRPORTS",
        "MANMADE_DISASTER_IMPLIED",
        "UNGP_FORESTS_RIVERS_OCEANS",
        "TAX_ETHNICITY_IRANIAN",
        "WB_678_DIGITAL_GOVERNMENT",
        "WB_694_BROADCAST_AND_MEDIA",
        "WB_133_INFORMATION_AND_COMMUNICATION_TECHNOLOGIES",
        "EPU_ECONOMY_HISTORIC"
      ]
    },
    {
      "title": "Iran",
      "title_en": null,
      "source": "www.bankingnews.gr",
      "url": "https://www.bankingnews.gr/diethni/articles/877922/tromero-oi-ipa-etoimes-na-aposyroun-aeroskafi-apo-m-anatoli-entos-72-oron-thriamvos-iran-me-mnimonio-6-simeion",
      "published_at": "",
      "language": null,
      "source_lang": null,
      "provider": "gdelt_gkg_geojson",
      "themes": [
        "MILITARY",
        "TAX_FNCACT_NAVY",
        "UNGP_FORESTS_RIVERS_OCEANS",
        "TAX_ETHNICITY_IRANIAN",
        "MEDIA_MSM",
        "WB_678_DIGITAL_GOVERNMENT",
        "WB_694_BROADCAST_AND_MEDIA",
        "WB_133_INFORMATION_AND_COMMUNICATION_TECHNOLOGIES",
        "EPU_ECONOMY_HISTORIC"
      ]
    },
    {
      "title": "Nigeria",
      "title_en": null,
      "source": "dailypost.ng",
      "url": "https://dailypost.ng/2026/05/27/cubana-chief-priest-opens-up-on-feud-with-burna-boy/",
      "published_at": "",
      "language": null,
      "source_lang": null,
      "provider": "gdelt_gkg_geojson",
      "themes": [
        "TAX_FNCACT_PRIEST",
        "TAX_FNCACT_SINGER",
        "TAX_FNCACT_SOCIALITE",
        "TAX_FNCACT_CHIEF",
        "ECON_ENTREPRENEURSHIP",
        "TAX_FNCACT_ENTREPRENEUR"
      ]
    },
    {
      "title": "Brazil",
      "title_en": null,
      "source": "vermelho.org.br",
      "url": "https://vermelho.org.br/2026/05/27/inflacao-oficial-desacelera-em-maio-e-fecha-em-062-diz-ibge/",
      "published_at": "",
      "language": null,
      "source_lang": null,
      "provider": "gdelt_gkg_geojson",
      "themes": [
        "USPEC_POLICY1",
        "EPU_POLICY_BUDGET",
        "TAX_FNCACT_OFFICIAL",
        "MARITIME",
        "TAX_ECON_PRICE"
      ]
    },
    {
      "title": "Greece",
      "title_en": null,
      "source": "english.news.cn",
      "url": "https://english.news.cn/20260527/e1a4d0ada39b44e3b4e9b14f89ca5986/c.html",
      "published_at": "",
      "language": null,
      "source_lang": null,
      "provider": "gdelt_gkg_geojson",
      "themes": [
        "MEDIA_MSM",
        "TAX_ETHNICITY_GREEKS",
        "TAX_WORLDLANGUAGES_GREEKS",
        "ECON_INFLATION",
        "WB_1104_MACROECONOMIC_VULNERABILITY_AND_DEBT",
        "WB_442_INFLATION",
        "GEN_HOLIDAY",
        "USPEC_POLICY1",
        "EPU_POLICY_SPENDING",
        "TAX_ECON_PRICE",
        "TAX_ETHNICITY_GREEK",
        "TAX_WORLDLANGUAGES_GREEK"
      ]
    },
    {
      "title": "Athens, AttikíR, Greece",
      "title_en": null,
      "source": "english.news.cn",
      "url": "https://english.news.cn/20260527/e1a4d0ada39b44e3b4e9b14f89ca5986/c.html",
      "published_at": "",
      "language": null,
      "source_lang": null,
      "provider": "gdelt_gkg_geojson",
      "themes": [
        "MEDIA_MSM",
        "TAX_ETHNICITY_GREEKS",
        "TAX_WORLDLANGUAGES_GREEKS",
        "GEN_HOLIDAY",
        "USPEC_POLICY1",
        "EPU_POLICY_SPENDING",
        "TAX_ECON_PRICE",
        "TAX_ETHNICITY_GREEK",
        "TAX_WORLDLANGUAGES_GREEK"
      ]
    },
    {
      "title": "Maliq, Qarku Korce, Albania",
      "title_en": null,
      "source": "sot.com.al",
      "url": "https://sot.com.al/ekonomia/ne-nuk-demshperblehemi-plus-cmimet-e-shtrenjta-fermeret-e-maliqit-reduktojne-mbjelljet-per-shkak-te-kostove-te-larta/",
      "published_at": "",
      "language": null,
      "source_lang": null,
      "provider": "gdelt_gkg_geojson",
      "themes": [
        "AGRICULTURE",
        "TAX_FNCACT_FARMERS",
        "AGRICULTURE",
        "TAX_FNCACT_FARMERS",
        "TAX_ECON_PRICE",
        "TAX_ECON_PRICE"
      ]
    },
    {
      "title": "South Africa",
      "title_en": null,
      "source": "www.zazoom.it",
      "url": "https://www.zazoom.it/2026-05-27/ritrovati-i-resti-di-mario-conti-il-ragno-del-cerro-torre/19261853/",
      "published_at": "",
      "language": null,
      "source_lang": null,
      "provider": "gdelt_gkg_geojson",
      "themes": [
        "ECON_ENTREPRENEURSHIP",
        "TAX_FNCACT_ENTREPRENEUR",
        "TAX_WORLDREPTILES_CROCODILE",
        "TAX_FNCACT_MOUNTAINEER",
        "TAX_FNCACT_CONTRACTOR"
      ]
    },
    {
      "title": "Livigno, Lombardia, Italy",
      "title_en": null,
      "source": "www.zazoom.it",
      "url": "https://www.zazoom.it/2026-05-27/ritrovati-i-resti-di-mario-conti-il-ragno-del-cerro-torre/19261853/",
      "published_at": "",
      "language": null,
      "source_lang": null,
      "provider": "gdelt_gkg_geojson",
      "themes": [
        "ECON_ENTREPRENEURSHIP",
        "TAX_FNCACT_ENTREPRENEUR",
        "WB_1979_NATURAL_RESOURCE_MANAGEMENT",
        "WB_435_AGRICULTURE_AND_FOOD_SECURITY",
        "WB_1986_MOUNTAINS",
        "TAX_WORLDREPTILES_CROCODILE",
        "TAX_FNCACT_MAN",
        "TAX_FNCACT_CONTRACTOR",
        "TAX_WORLDMAMMALS_SNOW_LEOPARD",
        "TAX_WORLDMAMMALS_LEOPARD"
      ]
    },
    {
      "title": "Philippines",
      "title_en": null,
      "source": "www.manilatimes.net",
      "url": "https://www.manilatimes.net/2026/05/28/business/top-business/ph-not-in-stagflation-mode-economists/2352904",
      "published_at": "",
      "language": null,
      "source_lang": null,
      "provider": "gdelt_gkg_geojson",
      "themes": [
        "ARMEDCONFLICT",
        "EPU_CATS_NATIONAL_SECURITY",
        "TAX_FNCACT_ANALYSTS",
        "USPEC_POLICY1",
        "EPU_ECONOMY",
        "EPU_ECONOMY_HISTORIC",
        "USPEC_POLICY1",
        "EPU_ECONOMY",
        "EPU_ECONOMY_HISTORIC",
        "ECON_INFLATION",
        "WB_1104_MACROECONOMIC_VULNERABILITY_AND_DEBT",
        "WB_442_INFLATION",
        "EDUCATION",
        "SOC_POINTSOFINTEREST_UNIVERSITY"
      ]
    },
    {
      "title": "Manila, Manila, Philippines",
      "title_en": null,
      "source": "www.manilatimes.net",
      "url": "https://www.manilatimes.net/2026/05/28/business/top-business/ph-not-in-stagflation-mode-economists/2352904",
      "published_at": "",
      "language": null,
      "source_lang": null,
      "provider": "gdelt_gkg_geojson",
      "themes": [
        "CEASEFIRE",
        "WB_2748_EMPLOYMENT",
        "USPEC_POLICY1",
        "EPU_ECONOMY",
        "EPU_ECONOMY_HISTORIC",
        "ECON_INFLATION",
        "WB_1104_MACROECONOMIC_VULNERABILITY_AND_DEBT",
        "WB_442_INFLATION",
        "ECON_REMITTANCE",
        "WB_775_TRADE_POLICY_AND_INTEGRATION",
        "WB_698_TRADE",
        "WB_780_TRADE_IN_SERVICES",
        "WB_783_TEMPORARY_MOVEMENT_OF_LABOR",
        "TAX_FNCACT_ECONOMISTS",
        "EPU_POLICY_POLICY",
        "EPU_POLICY_SPENDING"
      ]
    },
    {
      "title": "Philippine, Benguet, Philippines",
      "title_en": null,
      "source": "www.manilatimes.net",
      "url": "https://www.manilatimes.net/2026/05/28/business/top-business/ph-not-in-stagflation-mode-economists/2352904",
      "published_at": "",
      "language": null,
      "source_lang": null,
      "provider": "gdelt_gkg_geojson",
      "themes": [
        "ARMEDCONFLICT",
        "EPU_CATS_NATIONAL_SECURITY",
        "TAX_FNCACT_ANALYSTS",
        "USPEC_POLICY1",
        "EPU_ECONOMY",
        "EPU_ECONOMY_HISTORIC",
        "USPEC_POLICY1",
        "EPU_ECONOMY",
        "EPU_ECONOMY_HISTORIC",
        "ECON_INFLATION",
        "WB_1104_MACROECONOMIC_VULNERABILITY_AND_DEBT",
        "WB_442_INFLATION",
        "EDUCATION",
        "SOC_POINTSOFINTEREST_UNIVERSITY"
      ]
    },
    {
      "title": "Albania",
      "title_en": null,
      "source": "sot.com.al",
      "url": "https://sot.com.al/ekonomia/eurostat-72-4-milione-qytetare-ne-be-ne-rrezik-varferie-publikohen-te-dhenat-dhe-per-shqiperine/",
      "published_at": "",
      "language": null,
      "source_lang": null,
      "provider": "gdelt_gkg_geojson",
      "themes": [
        "TAX_ETHNICITY_ALBANIAN",
        "TAX_WORLDLANGUAGES_ALBANIAN",
        "POVERTY",
        "WB_695_POVERTY",
        "TAX_FNCACT_CHILDREN",
        "TAX_FNCACT_CHILDREN",
        "TAX_FNCACT_CHILDREN",
        "TAX_ETHNICITY_ALBANIANS",
        "TAX_WORLDLANGUAGES_ALBANIANS",
        "WB_2745_JOB_QUALITY_AND_LABOR_MARKET_PERFORMANCE",
        "WB_2670_JOBS",
        "WB_2689_JOBS_DIAGNOSTICS",
        "WB_2748_EMPLOYMENT",
        "TAX_ECON_PRICE"
      ]
    },
    {
      "title": "Brooklyn, Michigan, United States",
      "title_en": null,
      "source": "www.funkytaurusmedia.com",
      "url": "https://www.funkytaurusmedia.com/product_info.php?info=p50_funky-taurus-----george-clinton-----ufo-brooklyn---------exclusiv.html&XTCsid=d377jdf4e4cqn6vhksojim0r96",
      "published_at": "",
      "language": null,
      "source_lang": null,
      "provider": "gdelt_gkg_geojson",
      "themes": [
        "CRISISLEX_CRISISLEXREC",
        "CRISISLEX_T02_INJURED",
        "EPU_ECONOMY_HISTORIC",
        "ECON_WORLDCURRENCIES_DOLLAR",
        "KILL",
        "CRISISLEX_T03_DEAD",
        "WB_678_DIGITAL_GOVERNMENT",
        "WB_694_BROADCAST_AND_MEDIA",
        "WB_133_INFORMATION_AND_COMMUNICATION_TECHNOLOGIES",
        "WB_678_DIGITAL_GOVERNMENT",
        "WB_694_BROADCAST_AND_MEDIA",
        "WB_133_INFORMATION_AND_COMMUNICATION_TECHNOLOGIES"
      ]
    },
    {
      "title": "Vietnam",
      "title_en": null,
      "source": "www.businesstimes.com.sg",
      "url": "https://www.businesstimes.com.sg/esg/global-clean-energy-manufacturing-supply-far-exceeds-demand",
      "published_at": "",
      "language": null,
      "source_lang": null,
      "provider": "gdelt_gkg_geojson",
      "themes": [
        "ARMEDCONFLICT",
        "EPU_CATS_NATIONAL_SECURITY",
        "WB_1921_PRIVATE_SECTOR_DEVELOPMENT",
        "WB_346_COMPETITIVE_INDUSTRIES",
        "WB_818_INDUSTRY_POLICY_AND_REAL_SECTORS",
        "WB_1281_MANUFACTURING",
        "WB_1921_PRIVATE_SECTOR_DEVELOPMENT",
        "WB_346_COMPETITIVE_INDUSTRIES",
        "WB_818_INDUSTRY_POLICY_AND_REAL_SECTORS",
        "WB_1281_MANUFACTURING",
        "FUELPRICES",
        "TAX_ECON_PRICE",
        "ENV_OIL",
        "TAX_ECON_PRICE",
        "ECON_OILPRICE",
        "TAX_ECON_PRICE",
        "WB_1458_HEALTH_PROMOTION_AND_DISEASE_PREVENTION",
        "WB_1462_WATER_SANITATION_AND_HYGIENE",
        "WB_635_PUBLIC_HEALTH",
        "WB_621_HEALTH_NUTRITION_AND_POPULATION",
        "WB_1458_HEALTH_PROMOTION_AND_DISEASE_PREVENTION",
        "WB_1462_WATER_SANITATION_AND_HYGIENE",
        "WB_635_PUBLIC_HEALTH",
        "WB_621_HEALTH_NUTRITION_AND_POPULATION",
        "USPEC_POLICY1",
        "ENV_GREEN",
        "WB_507_ENERGY_AND_EXTRACTIVES",
        "WB_525_RENEWABLE_ENERGY",
        "UNGP_FORESTS_RIVERS_OCEANS"
      ]
    },
    {
      "title": "Laos",
      "title_en": null,
      "source": "www.businesstimes.com.sg",
      "url": "https://www.businesstimes.com.sg/esg/global-clean-energy-manufacturing-supply-far-exceeds-demand",
      "published_at": "",
      "language": null,
      "source_lang": null,
      "provider": "gdelt_gkg_geojson",
      "themes": [
        "ARMEDCONFLICT",
        "EPU_CATS_NATIONAL_SECURITY",
        "WB_1921_PRIVATE_SECTOR_DEVELOPMENT",
        "WB_346_COMPETITIVE_INDUSTRIES",
        "WB_818_INDUSTRY_POLICY_AND_REAL_SECTORS",
        "WB_1281_MANUFACTURING",
        "WB_1921_PRIVATE_SECTOR_DEVELOPMENT",
        "WB_346_COMPETITIVE_INDUSTRIES",
        "WB_818_INDUSTRY_POLICY_AND_REAL_SECTORS",
        "WB_1281_MANUFACTURING",
        "FUELPRICES",
        "TAX_ECON_PRICE",
        "ENV_OIL",
        "TAX_ECON_PRICE",
        "ECON_OILPRICE",
        "TAX_ECON_PRICE",
        "WB_1458_HEALTH_PROMOTION_AND_DISEASE_PREVENTION",
        "WB_1462_WATER_SANITATION_AND_HYGIENE",
        "WB_635_PUBLIC_HEALTH",
        "WB_621_HEALTH_NUTRITION_AND_POPULATION",
        "WB_1458_HEALTH_PROMOTION_AND_DISEASE_PREVENTION",
        "WB_1462_WATER_SANITATION_AND_HYGIENE",
        "WB_635_PUBLIC_HEALTH",
        "WB_621_HEALTH_NUTRITION_AND_POPULATION",
        "USPEC_POLICY1",
        "ENV_GREEN",
        "WB_507_ENERGY_AND_EXTRACTIVES",
        "WB_525_RENEWABLE_ENERGY",
        "UNGP_FORESTS_RIVERS_OCEANS"
      ]
    },
    {
      "title": "China",
      "title_en": null,
      "source": "www.businesstimes.com.sg",
      "url": "https://www.businesstimes.com.sg/esg/global-clean-energy-manufacturing-supply-far-exceeds-demand",
      "published_at": "",
      "language": null,
      "source_lang": null,
      "provider": "gdelt_gkg_geojson",
      "themes": [
        "ARMEDCONFLICT",
        "EPU_CATS_NATIONAL_SECURITY",
        "WB_1921_PRIVATE_SECTOR_DEVELOPMENT",
        "WB_346_COMPETITIVE_INDUSTRIES",
        "WB_818_INDUSTRY_POLICY_AND_REAL_SECTORS",
        "WB_1281_MANUFACTURING",
        "FUELPRICES",
        "TAX_ECON_PRICE",
        "ENV_OIL",
        "TAX_ECON_PRICE",
        "ECON_OILPRICE",
        "ENV_SOLAR",
        "WB_529_WIND_ENERGY",
        "WB_1458_HEALTH_PROMOTION_AND_DISEASE_PREVENTION",
        "WB_1462_WATER_SANITATION_AND_HYGIENE",
        "WB_635_PUBLIC_HEALTH",
        "WB_621_HEALTH_NUTRITION_AND_POPULATION",
        "ENV_GREEN",
        "WB_507_ENERGY_AND_EXTRACTIVES",
        "WB_525_RENEWABLE_ENERGY",
        "UNGP_FORESTS_RIVERS_OCEANS"
      ]
    },
    {
      "title": "Cambodia",
      "title_en": null,
      "source": "www.businesstimes.com.sg",
      "url": "https://www.businesstimes.com.sg/esg/global-clean-energy-manufacturing-supply-far-exceeds-demand",
      "published_at": "",
      "language": null,
      "source_lang": null,
      "provider": "gdelt_gkg_geojson",
      "themes": [
        "ARMEDCONFLICT",
        "EPU_CATS_NATIONAL_SECURITY",
        "WB_1921_PRIVATE_SECTOR_DEVELOPMENT",
        "WB_346_COMPETITIVE_INDUSTRIES",
        "WB_818_INDUSTRY_POLICY_AND_REAL_SECTORS",
        "WB_1281_MANUFACTURING",
        "FUELPRICES",
        "TAX_ECON_PRICE",
        "ENV_OIL",
        "TAX_ECON_PRICE",
        "ECON_OILPRICE",
        "TAX_ECON_PRICE",
        "WB_1458_HEALTH_PROMOTION_AND_DISEASE_PREVENTION",
        "WB_1462_WATER_SANITATION_AND_HYGIENE",
        "WB_635_PUBLIC_HEALTH",
        "WB_621_HEALTH_NUTRITION_AND_POPULATION",
        "WB_1458_HEALTH_PROMOTION_AND_DISEASE_PREVENTION",
        "WB_1462_WATER_SANITATION_AND_HYGIENE",
        "WB_635_PUBLIC_HEALTH",
        "WB_621_HEALTH_NUTRITION_AND_POPULATION",
        "USPEC_POLICY1",
        "ENV_GREEN",
        "WB_507_ENERGY_AND_EXTRACTIVES",
        "WB_525_RENEWABLE_ENERGY",
        "UNGP_FORESTS_RIVERS_OCEANS"
      ]
    },
    {
      "title": "Turkey",
      "title_en": null,
      "source": "www.businesstimes.com.sg",
      "url": "https://www.businesstimes.com.sg/esg/global-clean-energy-manufacturing-supply-far-exceeds-demand",
      "published_at": "",
      "language": null,
      "source_lang": null,
      "provider": "gdelt_gkg_geojson",
      "themes": [
        "WB_1921_PRIVATE_SECTOR_DEVELOPMENT",
        "WB_346_COMPETITIVE_INDUSTRIES",
        "WB_818_INDUSTRY_POLICY_AND_REAL_SECTORS",
        "WB_1281_MANUFACTURING",
        "TAX_ECON_PRICE",
        "ENV_SOLAR",
        "ENV_SOLAR",
        "ENV_SOLAR",
        "WB_1458_HEALTH_PROMOTION_AND_DISEASE_PREVENTION",
        "WB_1462_WATER_SANITATION_AND_HYGIENE",
        "WB_635_PUBLIC_HEALTH",
        "WB_621_HEALTH_NUTRITION_AND_POPULATION",
        "USPEC_POLICY1"
      ]
    },
    {
      "title": "Romania",
      "title_en": null,
      "source": "www.9am.ro",
      "url": "https://www.9am.ro/stiri/Recomandari/369765/Romania-pierde-1-din-6-tineri-din-sistem-Piata-muncii-achita-nota-de-plata.html",
      "published_at": "",
      "language": null,
      "source_lang": null,
      "provider": "gdelt_gkg_geojson",
      "themes": [
        "TAX_ECON_PRICE",
        "USPEC_POLICY1",
        "EPU_ECONOMY",
        "EPU_ECONOMY_HISTORIC",
        "WB_2745_JOB_QUALITY_AND_LABOR_MARKET_PERFORMANCE",
        "WB_2748_EMPLOYMENT",
        "EDUCATION",
        "MANMADE_DISASTER_IMPLIED",
        "SOC_POINTSOFINTEREST_SCHOOL",
        "EDUCATION",
        "MANMADE_DISASTER_IMPLIED",
        "SOC_POINTSOFINTEREST_SCHOOL",
        "EDUCATION",
        "MANMADE_DISASTER_IMPLIED",
        "SOC_POINTSOFINTEREST_SCHOOL",
        "EDUCATION",
        "MANMADE_DISASTER_IMPLIED",
        "SOC_POINTSOFINTEREST_SCHOOL",
        "SOC_POINTSOFINTEREST_HIGH_SCHOOL",
        "SOC_POINTSOFINTEREST_UNIVERSITY",
        "TAX_FNCACT_STUDENT",
        "TAX_ETHNICITY_ROMANIAN",
        "TAX_WORLDLANGUAGES_ROMANIAN",
        "WB_470_EDUCATION"
      ]
    },
    {
      "title": "Bucharest, Bucuresti, Romania",
      "title_en": null,
      "source": "www.9am.ro",
      "url": "https://www.9am.ro/stiri/Recomandari/369765/Romania-pierde-1-din-6-tineri-din-sistem-Piata-muncii-achita-nota-de-plata.html",
      "published_at": "",
      "language": null,
      "source_lang": null,
      "provider": "gdelt_gkg_geojson",
      "themes": [
        "TAX_ECON_PRICE",
        "USPEC_POLICY1",
        "EPU_ECONOMY",
        "EPU_ECONOMY_HISTORIC",
        "WB_2745_JOB_QUALITY_AND_LABOR_MARKET_PERFORMANCE",
        "WB_2748_EMPLOYMENT",
        "EDUCATION",
        "MANMADE_DISASTER_IMPLIED",
        "SOC_POINTSOFINTEREST_SCHOOL",
        "EDUCATION",
        "MANMADE_DISASTER_IMPLIED",
        "SOC_POINTSOFINTEREST_SCHOOL",
        "EDUCATION",
        "MANMADE_DISASTER_IMPLIED",
        "SOC_POINTSOFINTEREST_SCHOOL",
        "EDUCATION",
        "MANMADE_DISASTER_IMPLIED",
        "SOC_POINTSOFINTEREST_SCHOOL",
        "SOC_POINTSOFINTEREST_HIGH_SCHOOL",
        "SOC_POINTSOFINTEREST_UNIVERSITY",
        "TAX_FNCACT_STUDENT",
        "TAX_ETHNICITY_ROMANIAN",
        "TAX_WORLDLANGUAGES_ROMANIAN",
        "WB_470_EDUCATION"
      ]
    },
    {
      "title": "Tehran, Tehran, Iran",
      "title_en": null,
      "source": "news.bg",
      "url": "https://news.bg/world/sasht-iranskiyat-doklad-otnosno-eventualna-ramka-za-sporazumenie-e-palna-izmislitsa.html",
      "published_at": "",
      "language": null,
      "source_lang": null,
      "provider": "gdelt_gkg_geojson",
      "themes": [
        "ECON_MOU",
        "ECON_MOU",
        "MEDIA_MSM",
        "MEDIA_MSM",
        "WB_2433_CONFLICT_AND_VIOLENCE",
        "WB_2432_FRAGILITY_CONFLICT_AND_VIOLENCE"
      ]
    },
    {
      "title": "Hungary",
      "title_en": null,
      "source": "www.vg.hu",
      "url": "https://www.vg.hu/negyzetmeter/2026/05/ingatlanfejlesztesi-hullam-energiavalsag-kivaras",
      "published_at": "",
      "language": null,
      "source_lang": null,
      "provider": "gdelt_gkg_geojson",
      "themes": [
        "MEDIA_SOCIAL",
        "ECON_HOUSING_PRICES",
        "WB_678_DIGITAL_GOVERNMENT",
        "WB_694_BROADCAST_AND_MEDIA",
        "WB_133_INFORMATION_AND_COMMUNICATION_TECHNOLOGIES",
        "USPEC_POLICY1",
        "EPU_ECONOMY",
        "EPU_ECONOMY_HISTORIC",
        "WB_696_PUBLIC_SECTOR_MANAGEMENT",
        "WB_2048_COMPENSATION_CAREERS_AND_INCENTIVES",
        "WB_723_PUBLIC_ADMINISTRATION",
        "WB_724_HUMAN_RESOURCES_FOR_PUBLIC_SECTOR"
      ]
    },
    {
      "title": "Portugal",
      "title_en": null,
      "source": "jornaleconomico.sapo.pt",
      "url": "https://jornaleconomico.sapo.pt/noticias/europa-tem-de-impedir-os-outros-blocos-de-liderar-o-desenvolvimento-global/",
      "published_at": "",
      "language": null,
      "source_lang": null,
      "provider": "gdelt_gkg_geojson",
      "themes": [
        "MARITIME",
        "EPU_ECONOMY",
        "EPU_ECONOMY_HISTORIC",
        "WB_471_ECONOMIC_GROWTH",
        "TAX_ETHNICITY_PORTUGUESE",
        "TAX_WORLDLANGUAGES_PORTUGUESE",
        "TAX_ETHNICITY_PORTUGUESE",
        "TAX_WORLDLANGUAGES_PORTUGUESE"
      ]
    },
    {
      "title": "Ethiopia",
      "title_en": null,
      "source": "www.laosnews.net",
      "url": "http://www.laosnews.net/news/279079921/ethiopia-opens-new-regional-airport",
      "published_at": "",
      "language": null,
      "source_lang": null,
      "provider": "gdelt_gkg_geojson",
      "themes": [
        "SOC_POINTSOFINTEREST_AIRPORT",
        "WB_135_TRANSPORT",
        "WB_1803_TRANSPORT_INFRASTRUCTURE",
        "WB_1804_AIRPORTS",
        "SOC_POINTSOFINTEREST_AIRPORT",
        "WB_135_TRANSPORT",
        "WB_1803_TRANSPORT_INFRASTRUCTURE",
        "WB_1804_AIRPORTS",
        "TAX_WORLDLANGUAGES_ETHIOPIAN",
        "TAX_WORLDLANGUAGES_ETHIOPIAN",
        "MARITIME",
        "TAX_FNCACT_MINISTER",
        "LEADER",
        "TAX_FNCACT_PRIME_MINISTER",
        "EPU_ECONOMY",
        "EPU_ECONOMY_HISTORIC"
      ]
    },
    {
      "title": "United Kingdom",
      "title_en": null,
      "source": "www.vedomosti.ru",
      "url": "https://www.vedomosti.ru/politics/news/2026/05/27/1200676-velikobritaniya-polsha-soglashenie",
      "published_at": "",
      "language": null,
      "source_lang": null,
      "provider": "gdelt_gkg_geojson",
      "themes": [
        "CRISISLEX_C07_SAFETY",
        "ALLIANCE",
        "CRISISLEX_CRISISLEXREC",
        "TAX_ETHNICITY_RUSSIAN",
        "TAX_WORLDLANGUAGES_RUSSIAN",
        "WB_2670_JOBS",
        "WB_2769_JOBS_STRATEGIES",
        "WB_2840_INTEGRATION",
        "WB_2836_MIGRATION_POLICIES_AND_JOBS",
        "USPEC_POLICY1",
        "EPU_ECONOMY",
        "EPU_ECONOMY_HISTORIC"
      ]
    },
    {
      "title": "Kiev, Ukraine (General), Ukraine",
      "title_en": null,
      "source": "www.vedomosti.ru",
      "url": "https://www.vedomosti.ru/politics/news/2026/05/27/1200676-velikobritaniya-polsha-soglashenie",
      "published_at": "",
      "language": null,
      "source_lang": null,
      "provider": "gdelt_gkg_geojson",
      "themes": [
        "GENERAL_GOVERNMENT",
        "EPU_POLICY_GOVERNMENT",
        "ENV_NUCLEARPOWER",
        "WB_508_POWER_SYSTEMS",
        "WB_509_NUCLEAR_ENERGY",
        "WB_507_ENERGY_AND_EXTRACTIVES",
        "CRISISLEX_C07_SAFETY",
        "CRISISLEX_CRISISLEXREC",
        "TAX_ETHNICITY_RUSSIAN",
        "TAX_WORLDLANGUAGES_RUSSIAN",
        "WB_2670_JOBS",
        "WB_2769_JOBS_STRATEGIES",
        "WB_2840_INTEGRATION",
        "WB_2836_MIGRATION_POLICIES_AND_JOBS",
        "USPEC_POLICY1",
        "EPU_ECONOMY",
        "EPU_ECONOMY_HISTORIC"
      ]
    },
    {
      "title": "Denmark",
      "title_en": null,
      "source": "hnonline.sk",
      "url": "https://hnonline.sk/svet/96283417-sme-v-priestore-medzi-mierom-a-vojnou-sefka-britskych-kyberspionov-vini-rusko-z-hybridnych-utokov",
      "published_at": "",
      "language": null,
      "source_lang": null,
      "provider": "gdelt_gkg_geojson",
      "themes": [
        "ARMEDCONFLICT",
        "EPU_CATS_NATIONAL_SECURITY",
        "TAX_WORLDLANGUAGES_RUSSIA",
        "TAX_WORLDLANGUAGES_RUSSIA",
        "TAX_ECON_PRICE",
        "WB_161_DAMS_AND_RESERVOIRS",
        "WB_141_WATER_RESOURCES_MANAGEMENT",
        "WB_1000_WATER_MANAGEMENT_STRUCTURES",
        "CRISISLEX_T04_INFRASTRUCTURE"
      ]
    },
    {
      "title": "Poland",
      "title_en": null,
      "source": "hnonline.sk",
      "url": "https://hnonline.sk/svet/96283417-sme-v-priestore-medzi-mierom-a-vojnou-sefka-britskych-kyberspionov-vini-rusko-z-hybridnych-utokov",
      "published_at": "",
      "language": null,
      "source_lang": null,
      "provider": "gdelt_gkg_geojson",
      "themes": [
        "ARMEDCONFLICT",
        "EPU_CATS_NATIONAL_SECURITY",
        "TAX_WORLDLANGUAGES_RUSSIA",
        "TAX_WORLDLANGUAGES_RUSSIA",
        "TAX_ECON_PRICE",
        "WB_161_DAMS_AND_RESERVOIRS",
        "WB_141_WATER_RESOURCES_MANAGEMENT",
        "WB_1000_WATER_MANAGEMENT_STRUCTURES",
        "CRISISLEX_T04_INFRASTRUCTURE"
      ]
    },
    {
      "title": "Krasnoborsk, Arkhangel'skaya Oblast', Russia",
      "title_en": null,
      "source": "www.theguardian.com",
      "url": "https://www.theguardian.com/film/2026/may/27/russian-director-andrey-zvyagintsev-makes-appeal-to-putin",
      "published_at": "",
      "language": null,
      "source_lang": null,
      "provider": "gdelt_gkg_geojson",
      "themes": [
        "TAX_DISEASE_INFECTION",
        "ARMEDCONFLICT",
        "EPU_CATS_NATIONAL_SECURITY",
        "TAX_FNCACT_BUSINESS_EXECUTIVE",
        "TAX_FNCACT_EXECUTIVE",
        "TAX_ETHNICITY_RUSSIAN",
        "TAX_WORLDLANGUAGES_RUSSIAN",
        "TAX_WORLDLANGUAGES_RUSSIA",
        "TAX_FNCACT_EMPLOYEES",
        "EPU_ECONOMY_HISTORIC",
        "TAX_DISEASE_COVID_19"
      ]
    },
    {
      "title": "Texas, United States",
      "title_en": null,
      "source": "www.mediaite.com",
      "url": "https://www.mediaite.com/media/tv/jesus-christ-cnn-table-erupts-in-laughter-over-stray-penile-reference/",
      "published_at": "",
      "language": null,
      "source_lang": null,
      "provider": "gdelt_gkg_geojson",
      "themes": [
        "MEDIA_MSM",
        "EXTREMISM",
        "TAX_ECON_PRICE",
        "FUELPRICES",
        "ECON_GASOLINEPRICE",
        "ECON_HEATINGOIL",
        "ELECTION"
      ]
    },
    {
      "title": "Presevo, 00, Serbia",
      "title_en": null,
      "source": "naslovi.net",
      "url": "https://naslovi.net/2026-05-27/vreme/hapsenja-po-srbiji-zbog-utaje-poreza-i-pranja-novca/41874140",
      "published_at": "",
      "language": null,
      "source_lang": null,
      "provider": "gdelt_gkg_geojson",
      "themes": [
        "SOC_GENERALCRIME",
        "SOC_GENERALCRIME",
        "ECON_TAXATION",
        "USPEC_POLICY1",
        "EPU_POLICY_TAX",
        "EPU_CATS_TAXES",
        "ECON_TAXATION",
        "USPEC_POLICY1",
        "EPU_POLICY_TAX",
        "EPU_CATS_TAXES",
        "ECON_TAXATION",
        "USPEC_POLICY1",
        "EPU_POLICY_TAX",
        "EPU_CATS_TAXES",
        "ECON_TAXATION",
        "USPEC_POLICY1",
        "EPU_POLICY_TAX",
        "EPU_CATS_TAXES",
        "KILL",
        "EPU_ECONOMY",
        "EPU_ECONOMY_HISTORIC",
        "EPU_ECONOMY",
        "EPU_ECONOMY_HISTORIC",
        "WB_2670_JOBS",
        "WB_1467_EDUCATION_FOR_ALL",
        "WB_470_EDUCATION",
        "WB_2131_EMPLOYABILITY_SKILLS_AND_JOBS",
        "WB_1484_EDUCATION_SKILLS_DEVELOPMENT_AND_LABOR_MARKET",
        "TAX_FNCACT_CRIMINAL",
        "TAX_FNCACT_CRIMINAL",
        "SECURITY_SERVICES",
        "TAX_FNCACT_POLICE",
        "CRISISLEX_C07_SAFETY",
        "CORRUPTION",
        "WB_2019_ANTI_CORRUPTION_LEGISLATION",
        "WB_696_PUBLIC_SECTOR_MANAGEMENT",
        "WB_831_GOVERNANCE",
        "WB_832_ANTI_CORRUPTION",
        "WB_2020_BRIBERY_FRAUD_AND_COLLUSION",
        "CORRUPTION",
        "WB_2019_ANTI_CORRUPTION_LEGISLATION",
        "WB_696_PUBLIC_SECTOR_MANAGEMENT",
        "WB_831_GOVERNANCE",
        "WB_832_ANTI_CORRUPTION",
        "WB_2020_BRIBERY_FRAUD_AND_COLLUSION"
      ]
    },
    {
      "title": "Serbia",
      "title_en": null,
      "source": "naslovi.net",
      "url": "https://naslovi.net/2026-05-27/vreme/hapsenja-po-srbiji-zbog-utaje-poreza-i-pranja-novca/41874140",
      "published_at": "",
      "language": null,
      "source_lang": null,
      "provider": "gdelt_gkg_geojson",
      "themes": [
        "SOC_GENERALCRIME",
        "SOC_GENERALCRIME",
        "ECON_TAXATION",
        "USPEC_POLICY1",
        "EPU_POLICY_TAX",
        "EPU_CATS_TAXES",
        "ECON_TAXATION",
        "USPEC_POLICY1",
        "EPU_POLICY_TAX",
        "EPU_CATS_TAXES",
        "ECON_TAXATION",
        "USPEC_POLICY1",
        "EPU_POLICY_TAX",
        "EPU_CATS_TAXES",
        "KILL",
        "WB_2670_JOBS",
        "WB_1467_EDUCATION_FOR_ALL",
        "WB_470_EDUCATION",
        "WB_2131_EMPLOYABILITY_SKILLS_AND_JOBS",
        "WB_1484_EDUCATION_SKILLS_DEVELOPMENT_AND_LABOR_MARKET",
        "ARREST",
        "CRISISLEX_CRISISLEXREC",
        "TAX_FNCACT_CRIMINAL",
        "SECURITY_SERVICES",
        "TAX_FNCACT_POLICE",
        "CRISISLEX_C07_SAFETY",
        "CORRUPTION",
        "WB_2019_ANTI_CORRUPTION_LEGISLATION",
        "WB_696_PUBLIC_SECTOR_MANAGEMENT",
        "WB_831_GOVERNANCE",
        "WB_832_ANTI_CORRUPTION",
        "WB_2020_BRIBERY_FRAUD_AND_COLLUSION"
      ]
    },
    {
      "title": "Vermont, United States",
      "title_en": null,
      "source": "www.mississippivalleypublishing.com",
      "url": "https://www.mississippivalleypublishing.com/daily_democrat/daily_democrat/data-center-battles-started-in-the-states-now-it-s-congress-under-siege/article_5c3b17a5-3099-4154-b2b0-5b80dc8cdb79.html",
      "published_at": "",
      "language": null,
      "source_lang": null,
      "provider": "gdelt_gkg_geojson",
      "themes": [
        "LEGISLATION",
        "EPU_POLICY_LEGISLATION",
        "EPU_ECONOMY",
        "AFFECT",
        "TAX_FNCACT_REGULATORS",
        "TAX_FNCACT_WORKERS"
      ]
    },
    {
      "title": "Alexandria, Al Iskandariyah, Egypt",
      "title_en": null,
      "source": "www.mississippivalleypublishing.com",
      "url": "https://www.mississippivalleypublishing.com/daily_democrat/daily_democrat/data-center-battles-started-in-the-states-now-it-s-congress-under-siege/article_5c3b17a5-3099-4154-b2b0-5b80dc8cdb79.html",
      "published_at": "",
      "language": null,
      "source_lang": null,
      "provider": "gdelt_gkg_geojson",
      "themes": [
        "LEGISLATION",
        "EPU_POLICY_LEGISLATION",
        "EPU_POLICY_GOVERNMENT",
        "EPU_ECONOMY",
        "AFFECT",
        "TAX_FNCACT_REGULATORS",
        "TAX_FNCACT_WORKERS"
      ]
    },
    {
      "title": "Environmental Protection Agency, District Of Columbia, United States",
      "title_en": null,
      "source": "www.mississippivalleypublishing.com",
      "url": "https://www.mississippivalleypublishing.com/daily_democrat/daily_democrat/data-center-battles-started-in-the-states-now-it-s-congress-under-siege/article_5c3b17a5-3099-4154-b2b0-5b80dc8cdb79.html",
      "published_at": "",
      "language": null,
      "source_lang": null,
      "provider": "gdelt_gkg_geojson",
      "themes": [
        "TAX_ETHNICITY_AMERICANS",
        "EPU_POLICY_POLITICAL",
        "LEADER",
        "TAX_FNCACT_LAWMAKERS",
        "EPU_POLICY_LAWMAKERS",
        "EPU_ECONOMY_HISTORIC",
        "EPU_CATS_REGULATION",
        "UNGP_FORESTS_RIVERS_OCEANS",
        "GENERAL_GOVERNMENT",
        "USPEC_POLITICS_GENERAL1",
        "EPU_POLICY_CONGRESS"
      ]
    },
    {
      "title": "Smackover, Arkansas, United States",
      "title_en": null,
      "source": "www.magnoliareporter.com",
      "url": "https://www.magnoliareporter.com/news_and_business/mike_mcneills_diary/article_fd161eeb-05cb-4df3-b0e1-762724a22d12.html",
      "published_at": "",
      "language": null,
      "source_lang": null,
      "provider": "gdelt_gkg_geojson",
      "themes": [
        "EPU_ECONOMY_HISTORIC"
      ]
    },
    {
      "title": "Lafayette, Louisiana, United States",
      "title_en": null,
      "source": "www.magnoliareporter.com",
      "url": "https://www.magnoliareporter.com/news_and_business/mike_mcneills_diary/article_fd161eeb-05cb-4df3-b0e1-762724a22d12.html",
      "published_at": "",
      "language": null,
      "source_lang": null,
      "provider": "gdelt_gkg_geojson",
      "themes": [
        "EPU_ECONOMY_HISTORIC",
        "SOC_POINTSOFINTEREST_SCHOOL",
        "SOC_POINTSOFINTEREST_HIGH_SCHOOL"
      ]
    },
    {
      "title": "Norway",
      "title_en": null,
      "source": "www.fool.com",
      "url": "https://www.fool.com/investing/2026/05/27/is-the-cheapest-cruise-line-stock-finally-too-chea/?source=iedfolrf0000001",
      "published_at": "",
      "language": null,
      "source_lang": null,
      "provider": "gdelt_gkg_geojson",
      "themes": [
        "TAX_FNCACT_OPERATOR",
        "TAX_MILITARY_TITLE_CAPTAIN",
        "TAX_FNCACT_CAPTAIN",
        "TAX_FNCACT_CEO",
        "EPU_ECONOMY_HISTORIC",
        "TAX_FNCACT_PERFORMER",
        "TAX_WORLDLANGUAGES_NORWEGIAN"
      ]
    },
    {
      "title": "Kenya",
      "title_en": null,
      "source": "www.fltimes.com",
      "url": "https://www.fltimes.com/news/the-scoop-on-poop-cornell-helping-develop-fertilizer-from-human-waste-in-africa/article_d78f39df-55f0-4592-8a0e-65a4a65ac3fa.html",
      "published_at": "",
      "language": null,
      "source_lang": null,
      "provider": "gdelt_gkg_geojson",
      "themes": [
        "GENERAL_HEALTH",
        "UNGP_FORESTS_RIVERS_OCEANS",
        "EDUCATION",
        "SOC_POINTSOFINTEREST_UNIVERSITY",
        "WB_2936_GOLD",
        "WB_507_ENERGY_AND_EXTRACTIVES",
        "WB_895_MINING_SYSTEMS",
        "WB_1699_METAL_ORE_MINING",
        "SCIENCE",
        "AGRICULTURE",
        "TAX_FNCACT_FARMERS",
        "SANITATION",
        "WB_137_WATER",
        "WB_139_SANITATION_AND_WASTEWATER",
        "WB_2000_SANITATION",
        "WB_1199_WATER_SUPPLY_AND_SANITATION",
        "CRISISLEX_C06_WATER_SANITATION",
        "WB_1968_CROP_SELECTION_AND_PRODUCTION",
        "TAX_WORLDMAMMALS_HUMAN",
        "WB_175_FERTILIZERS",
        "WB_174_CROP_PRODUCTION",
        "WB_435_AGRICULTURE_AND_FOOD_SECURITY",
        "WB_1949_CLIMATE_SMART_AGRICULTURE",
        "WB_175_FERTILIZERS",
        "WB_174_CROP_PRODUCTION",
        "WB_435_AGRICULTURE_AND_FOOD_SECURITY",
        "WB_1949_CLIMATE_SMART_AGRICULTURE",
        "TAX_ECON_PRICE"
      ]
    },
    {
      "title": "Cagayan Valley, Philippines (General), Philippines",
      "title_en": null,
      "source": "www.manilatimes.net",
      "url": "https://www.manilatimes.net/2026/05/28/business/agribusiness/a-scary-perfect-storm-is-approaching/2352876",
      "published_at": "",
      "language": null,
      "source_lang": null,
      "provider": "gdelt_gkg_geojson",
      "themes": [
        "TAX_WORLDLANGUAGES_CAGAYAN",
        "TAX_WORLDLANGUAGES_CAGAYAN",
        "TAX_FNCACT_FARMERS",
        "TAX_FNCACT_FARMERS",
        "NATURAL_DISASTER_DROUGHTS",
        "EPU_ECONOMY",
        "EPU_ECONOMY_HISTORIC",
        "TAX_FOODSTAPLES_RICE",
        "TAX_FOODSTAPLES_RICE"
      ]
    },
    {
      "title": "Visayas, Philippines (General), Philippines",
      "title_en": null,
      "source": "www.manilatimes.net",
      "url": "https://www.manilatimes.net/2026/05/28/business/agribusiness/a-scary-perfect-storm-is-approaching/2352876",
      "published_at": "",
      "language": null,
      "source_lang": null,
      "provider": "gdelt_gkg_geojson",
      "themes": [
        "TAX_WORLDLANGUAGES_CAGAYAN",
        "TAX_WORLDLANGUAGES_CAGAYAN",
        "TAX_FNCACT_FARMERS",
        "NATURAL_DISASTER_DROUGHTS",
        "EPU_ECONOMY",
        "EPU_ECONOMY_HISTORIC",
        "TAX_FOODSTAPLES_RICE",
        "TAX_FOODSTAPLES_RICE"
      ]
    },
    {
      "title": "Prague, Praha, HlavníEsto, Czech Republic",
      "title_en": null,
      "source": "www.ansa.it",
      "url": "https://www.ansa.it/toscana/notizie/2026/05/27/disegno-e-dunque-sogno-mostra-omaggio-a-paolo-antonio-martini_d5c35130-7ca9-43e2-9d6c-ef33b475e96c.html",
      "published_at": "",
      "language": null,
      "source_lang": null,
      "provider": "gdelt_gkg_geojson",
      "themes": [
        "TOURISM",
        "TAX_FNCACT_TOURIST",
        "GENERAL_GOVERNMENT",
        "EPU_ECONOMY_HISTORIC",
        "TAX_FNCACT_MANUFACTURER",
        "TAX_ETHNICITY_CZECH",
        "TAX_WORLDLANGUAGES_CZECH"
      ]
    },
    {
      "title": "Saint Petersburg, Sankt-Peterburg, Russia",
      "title_en": null,
      "source": "www.ansa.it",
      "url": "https://www.ansa.it/toscana/notizie/2026/05/27/disegno-e-dunque-sogno-mostra-omaggio-a-paolo-antonio-martini_d5c35130-7ca9-43e2-9d6c-ef33b475e96c.html",
      "published_at": "",
      "language": null,
      "source_lang": null,
      "provider": "gdelt_gkg_geojson",
      "themes": [
        "GENERAL_GOVERNMENT",
        "EPU_ECONOMY_HISTORIC",
        "TAX_FNCACT_MANUFACTURER",
        "TAX_ETHNICITY_CZECH",
        "TAX_WORLDLANGUAGES_CZECH"
      ]
    },
    {
      "title": "Belfast, Belfast, United Kingdom",
      "title_en": null,
      "source": "www.yorkpress.co.uk",
      "url": "https://www.yorkpress.co.uk/news/national/26143534.stormont-executive-taking-steps-right-direction-despite-gbp1bn-hole-budget/",
      "published_at": "",
      "language": null,
      "source_lang": null,
      "provider": "gdelt_gkg_geojson",
      "themes": [
        "TAX_FNCACT_EXECUTIVE",
        "UNGP_FORESTS_RIVERS_OCEANS",
        "WB_678_DIGITAL_GOVERNMENT",
        "WB_694_BROADCAST_AND_MEDIA",
        "WB_133_INFORMATION_AND_COMMUNICATION_TECHNOLOGIES",
        "GENERAL_GOVERNMENT",
        "EPU_POLICY_GOVERNMENT",
        "USPEC_POLICY1",
        "EPU_ECONOMY",
        "EPU_ECONOMY_HISTORIC"
      ]
    },
    {
      "title": "Lough Neagh, United Kingdom (General), United Kingdom",
      "title_en": null,
      "source": "www.yorkpress.co.uk",
      "url": "https://www.yorkpress.co.uk/news/national/26143534.stormont-executive-taking-steps-right-direction-despite-gbp1bn-hole-budget/",
      "published_at": "",
      "language": null,
      "source_lang": null,
      "provider": "gdelt_gkg_geojson",
      "themes": [
        "WB_2433_CONFLICT_AND_VIOLENCE",
        "WB_2432_FRAGILITY_CONFLICT_AND_VIOLENCE",
        "UNGP_CRIME_VIOLENCE",
        "TAX_ETHNICITY_BLACK",
        "GENDER_VIOLENCE",
        "UNGP_GENDER_EQUALITY",
        "TAX_FNCACT_WOMEN",
        "GENERAL_HEALTH",
        "MEDICAL",
        "TAX_FNCACT_CHILDREN",
        "UNGP_FORESTS_RIVERS_OCEANS",
        "WB_678_DIGITAL_GOVERNMENT",
        "WB_694_BROADCAST_AND_MEDIA",
        "WB_133_INFORMATION_AND_COMMUNICATION_TECHNOLOGIES",
        "TAX_FNCACT_MINISTER",
        "TAX_FNCACT_MINISTER",
        "USPEC_POLICY1",
        "EPU_ECONOMY",
        "EPU_ECONOMY_HISTORIC",
        "TAX_FNCACT_DEPUTY"
      ]
    },
    {
      "title": "Genoa, Liguria, Italy",
      "title_en": null,
      "source": "www.genovatoday.it",
      "url": "https://www.genovatoday.it/economia/sotheby-immobiliare-lusso-apre.html",
      "published_at": "",
      "language": null,
      "source_lang": null,
      "provider": "gdelt_gkg_geojson",
      "themes": [
        "TAX_DISEASE_DIZZINESS",
        "ECON_HOUSING_PRICES",
        "TAX_FNCACT_QUEEN",
        "TAX_FNCACT_QUEEN",
        "WB_872_SMART_CITIES",
        "WB_813_URBAN_GOVERNANCE_AND_CITY_SYSTEMS",
        "WB_699_URBAN_DEVELOPMENT"
      ]
    },
    {
      "title": "Portofino, Liguria, Italy",
      "title_en": null,
      "source": "www.genovatoday.it",
      "url": "https://www.genovatoday.it/economia/sotheby-immobiliare-lusso-apre.html",
      "published_at": "",
      "language": null,
      "source_lang": null,
      "provider": "gdelt_gkg_geojson",
      "themes": [
        "TAX_DISEASE_DIZZINESS",
        "ECON_HOUSING_PRICES",
        "TAX_FNCACT_QUEEN",
        "TAX_FNCACT_QUEEN",
        "WB_872_SMART_CITIES",
        "WB_813_URBAN_GOVERNANCE_AND_CITY_SYSTEMS",
        "WB_699_URBAN_DEVELOPMENT"
      ]
    },
    {
      "title": "Armenia",
      "title_en": null,
      "source": "www.amic.ru",
      "url": "https://www.amic.ru/news/pashinyan-otvetil-na-ugrozu-rossii-prekratit-soglashenie-po-gazu-584736",
      "published_at": "",
      "language": null,
      "source_lang": null,
      "provider": "gdelt_gkg_geojson",
      "themes": [
        "TAX_FNCACT_AUTHORITIES",
        "CRISISLEX_CRISISLEXREC",
        "EPU_POLICY_AUTHORITIES",
        "TAX_ECON_PRICE",
        "TAX_ETHNICITY_RUSSIAN",
        "TAX_WORLDLANGUAGES_RUSSIAN",
        "GENERAL_GOVERNMENT",
        "EPU_POLICY_GOVERNMENT",
        "TAX_ETHNICITY_ARMENIAN",
        "TAX_WORLDLANGUAGES_ARMENIAN",
        "TAX_FNCACT_MINISTER"
      ]
    },
    {
      "title": "Roxboro, Quebec, Canada",
      "title_en": null,
      "source": "www.thesuburban.com",
      "url": "https://www.thesuburban.com/news/city_news/hampstead-welcomes-start-of-roadwork-on-ellerdale/article_ce79a888-8c8b-41a0-85a7-21db16befb85.html",
      "published_at": "",
      "language": null,
      "source_lang": null,
      "provider": "gdelt_gkg_geojson",
      "themes": [
        "TAX_ECON_PRICE"
      ]
    },
    {
      "title": "White House, District Of Columbia, United States",
      "title_en": null,
      "source": "www.wallstreet-online.de",
      "url": "https://www.wallstreet-online.de/nachricht/20930592-us-anleihen-leichte-kursgewinne",
      "published_at": "",
      "language": null,
      "source_lang": null,
      "provider": "gdelt_gkg_geojson",
      "themes": [
        "WB_678_DIGITAL_GOVERNMENT",
        "WB_694_BROADCAST_AND_MEDIA",
        "WB_133_INFORMATION_AND_COMMUNICATION_TECHNOLOGIES",
        "ECON_OILPRICE",
        "TAX_ECON_PRICE",
        "ENV_OIL",
        "TAX_ECON_PRICE",
        "EPU_POLICY_WHITE_HOUSE",
        "EPU_ECONOMY",
        "EPU_ECONOMY_HISTORIC",
        "EPU_ECONOMY",
        "EPU_ECONOMY_HISTORIC",
        "UNGP_FORESTS_RIVERS_OCEANS"
      ]
    },
    {
      "title": "Karnataka, Karnataka, India",
      "title_en": null,
      "source": "www.newkerala.com",
      "url": "https://www.newkerala.com/news/a/karnataka-cm-siddaramaiah-accepts-social-educational-survey-report-139.htm",
      "published_at": "",
      "language": null,
      "source_lang": null,
      "provider": "gdelt_gkg_geojson",
      "themes": [
        "TAX_FNCACT_CHIEF",
        "EPU_ECONOMY",
        "EPU_ECONOMY_HISTORIC",
        "TAX_FNCACT_MINISTER",
        "GENERAL_GOVERNMENT",
        "EPU_POLICY_GOVERNMENT",
        "USPEC_POLITICS_GENERAL1",
        "EPU_POLICY_CONGRESS"
      ]
    },
    {
      "title": "Tel Aviv, Tel Aviv, Israel",
      "title_en": null,
      "source": "www.finanznachrichten.de",
      "url": "https://www.finanznachrichten.de/nachrichten-2026-05/68609376-israel-corporation-ltd-israel-corp-reports-results-for-first-quarter-2026-008.htm",
      "published_at": "",
      "language": null,
      "source_lang": null,
      "provider": "gdelt_gkg_geojson",
      "themes": [
        "ECON_STOCKMARKET",
        "TAX_ETHNICITY_ENGLISH",
        "TAX_WORLDLANGUAGES_ENGLISH",
        "TAX_ETHNICITY_ENGLISH",
        "TAX_WORLDLANGUAGES_ENGLISH"
      ]
    },
    {
      "title": "Perugia, Umbria, Italy",
      "title_en": null,
      "source": "www.perugiatoday.it",
      "url": "https://www.perugiatoday.it/cronaca/rapina-due-donne-al-bancomat-a-processo-perugia.html",
      "published_at": "",
      "language": null,
      "source_lang": null,
      "provider": "gdelt_gkg_geojson",
      "themes": [
        "WB_696_PUBLIC_SECTOR_MANAGEMENT",
        "WB_2048_COMPENSATION_CAREERS_AND_INCENTIVES",
        "WB_723_PUBLIC_ADMINISTRATION",
        "WB_724_HUMAN_RESOURCES_FOR_PUBLIC_SECTOR",
        "TAX_FNCACT_VICTIM",
        "ECON_STOCKMARKET",
        "CONSTITUTIONAL",
        "TRIAL",
        "TAX_FNCACT_LAWYERS",
        "CRISISLEX_C05_NEED_OF_SHELTERS",
        "CRIME_COMMON_ROBBERY",
        "TAX_FNCACT_MAN",
        "SOC_GENERALCRIME",
        "ARREST",
        "CRISISLEX_CRISISLEXREC",
        "TAX_FNCACT_WOMEN",
        "TAX_FNCACT_WOMEN"
      ]
    },
    {
      "title": "Rome, Lazio, Italy",
      "title_en": null,
      "source": "hnonline.sk",
      "url": "https://hnonline.sk/finweb/zahranicna-ekonomika/96283415-sest-krajin-eu-vratane-slovenska-ziada-ochranu-pre-tazky-priemysel-treba-ho-udrzat-doma-tvrdi-cesky-minister",
      "published_at": "",
      "language": null,
      "source_lang": null,
      "provider": "gdelt_gkg_geojson",
      "themes": [
        "EPU_ECONOMY_HISTORIC",
        "EPU_ECONOMY_HISTORIC"
      ]
    },
    {
      "title": "Bulgaria",
      "title_en": null,
      "source": "hnonline.sk",
      "url": "https://hnonline.sk/finweb/zahranicna-ekonomika/96283415-sest-krajin-eu-vratane-slovenska-ziada-ochranu-pre-tazky-priemysel-treba-ho-udrzat-doma-tvrdi-cesky-minister",
      "published_at": "",
      "language": null,
      "source_lang": null,
      "provider": "gdelt_gkg_geojson",
      "themes": [
        "EPU_ECONOMY_HISTORIC"
      ]
    },
    {
      "title": "Czech Republic",
      "title_en": null,
      "source": "hnonline.sk",
      "url": "https://hnonline.sk/finweb/zahranicna-ekonomika/96283415-sest-krajin-eu-vratane-slovenska-ziada-ochranu-pre-tazky-priemysel-treba-ho-udrzat-doma-tvrdi-cesky-minister",
      "published_at": "",
      "language": null,
      "source_lang": null,
      "provider": "gdelt_gkg_geojson",
      "themes": [
        "EPU_ECONOMY_HISTORIC",
        "EPU_ECONOMY_HISTORIC"
      ]
    },
    {
      "title": "Sweden",
      "title_en": null,
      "source": "www.di.se",
      "url": "https://www.di.se/nyheter/mycket-spekulation-i-jakten-pa-nya-kursraketer/",
      "published_at": "",
      "language": null,
      "source_lang": null,
      "provider": "gdelt_gkg_geojson",
      "themes": [
        "SOC_EMERGINGTECH",
        "EPU_ECONOMY_HISTORIC",
        "TAX_WORLDLANGUAGES_SWEDISH",
        "TAX_FNCACT_DENTIST",
        "TAX_FNCACT_DENTIST",
        "UNGP_FORESTS_RIVERS_OCEANS",
        "WB_290_TELECOMMUNICATIONS_ORGANIZATIONAL_DESIGN",
        "WB_288_TELECOMMUNICATIONS_SECTOR_POLICY_AND_REGULATION",
        "WB_286_TELECOMMUNICATIONS_AND_BROADBAND_ACCESS",
        "WB_133_INFORMATION_AND_COMMUNICATION_TECHNOLOGIES"
      ]
    },
    {
      "title": "Bolivia",
      "title_en": null,
      "source": "www.ultimahora.com",
      "url": "https://www.ultimahora.com/lu-sapena-participo-como-coautora-del-libro-mujeres-de-legado-presentado-en-bolivia",
      "published_at": "",
      "language": null,
      "source_lang": null,
      "provider": "gdelt_gkg_geojson",
      "themes": [
        "ECON_ENTREPRENEURSHIP",
        "TAX_ETHNICITY_BOLIVIA",
        "TAX_ETHNICITY_BOLIVIA",
        "TAX_WORLDLANGUAGES_LATIN",
        "TAX_FNCACT_LEADERS",
        "TAX_FNCACT_WOMEN",
        "TAX_FNCACT_WOMEN",
        "TAX_FNCACT_WOMEN",
        "TAX_FNCACT_OFFICIAL"
      ]
    },
    {
      "title": "Pontevedra, Galicia, Spain",
      "title_en": null,
      "source": "www.diariosigloxxi.com",
      "url": "https://www.diariosigloxxi.com/texto-ep/mostrar/20260527182013/junta-iberpapel-aprueba-pago-dividendo-complementario-018-euros-8-junio",
      "published_at": "",
      "language": null,
      "source_lang": null,
      "provider": "gdelt_gkg_geojson",
      "themes": [
        "CORRUPTION",
        "WB_2019_ANTI_CORRUPTION_LEGISLATION",
        "WB_696_PUBLIC_SECTOR_MANAGEMENT",
        "WB_831_GOVERNANCE",
        "WB_832_ANTI_CORRUPTION",
        "WB_2020_BRIBERY_FRAUD_AND_COLLUSION",
        "TAX_WORLDMAMMALS_SEAL",
        "ECON_WORLDCURRENCIES_EUROS",
        "TAX_FNCACT_DISTRIBUTOR"
      ]
    },
    {
      "title": "Lisbon, Lisboa, Portugal",
      "title_en": null,
      "source": "omirante.pt",
      "url": "https://omirante.pt/nacional/2026-05-27-banco-de-portugal-anuncia-regras-mais-exigentes-no-credito-a-habitacao-0c33020e",
      "published_at": "",
      "language": null,
      "source_lang": null,
      "provider": "gdelt_gkg_geojson",
      "themes": [
        "LEADER",
        "TAX_FNCACT_GOVERNOR",
        "TAX_FNCACT_REGULATOR",
        "TAX_FNCACT_REGULATOR",
        "TAX_FNCACT_BOSS",
        "WB_1104_MACROECONOMIC_VULNERABILITY_AND_DEBT",
        "WB_450_DEBT",
        "WB_1098_MONETARY_AND_FINANCIAL_STABILITY",
        "WB_471_ECONOMIC_GROWTH",
        "WB_1096_MACROECONOMIC_SUSTAINABILITY",
        "WB_1100_SUSTAINABLE_GROWTH"
      ]
    },
    {
      "title": "Hualien County, Hualian Xian, Taiwan",
      "title_en": null,
      "source": "n.yam.com",
      "url": "https://n.yam.com/Article/20260527290105",
      "published_at": "",
      "language": null,
      "source_lang": null,
      "provider": "gdelt_gkg_geojson",
      "themes": [
        "USPEC_POLICY1",
        "EPU_POLICY_POLICY",
        "CRISISLEX_C07_SAFETY",
        "CRISISLEX_C07_SAFETY",
        "ECON_WORLDCURRENCIES_YUAN",
        "GENERAL_HEALTH",
        "CRISISLEX_C03_WELLBEING_HEALTH",
        "CRISISLEX_C03_WELLBEING_HEALTH",
        "CRISISLEX_C03_WELLBEING_HEALTH",
        "CRISISLEX_C03_WELLBEING_HEALTH",
        "TAX_FNCACT_SECRETARY",
        "TAX_FNCACT_MANAGER",
        "TAX_FNCACT_MANAGER",
        "MEDICAL",
        "SOC_POINTSOFINTEREST_HOSPITAL",
        "SOC_POINTSOFINTEREST_HOSPITAL",
        "TAX_WORLDMAMMALS_HUMAN"
      ]
    },
    {
      "title": "California, United States",
      "title_en": null,
      "source": "www.wcpo.com",
      "url": "https://www.wcpo.com/politics/billionaire-democrat-steyer-runs-nations-most-expensive-campaign-of-the-year",
      "published_at": "",
      "language": null,
      "source_lang": null,
      "provider": "gdelt_gkg_geojson",
      "themes": [
        "TAX_FNCACT_MANAGER",
        "TAX_FNCACT_FUND_MANAGER",
        "EPU_POLICY_POLITICAL",
        "MEDIA_MSM",
        "WB_678_DIGITAL_GOVERNMENT",
        "WB_694_BROADCAST_AND_MEDIA",
        "WB_133_INFORMATION_AND_COMMUNICATION_TECHNOLOGIES",
        "TAX_POLITICAL_PARTY_DEMOCRAT",
        "USPEC_POLITICS_GENERAL1",
        "PROTEST",
        "MOVEMENT_GENERAL",
        "TAX_FNCACT_ACTIVIST",
        "LEADER",
        "TAX_FNCACT_GOVERNOR",
        "TAX_ECON_PRICE"
      ]
    },
    {
      "title": "South Carolina, United States",
      "title_en": null,
      "source": "www.wcpo.com",
      "url": "https://www.wcpo.com/politics/billionaire-democrat-steyer-runs-nations-most-expensive-campaign-of-the-year",
      "published_at": "",
      "language": null,
      "source_lang": null,
      "provider": "gdelt_gkg_geojson",
      "themes": [
        "TAX_FNCACT_PRESIDENT",
        "TAX_FNCACT_VICE_PRESIDENT",
        "ECON_ENTREPRENEURSHIP",
        "TAX_FNCACT_MAYOR",
        "GOV_LOCALGOV",
        "TAX_FNCACT_MAYOR",
        "TAX_FNCACT_LEADERS",
        "LEADER",
        "TAX_FNCACT_GOVERNOR",
        "LEADER",
        "TAX_FNCACT_GOVERNOR"
      ]
    },
    {
      "title": "Madhya Pradesh, Madhya Pradesh, India",
      "title_en": null,
      "source": "www.palpalindia.com",
      "url": "https://www.palpalindia.com/2026/05/27/Madhya-Pradesh-High-Court-Jabalpur-cannot-provide-24-hour-security-for-every-interfaith-marriage-High-Court-dismisses-couple-petition.html",
      "published_at": "",
      "language": null,
      "source_lang": null,
      "provider": "gdelt_gkg_geojson",
      "themes": [
        "CRISISLEX_C07_SAFETY",
        "SECURITY_SERVICES",
        "TAX_FNCACT_POLICE",
        "SECURITY_SERVICES",
        "TAX_FNCACT_POLICE",
        "WB_696_PUBLIC_SECTOR_MANAGEMENT",
        "WB_840_JUSTICE",
        "UNGP_FORESTS_RIVERS_OCEANS",
        "ECON_TAXATION",
        "USPEC_POLICY1",
        "EPU_POLICY_TAX",
        "EPU_CATS_TAXES"
      ]
    },
    {
      "title": "Ratlam, Madhya Pradesh, India",
      "title_en": null,
      "source": "www.palpalindia.com",
      "url": "https://www.palpalindia.com/2026/05/27/Madhya-Pradesh-High-Court-Jabalpur-cannot-provide-24-hour-security-for-every-interfaith-marriage-High-Court-dismisses-couple-petition.html",
      "published_at": "",
      "language": null,
      "source_lang": null,
      "provider": "gdelt_gkg_geojson",
      "themes": [
        "CRISISLEX_C07_SAFETY",
        "SECURITY_SERVICES",
        "TAX_FNCACT_POLICE",
        "SECURITY_SERVICES",
        "TAX_FNCACT_POLICE",
        "LEGISLATION",
        "EPU_POLICY_LAW",
        "WB_696_PUBLIC_SECTOR_MANAGEMENT",
        "WB_840_JUSTICE",
        "UNGP_FORESTS_RIVERS_OCEANS",
        "ECON_TAXATION",
        "USPEC_POLICY1",
        "EPU_POLICY_TAX",
        "EPU_CATS_TAXES"
      ]
    },
    {
      "title": "Jabalpur, Madhya Pradesh, India",
      "title_en": null,
      "source": "www.palpalindia.com",
      "url": "https://www.palpalindia.com/2026/05/27/Madhya-Pradesh-High-Court-Jabalpur-cannot-provide-24-hour-security-for-every-interfaith-marriage-High-Court-dismisses-couple-petition.html",
      "published_at": "",
      "language": null,
      "source_lang": null,
      "provider": "gdelt_gkg_geojson",
      "themes": [
        "SOC_GENERALCRIME",
        "CRISISLEX_C07_SAFETY",
        "LEGISLATION",
        "EPU_POLICY_LAW",
        "WB_336_NON_BANK_FINANCIAL_INSTITUTIONS",
        "WB_1920_FINANCIAL_SECTOR_DEVELOPMENT",
        "WB_612_HOUSING_FINANCE",
        "WB_332_CAPITAL_MARKETS",
        "UNGP_FORESTS_RIVERS_OCEANS",
        "ECON_TAXATION",
        "USPEC_POLICY1",
        "EPU_POLICY_TAX",
        "EPU_CATS_TAXES",
        "KIDNAP"
      ]
    },
    {
      "title": "Delhi, Delhi, India",
      "title_en": null,
      "source": "www.palpalindia.com",
      "url": "https://www.palpalindia.com/2026/05/27/Madhya-Pradesh-High-Court-Jabalpur-cannot-provide-24-hour-security-for-every-interfaith-marriage-High-Court-dismisses-couple-petition.html",
      "published_at": "",
      "language": null,
      "source_lang": null,
      "provider": "gdelt_gkg_geojson",
      "themes": [
        "UNREST_BELLIGERENT",
        "WB_2433_CONFLICT_AND_VIOLENCE",
        "WB_2432_FRAGILITY_CONFLICT_AND_VIOLENCE",
        "SECURITY_SERVICES",
        "TAX_FNCACT_POLICE",
        "SECURITY_SERVICES",
        "TAX_FNCACT_POLICE",
        "RELIGION",
        "RELIGION",
        "RELIGION",
        "TAX_RELIGION_HINDU",
        "TAX_ETHNICITY_HINDU",
        "TAX_RELIGION_HINDU",
        "TAX_ETHNICITY_HINDU",
        "TAX_RELIGION_ISLAM",
        "CONSTITUTIONAL",
        "ECON_TAXATION",
        "USPEC_POLICY1",
        "EPU_POLICY_TAX",
        "EPU_CATS_TAXES"
      ]
    },
    {
      "title": "Desales University, Pennsylvania, United States",
      "title_en": null,
      "source": "www.wfmz.com",
      "url": "https://www.wfmz.com/news/area/lehighvalley/lehigh-county/southern-lehigh-county/the-curtain-rises-pa-shakespeare-festival-takes-stage-at-desales-university/article_aec6a5ee-a89f-48e3-9383-459db7941eb5.html",
      "published_at": "",
      "language": null,
      "source_lang": null,
      "provider": "gdelt_gkg_geojson",
      "themes": [
        "EDUCATION",
        "SOC_POINTSOFINTEREST_UNIVERSITY",
        "ECON_WORLDCURRENCIES_DOLLAR"
      ]
    },
    {
      "title": "Saucon, Pennsylvania, United States",
      "title_en": null,
      "source": "www.wfmz.com",
      "url": "https://www.wfmz.com/news/area/lehighvalley/lehigh-county/southern-lehigh-county/the-curtain-rises-pa-shakespeare-festival-takes-stage-at-desales-university/article_aec6a5ee-a89f-48e3-9383-459db7941eb5.html",
      "published_at": "",
      "language": null,
      "source_lang": null,
      "provider": "gdelt_gkg_geojson",
      "themes": [
        "TAX_FNCACT_DIRECTOR",
        "ECON_WORLDCURRENCIES_DOLLAR",
        "TAX_FNCACT_KING",
        "TAX_FNCACT_VOLUNTEERS"
      ]
    },
    {
      "title": "Mediterranean Sea, Oceans (General), Oceans",
      "title_en": null,
      "source": "www.nrc.nl",
      "url": "https://www.nrc.nl/nieuws/2026/05/27/nederlandse-mijnenjager-naar-de-middellandse-zee-kan-vanaf-medio-juni-worden-ingezet-in-de-straat-van-hormuz-a4928767",
      "published_at": "",
      "language": null,
      "source_lang": null,
      "provider": "gdelt_gkg_geojson",
      "themes": [
        "MANMADE_DISASTER_IMPLIED",
        "TAX_FNCACT_MINISTERS",
        "ALLIANCE",
        "TAX_ETHNICITY_DUTCH",
        "TAX_WORLDLANGUAGES_DUTCH",
        "TAX_ETHNICITY_DUTCH",
        "TAX_WORLDLANGUAGES_DUTCH",
        "EPU_ECONOMY_HISTORIC",
        "UNGP_FORESTS_RIVERS_OCEANS",
        "UNGP_FORESTS_RIVERS_OCEANS"
      ]
    },
    {
      "title": "Netherlands",
      "title_en": null,
      "source": "www.nrc.nl",
      "url": "https://www.nrc.nl/nieuws/2026/05/27/nederlandse-mijnenjager-naar-de-middellandse-zee-kan-vanaf-medio-juni-worden-ingezet-in-de-straat-van-hormuz-a4928767",
      "published_at": "",
      "language": null,
      "source_lang": null,
      "provider": "gdelt_gkg_geojson",
      "themes": [
        "MANMADE_DISASTER_IMPLIED",
        "TAX_ETHNICITY_BELGIAN",
        "AFFECT",
        "TAX_FNCACT_MINISTERS",
        "ALLIANCE",
        "TAX_ETHNICITY_DUTCH",
        "TAX_WORLDLANGUAGES_DUTCH",
        "EPU_ECONOMY_HISTORIC",
        "MEDICAL"
      ]
    },
    {
      "title": "Belgrade, Serbia (General),",
      "title_en": null,
      "source": "www.kamatica.com",
      "url": "https://www.kamatica.com/vest/globalna-ekonomska-elita-u-junu-stize-u-beograd/79001",
      "published_at": "",
      "language": null,
      "source_lang": null,
      "provider": "gdelt_gkg_geojson",
      "themes": [
        "TAX_FNCACT_ECONOMIST",
        "EPU_ECONOMY",
        "EPU_ECONOMY_HISTORIC",
        "EPU_ECONOMY",
        "EPU_ECONOMY_HISTORIC"
      ]
    },
    {
      "title": "Iraq",
      "title_en": null,
      "source": "q108.com",
      "url": "https://q108.com/news/030030-the-chicks-announce-intimate-taking-the-long-way-20th-anniversary-tour-this-is-our-lives/",
      "published_at": "",
      "language": null,
      "source_lang": null,
      "provider": "gdelt_gkg_geojson",
      "themes": [
        "MEDIA_MSM",
        "CRISISLEX_CRISISLEXREC",
        "LEADER",
        "TAX_FNCACT_PRESIDENT",
        "USPEC_POLITICS_GENERAL1",
        "LEADER",
        "TAX_FNCACT_PRESIDENT",
        "USPEC_POLITICS_GENERAL1",
        "EPU_ECONOMY_HISTORIC"
      ]
    },
    {
      "title": "London, London, City Of, United Kingdom",
      "title_en": null,
      "source": "q108.com",
      "url": "https://q108.com/news/030030-the-chicks-announce-intimate-taking-the-long-way-20th-anniversary-tour-this-is-our-lives/",
      "published_at": "",
      "language": null,
      "source_lang": null,
      "provider": "gdelt_gkg_geojson",
      "themes": [
        "MEDIA_MSM",
        "CRISISLEX_CRISISLEXREC",
        "LEADER",
        "TAX_FNCACT_PRESIDENT",
        "USPEC_POLITICS_GENERAL1",
        "LEADER",
        "TAX_FNCACT_PRESIDENT",
        "USPEC_POLITICS_GENERAL1",
        "EPU_ECONOMY_HISTORIC"
      ]
    },
    {
      "title": "Brisbane, Queensland, Australia",
      "title_en": null,
      "source": "blog.udn.com:443",
      "url": "https://blog.udn.com:443/075f5d2f/189318590",
      "published_at": "",
      "language": null,
      "source_lang": null,
      "provider": "gdelt_gkg_geojson",
      "themes": [
        "EDUCATION",
        "SOC_POINTSOFINTEREST_UNIVERSITY",
        "GENERAL_HEALTH",
        "MEDICAL",
        "TAX_FNCACT_NURSE",
        "TAX_FNCACT_CHILDREN",
        "WB_470_EDUCATION",
        "TAX_ECON_PRICE",
        "WB_2937_SILVER",
        "WB_507_ENERGY_AND_EXTRACTIVES",
        "WB_895_MINING_SYSTEMS",
        "WB_1699_METAL_ORE_MINING"
      ]
    },
    {
      "title": "Australia",
      "title_en": null,
      "source": "blog.udn.com:443",
      "url": "https://blog.udn.com:443/075f5d2f/189318590",
      "published_at": "",
      "language": null,
      "source_lang": null,
      "provider": "gdelt_gkg_geojson",
      "themes": [
        "SOC_GENERALCRIME",
        "EPU_CATS_MIGRATION_FEAR_FEAR",
        "ECON_ENTREPRENEURSHIP",
        "TAX_FNCACT_ENTREPRENEUR",
        "TAX_FNCACT_GUARD",
        "TAX_ETHNICITY_AUSTRALIAN",
        "TAX_FNCACT_VICTIM"
      ]
    },
    {
      "title": "Democratic Republic of the Congo",
      "title_en": null,
      "source": "www.messengernewspapers.co.uk",
      "url": "https://www.messengernewspapers.co.uk/news/national/26143644.uganda-closes-democratic-republic-congo-border-rare-ebola-cases-surge/",
      "published_at": "",
      "language": null,
      "source_lang": null,
      "provider": "gdelt_gkg_geojson",
      "themes": [
        "CRISISLEX_C03_WELLBEING_HEALTH",
        "GENERAL_GOVERNMENT",
        "TAX_DISEASE_OUTBREAK",
        "WB_635_PUBLIC_HEALTH",
        "WB_2165_HEALTH_EMERGENCIES",
        "WB_2166_HEALTH_EMERGENCY_PREPAREDNESS_AND_DISASTER_RESPONSE",
        "WB_2167_PANDEMICS",
        "TAX_DISEASE_EBOLA",
        "WB_1406_DISEASES",
        "WB_621_HEALTH_NUTRITION_AND_POPULATION",
        "WB_1415_COMMUNICABLE_DISEASE",
        "WB_2663_EBOLA",
        "TAX_FNCACT_WORKERS",
        "WB_1383_HEALTH_MANAGEMENT_AND_ADMINISTRATION",
        "WB_631_HUMAN_RESOURCES_FOR_HEALTH",
        "TAX_FNCACT_VICE_PRESIDENT",
        "LEADER",
        "TAX_FNCACT_PRESIDENT",
        "USPEC_POLITICS_GENERAL1",
        "DEMOCRACY",
        "GENERAL_HEALTH",
        "MEDICAL",
        "GENERAL_HEALTH",
        "MEDICAL",
        "EPU_CATS_MIGRATION_FEAR_FEAR",
        "ECON_DEVELOPMENTORGS_WORLD_HEALTH_ORGANISATION",
        "SCIENCE",
        "BORDER"
      ]
    },
    {
      "title": "Suriname",
      "title_en": null,
      "source": "www.waterkant.net",
      "url": "https://www.waterkant.net/suriname/2026/05/27/saya-ik-kon-waterpompen-gratis-via-ondernemer-aan-overheid-laten-verstrekken/",
      "published_at": "",
      "language": null,
      "source_lang": null,
      "provider": "gdelt_gkg_geojson",
      "themes": [
        "ECON_ENTREPRENEURSHIP",
        "TAX_FNCACT_ENTREPRENEUR",
        "LEADER",
        "TAX_FNCACT_POLITICIANS",
        "MEDIA_MSM",
        "CRISISLEX_T11_UPDATESSYMPATHY"
      ]
    },
    {
      "title": "Guyana",
      "title_en": null,
      "source": "www.waterkant.net",
      "url": "https://www.waterkant.net/suriname/2026/05/27/saya-ik-kon-waterpompen-gratis-via-ondernemer-aan-overheid-laten-verstrekken/",
      "published_at": "",
      "language": null,
      "source_lang": null,
      "provider": "gdelt_gkg_geojson",
      "themes": [
        "ECON_ENTREPRENEURSHIP",
        "TAX_FNCACT_ENTREPRENEUR",
        "ECON_ENTREPRENEURSHIP",
        "TAX_FNCACT_ENTREPRENEUR",
        "ECON_ENTREPRENEURSHIP",
        "TAX_FNCACT_ENTREPRENEUR",
        "TAX_ETHNICITY_HAITIAN",
        "MEDIA_MSM",
        "GENERAL_GOVERNMENT",
        "EPU_POLICY_GOVERNMENT",
        "GENERAL_GOVERNMENT",
        "EPU_POLICY_GOVERNMENT",
        "CRISISLEX_T11_UPDATESSYMPATHY",
        "WB_137_WATER",
        "WB_137_WATER"
      ]
    },
    {
      "title": "Haiti",
      "title_en": null,
      "source": "www.waterkant.net",
      "url": "https://www.waterkant.net/suriname/2026/05/27/saya-ik-kon-waterpompen-gratis-via-ondernemer-aan-overheid-laten-verstrekken/",
      "published_at": "",
      "language": null,
      "source_lang": null,
      "provider": "gdelt_gkg_geojson",
      "themes": [
        "ECON_ENTREPRENEURSHIP",
        "TAX_FNCACT_ENTREPRENEUR",
        "ECON_ENTREPRENEURSHIP",
        "TAX_FNCACT_ENTREPRENEUR",
        "ECON_ENTREPRENEURSHIP",
        "TAX_FNCACT_ENTREPRENEUR",
        "TAX_ETHNICITY_HAITIAN",
        "GENERAL_GOVERNMENT",
        "EPU_POLICY_GOVERNMENT",
        "GENERAL_GOVERNMENT",
        "EPU_POLICY_GOVERNMENT",
        "CRISISLEX_T11_UPDATESSYMPATHY",
        "WB_137_WATER",
        "WB_137_WATER"
      ]
    },
    {
      "title": "Canada",
      "title_en": null,
      "source": "www.deraktionaer.de",
      "url": "https://www.deraktionaer.de/nachricht/rounduppistoriuswirbtfuertkms-u-booteseiteanseitemitkanada-527666.html",
      "published_at": "",
      "language": null,
      "source_lang": null,
      "provider": "gdelt_gkg_geojson",
      "themes": [
        "TAX_FNCACT_MINISTER",
        "TAX_FNCACT_PRIME_MINISTER",
        "TAX_ETHNICITY_GERMAN",
        "TAX_WORLDLANGUAGES_GERMAN",
        "MARITIME",
        "WB_2670_JOBS",
        "WB_1467_EDUCATION_FOR_ALL",
        "WB_470_EDUCATION",
        "WB_2131_EMPLOYABILITY_SKILLS_AND_JOBS",
        "WB_1484_EDUCATION_SKILLS_DEVELOPMENT_AND_LABOR_MARKET",
        "CRISISLEX_C07_SAFETY",
        "TAX_ETHNICITY_CANADIAN",
        "TAX_ETHNICITY_CANADIAN",
        "EPU_ECONOMY",
        "EPU_ECONOMY_HISTORIC",
        "WB_508_POWER_SYSTEMS",
        "WB_509_NUCLEAR_ENERGY",
        "WB_507_ENERGY_AND_EXTRACTIVES",
        "TAX_DISEASE_CONVENTIONAL"
      ]
    }
  ]
}