{
  "count": 108,
  "data": [
    {
      "title": "Guangdong, Jilin, China",
      "title_en": null,
      "source": "www.163.com",
      "url": "https://www.163.com/dy/article/L0A9B6ES0519DFFO.html",
      "published_at": "",
      "language": null,
      "source_lang": null,
      "provider": "gdelt_gkg_geojson",
      "themes": [
        "EPU_ECONOMY_HISTORIC",
        "WB_135_TRANSPORT",
        "WB_135_TRANSPORT",
        "USPEC_POLICY1",
        "EPU_POLICY_POLICY",
        "TAX_FNCACT_DEPUTY"
      ]
    },
    {
      "title": "Bangalore, Karnataka, India",
      "title_en": null,
      "source": "www.mexicostar.com",
      "url": "http://www.mexicostar.com/news/279147237/triton-group-redefines-residential-real-estate-through-assured-income-homes",
      "published_at": "",
      "language": null,
      "source_lang": null,
      "provider": "gdelt_gkg_geojson",
      "themes": [
        "WB_904_HOUSING_MARKETS",
        "WB_817_LAND_AND_HOUSING",
        "WB_813_URBAN_GOVERNANCE_AND_CITY_SYSTEMS",
        "WB_699_URBAN_DEVELOPMENT",
        "ECON_HOUSING_PRICES",
        "CRISISLEX_C03_WELLBEING_HEALTH",
        "SOC_POINTSOFINTEREST_AIRPORT",
        "WB_135_TRANSPORT",
        "WB_1803_TRANSPORT_INFRASTRUCTURE",
        "WB_1804_AIRPORTS",
        "SOC_POINTSOFINTEREST_AIRPORT",
        "WB_135_TRANSPORT",
        "WB_1803_TRANSPORT_INFRASTRUCTURE",
        "WB_1804_AIRPORTS",
        "EPU_ECONOMY_HISTORIC"
      ]
    },
    {
      "title": "New Delhi, Delhi, India",
      "title_en": null,
      "source": "www.mexicostar.com",
      "url": "http://www.mexicostar.com/news/279147237/triton-group-redefines-residential-real-estate-through-assured-income-homes",
      "published_at": "",
      "language": null,
      "source_lang": null,
      "provider": "gdelt_gkg_geojson",
      "themes": [
        "IDEOLOGY",
        "ECON_HOUSING_PRICES"
      ]
    },
    {
      "title": "Portugal",
      "title_en": null,
      "source": "www.theportugalnews.com",
      "url": "https://www.theportugalnews.com/news/2026-06-25/property-of-the-week-a-stunning-luxury-villa-with-panoramic-sea-views-in-loules/1045738",
      "published_at": "",
      "language": null,
      "source_lang": null,
      "provider": "gdelt_gkg_geojson",
      "themes": [
        "ECON_HOUSING_PRICES",
        "UNGP_FORESTS_RIVERS_OCEANS",
        "TAX_ETHNICITY_PORTUGUESE",
        "TAX_WORLDLANGUAGES_PORTUGUESE",
        "PROTEST",
        "STRIKE"
      ]
    },
    {
      "title": "Vilamoura, Porto, Portugal",
      "title_en": null,
      "source": "www.theportugalnews.com",
      "url": "https://www.theportugalnews.com/news/2026-06-25/property-of-the-week-a-stunning-luxury-villa-with-panoramic-sea-views-in-loules/1045738",
      "published_at": "",
      "language": null,
      "source_lang": null,
      "provider": "gdelt_gkg_geojson",
      "themes": [
        "ECON_HOUSING_PRICES",
        "SOC_POINTSOFINTEREST_AIRPORT",
        "WB_135_TRANSPORT",
        "WB_1803_TRANSPORT_INFRASTRUCTURE",
        "WB_1804_AIRPORTS"
      ]
    },
    {
      "title": "Mumbai, Maharashtra, India",
      "title_en": null,
      "source": "www.loksatta.com",
      "url": "https://www.loksatta.com/mumbai/mumbai-monsoon-waterlogging-bmc-547-water-pumps-failure-heavy-rain-mumbai-print-news-ssb-93-5982132/",
      "published_at": "",
      "language": null,
      "source_lang": null,
      "provider": "gdelt_gkg_geojson",
      "themes": [
        "TAX_ECON_PRICE",
        "WB_137_WATER",
        "WB_137_WATER",
        "WB_137_WATER"
      ]
    },
    {
      "title": "Agadir, Souss-Massa-DrâMo, Morocco",
      "title_en": null,
      "source": "www.moroccoworldnews.com",
      "url": "https://www.moroccoworldnews.com/2026/06/325020/safran-expands-morocco-operations-with-mad-350-million-investment/",
      "published_at": "",
      "language": null,
      "source_lang": null,
      "provider": "gdelt_gkg_geojson",
      "themes": [
        "TAX_ETHNICITY_FRENCH",
        "TAX_WORLDLANGUAGES_FRENCH",
        "EPU_ECONOMY_HISTORIC"
      ]
    },
    {
      "title": "Nouaceur, Region De Chaouia-Ouardigha, Morocco",
      "title_en": null,
      "source": "www.moroccoworldnews.com",
      "url": "https://www.moroccoworldnews.com/2026/06/325020/safran-expands-morocco-operations-with-mad-350-million-investment/",
      "published_at": "",
      "language": null,
      "source_lang": null,
      "provider": "gdelt_gkg_geojson",
      "themes": [
        "WB_698_TRADE",
        "LEADER",
        "TAX_ETHNICITY_FRENCH",
        "TAX_WORLDLANGUAGES_FRENCH",
        "EPU_ECONOMY_HISTORIC",
        "TAX_FNCACT_MINISTER"
      ]
    },
    {
      "title": "Morocco",
      "title_en": null,
      "source": "www.moroccoworldnews.com",
      "url": "https://www.moroccoworldnews.com/2026/06/325020/safran-expands-morocco-operations-with-mad-350-million-investment/",
      "published_at": "",
      "language": null,
      "source_lang": null,
      "provider": "gdelt_gkg_geojson",
      "themes": [
        "TAX_ETHNICITY_FRENCH",
        "TAX_WORLDLANGUAGES_FRENCH",
        "EPU_ECONOMY_HISTORIC"
      ]
    },
    {
      "title": "Casablanca, Grand Casablanca, Morocco",
      "title_en": null,
      "source": "www.moroccoworldnews.com",
      "url": "https://www.moroccoworldnews.com/2026/06/325020/safran-expands-morocco-operations-with-mad-350-million-investment/",
      "published_at": "",
      "language": null,
      "source_lang": null,
      "provider": "gdelt_gkg_geojson",
      "themes": [
        "WB_698_TRADE",
        "LEADER",
        "TAX_ETHNICITY_FRENCH",
        "TAX_WORLDLANGUAGES_FRENCH",
        "EPU_ECONOMY_HISTORIC",
        "TAX_FNCACT_CEO",
        "TAX_FNCACT_MINISTER"
      ]
    },
    {
      "title": "France",
      "title_en": null,
      "source": "www.moroccoworldnews.com",
      "url": "https://www.moroccoworldnews.com/2026/06/325020/safran-expands-morocco-operations-with-mad-350-million-investment/",
      "published_at": "",
      "language": null,
      "source_lang": null,
      "provider": "gdelt_gkg_geojson",
      "themes": [
        "TAX_ETHNICITY_FRENCH",
        "TAX_WORLDLANGUAGES_FRENCH",
        "EPU_ECONOMY_HISTORIC"
      ]
    },
    {
      "title": "Russia",
      "title_en": null,
      "source": "www.thenewslens.com",
      "url": "https://www.thenewslens.com/article/268662",
      "published_at": "",
      "language": null,
      "source_lang": null,
      "provider": "gdelt_gkg_geojson",
      "themes": [
        "MARITIME",
        "TAX_ECON_PRICE",
        "UNGP_FORESTS_RIVERS_OCEANS",
        "TAX_ETHNICITY_RUSSIAN",
        "TAX_WORLDLANGUAGES_RUSSIAN",
        "MILITARY",
        "WB_135_TRANSPORT"
      ]
    },
    {
      "title": "India",
      "title_en": null,
      "source": "www.thenewslens.com",
      "url": "https://www.thenewslens.com/article/268662",
      "published_at": "",
      "language": null,
      "source_lang": null,
      "provider": "gdelt_gkg_geojson",
      "themes": [
        "ARMEDCONFLICT",
        "EPU_CATS_NATIONAL_SECURITY",
        "ARMEDCONFLICT",
        "EPU_CATS_NATIONAL_SECURITY",
        "CRISISLEX_C07_SAFETY",
        "TAX_ECON_PRICE",
        "TAX_FNCACT_OFFICIAL",
        "SOC_POINTSOFINTEREST_HEADQUARTERS",
        "SOC_POINTSOFINTEREST_HEADQUARTERS"
      ]
    },
    {
      "title": "Iran",
      "title_en": null,
      "source": "www.thenewslens.com",
      "url": "https://www.thenewslens.com/article/268662",
      "published_at": "",
      "language": null,
      "source_lang": null,
      "provider": "gdelt_gkg_geojson",
      "themes": [
        "MARITIME",
        "TAX_ECON_PRICE",
        "UNGP_FORESTS_RIVERS_OCEANS",
        "TAX_ETHNICITY_RUSSIAN",
        "TAX_WORLDLANGUAGES_RUSSIAN",
        "MILITARY",
        "WB_135_TRANSPORT"
      ]
    },
    {
      "title": "Washington, Washington, United States",
      "title_en": null,
      "source": "www.thenewslens.com",
      "url": "https://www.thenewslens.com/article/268662",
      "published_at": "",
      "language": null,
      "source_lang": null,
      "provider": "gdelt_gkg_geojson",
      "themes": [
        "TAX_ECON_PRICE",
        "UNGP_FORESTS_RIVERS_OCEANS",
        "TAX_ETHNICITY_RUSSIAN",
        "TAX_WORLDLANGUAGES_RUSSIAN"
      ]
    },
    {
      "title": "Red Sea, Djibouti (General), Djibouti",
      "title_en": null,
      "source": "www.thenewslens.com",
      "url": "https://www.thenewslens.com/article/268662",
      "published_at": "",
      "language": null,
      "source_lang": null,
      "provider": "gdelt_gkg_geojson",
      "themes": [
        "MARITIME",
        "TAX_ECON_PRICE",
        "UNGP_FORESTS_RIVERS_OCEANS",
        "TAX_ETHNICITY_RUSSIAN",
        "TAX_WORLDLANGUAGES_RUSSIAN",
        "MILITARY",
        "WB_135_TRANSPORT"
      ]
    },
    {
      "title": "Louisiana, United States",
      "title_en": null,
      "source": "talkradio960.com",
      "url": "https://talkradio960.com/ixp/33/p/louisiana-man-fined-fried-speckled-trout/",
      "published_at": "",
      "language": null,
      "source_lang": null,
      "provider": "gdelt_gkg_geojson",
      "themes": [
        "WB_2024_ANTI_CORRUPTION_AUTHORITIES",
        "WB_696_PUBLIC_SECTOR_MANAGEMENT",
        "WB_840_JUSTICE",
        "WB_2025_INVESTIGATION",
        "WB_831_GOVERNANCE",
        "WB_832_ANTI_CORRUPTION",
        "WB_1014_CRIMINAL_JUSTICE",
        "TAX_WORLDFISH_FISH",
        "TAX_WORLDFISH_FISH",
        "TAX_WORLDFISH_FISH",
        "TAX_WORLDFISH_FISH",
        "TAX_WORLDFISH_TROUT",
        "TAX_WORLDFISH_SPECKLED_TROUT",
        "TAX_ECON_PRICE",
        "MEDIA_MSM",
        "TAX_FNCACT_OFFICIALS"
      ]
    },
    {
      "title": "Indonesia",
      "title_en": null,
      "source": "retizen.republika.co.id",
      "url": "https://retizen.republika.co.id/posts/766565/distribusi-pendapatan-dalam-islam-mewujudkan-holistic-welfare",
      "published_at": "",
      "language": null,
      "source_lang": null,
      "provider": "gdelt_gkg_geojson",
      "themes": [
        "EDUCATION",
        "WB_470_EDUCATION",
        "TAX_RELIGION_ISLAM",
        "TAX_RELIGION_ISLAM",
        "USPEC_POLICY1",
        "EPU_ECONOMY",
        "EPU_ECONOMY_HISTORIC",
        "USPEC_POLICY1",
        "EPU_ECONOMY",
        "EPU_ECONOMY_HISTORIC",
        "USPEC_POLICY1",
        "EPU_ECONOMY",
        "EPU_ECONOMY_HISTORIC",
        "TAX_RELIGION_SHARIA",
        "WB_695_POVERTY",
        "INEQUALITY"
      ]
    },
    {
      "title": "South Kalimantan, Kalimantan Selatan, Indonesia",
      "title_en": null,
      "source": "banjarmasin.tribunnews.com",
      "url": "https://banjarmasin.tribunnews.com/kalsel/1366449/daftar-acara-menarik-memeriahkan-festival-bamboo-rafting-loksado-hss-kalsel-ada-hiburan-rakyat",
      "published_at": "",
      "language": null,
      "source_lang": null,
      "provider": "gdelt_gkg_geojson",
      "themes": [
        "TAX_FNCACT_MERCHANT",
        "DELAY",
        "USPEC_POLITICS_GENERAL1",
        "LEADER",
        "TAX_FNCACT_GOVERNOR",
        "TAX_FNCACT_OFFICIALS",
        "USPEC_POLICY1",
        "EPU_ECONOMY",
        "EPU_ECONOMY_HISTORIC"
      ]
    },
    {
      "title": "Kazakhstan",
      "title_en": null,
      "source": "www.pr-inside.com",
      "url": "https://www.pr-inside.com/hydrosat-and-kazakhstan-gharysh-sapary-sign-agreement-to-advance-satellite-based-r5194655.htm",
      "published_at": "",
      "language": null,
      "source_lang": null,
      "provider": "gdelt_gkg_geojson",
      "themes": [
        "SCIENCE",
        "SOC_INNOVATION",
        "SCIENCE",
        "SOC_INNOVATION",
        "WB_482_TERTIARY_EDUCATION",
        "WB_478_LEVELS_OF_EDUCATION",
        "EDUCATION",
        "WB_470_EDUCATION",
        "GENERAL_GOVERNMENT",
        "GENERAL_GOVERNMENT",
        "EPU_POLICY_GOVERNMENT",
        "LEADER",
        "TAX_FNCACT_PRIME_MINISTER",
        "TAX_FNCACT_MINISTER",
        "TAX_FNCACT_DEPUTY",
        "EPU_ECONOMY_HISTORIC",
        "TAX_FNCACT_MINISTER",
        "TAX_FNCACT_MINISTER",
        "TAX_FNCACT_REPRESENTATIVES"
      ]
    },
    {
      "title": "Romania",
      "title_en": null,
      "source": "jurnalul.ro",
      "url": "https://jurnalul.ro/bani-afaceri/economia/transgaz-cauta-viitorii-specialisti-la-constanta-1037168.html",
      "published_at": "",
      "language": null,
      "source_lang": null,
      "provider": "gdelt_gkg_geojson",
      "themes": [
        "USPEC_POLICY1",
        "EPU_ECONOMY",
        "EPU_ECONOMY_HISTORIC",
        "TAX_FNCACT_STUDENTS",
        "EDUCATION",
        "SOC_POINTSOFINTEREST_UNIVERSITY"
      ]
    },
    {
      "title": "Caracas, Distrito Federal, Venezuela",
      "title_en": null,
      "source": "www.aciprensa.com",
      "url": "https://www.aciprensa.com/noticias/126365/terremoto-en-venezuela-papa-leon-xiv-dona-100000-euros",
      "published_at": "",
      "language": null,
      "source_lang": null,
      "provider": "gdelt_gkg_geojson",
      "themes": [
        "EPU_ECONOMY",
        "EPU_ECONOMY_HISTORIC",
        "SLFID_ECONOMIC_DEVELOPMENTAID",
        "AID_ECONOMIC",
        "TAX_RELIGION_CHURCH",
        "TAX_FNCACT_MINISTER",
        "NATURAL_DISASTER_EARTHQUAKES",
        "TAX_RELIGION_CATHOLIC",
        "TAX_FNCACT_ARCHBISHOP"
      ]
    },
    {
      "title": "Venezuela",
      "title_en": null,
      "source": "www.aciprensa.com",
      "url": "https://www.aciprensa.com/noticias/126365/terremoto-en-venezuela-papa-leon-xiv-dona-100000-euros",
      "published_at": "",
      "language": null,
      "source_lang": null,
      "provider": "gdelt_gkg_geojson",
      "themes": [
        "EPU_ECONOMY",
        "EPU_ECONOMY_HISTORIC",
        "TAX_FNCACT_PONTIFF",
        "TAX_FNCACT_PONTIFF",
        "SLFID_ECONOMIC_DEVELOPMENTAID",
        "AID_ECONOMIC",
        "TAX_WORLDMAMMALS_LION",
        "TAX_WORLDMAMMALS_LION",
        "SELF_IDENTIFIED_HUMANITARIAN_CRISIS",
        "AID_HUMANITARIAN",
        "NATURAL_DISASTER_EARTHQUAKES",
        "CRISISLEX_CRISISLEXREC",
        "TAX_RELIGION_CATHOLIC"
      ]
    },
    {
      "title": "Nigeria",
      "title_en": null,
      "source": "www.premiumtimesng.com",
      "url": "https://www.premiumtimesng.com/news/top-news/890667-advocacy-group-urges-men-to-turn-support-for-girls-education-into-action.html",
      "published_at": "",
      "language": null,
      "source_lang": null,
      "provider": "gdelt_gkg_geojson",
      "themes": [
        "MANMADE_DISASTER_IMPLIED",
        "SOC_POINTSOFINTEREST_SCHOOL",
        "EDUCATION",
        "WB_470_EDUCATION",
        "EDUCATION",
        "WB_470_EDUCATION",
        "EDUCATION",
        "WB_470_EDUCATION",
        "UNGP_CRIME_VIOLENCE",
        "TAX_DISEASE_PREGNANCY",
        "SOC_EARLYMARRIAGE",
        "WB_742_YOUTH_AND_GENDER_BASED_VIOLENCE",
        "WB_738_SOCIAL_COHESION",
        "WB_2444_EARLY_MARRIAGE",
        "WB_134_SOCIAL_DEVELOPMENT",
        "TAX_FNCACT_CHILD",
        "USPEC_POLICY1",
        "WB_1513_EDUCATION_POLICY_AND_PLANNING",
        "WB_1497_EDUCATION_MANAGEMENT_AND_ADMINISTRATION",
        "WB_498_EDUCATION_FINANCE",
        "WB_1540_ECONOMICS_OF_EDUCATION",
        "EPU_POLICY_POLICY",
        "CRISISLEX_T11_UPDATESSYMPATHY"
      ]
    },
    {
      "title": "Rohrenfurth, Hessen, Germany",
      "title_en": null,
      "source": "www.hna.de",
      "url": "https://www.hna.de/lokales/melsungen/melsungen-ort45520/landkreis-lehnt-zusaetzlichen-schulbus-fuer-roehrenfurth-ab-94368363.html",
      "published_at": "",
      "language": null,
      "source_lang": null,
      "provider": "gdelt_gkg_geojson",
      "themes": [
        "WB_1979_NATURAL_RESOURCE_MANAGEMENT",
        "WB_435_AGRICULTURE_AND_FOOD_SECURITY",
        "WB_1986_MOUNTAINS",
        "TAX_ECON_PRICE",
        "EDUCATION",
        "SOC_POINTSOFINTEREST_SCHOOL",
        "TAX_ETHNICITY_BLACK"
      ]
    },
    {
      "title": "Guxhagen, Hessen, Germany",
      "title_en": null,
      "source": "www.hna.de",
      "url": "https://www.hna.de/lokales/melsungen/melsungen-ort45520/landkreis-lehnt-zusaetzlichen-schulbus-fuer-roehrenfurth-ab-94368363.html",
      "published_at": "",
      "language": null,
      "source_lang": null,
      "provider": "gdelt_gkg_geojson",
      "themes": [
        "TAX_ECON_PRICE",
        "EDUCATION",
        "SOC_POINTSOFINTEREST_SCHOOL",
        "EDUCATION",
        "SOC_POINTSOFINTEREST_SCHOOL",
        "TAX_FNCACT_CHILD",
        "CLOSURE",
        "SOC_POINTSOFINTEREST_SCHOOLS"
      ]
    },
    {
      "title": "Melsungen, Hessen, Germany",
      "title_en": null,
      "source": "www.hna.de",
      "url": "https://www.hna.de/lokales/melsungen/melsungen-ort45520/landkreis-lehnt-zusaetzlichen-schulbus-fuer-roehrenfurth-ab-94368363.html",
      "published_at": "",
      "language": null,
      "source_lang": null,
      "provider": "gdelt_gkg_geojson",
      "themes": [
        "WB_135_TRANSPORT",
        "TAX_ECON_PRICE",
        "EDUCATION",
        "SOC_POINTSOFINTEREST_SCHOOL",
        "EDUCATION",
        "SOC_POINTSOFINTEREST_SCHOOL",
        "TAX_FNCACT_CHILD",
        "CLOSURE",
        "SOC_POINTSOFINTEREST_SCHOOLS",
        "SOC_POINTSOFINTEREST_SCHOOLS"
      ]
    },
    {
      "title": "Schwalm-Eder-Kreis, Hessen, Germany",
      "title_en": null,
      "source": "www.hna.de",
      "url": "https://www.hna.de/lokales/melsungen/melsungen-ort45520/landkreis-lehnt-zusaetzlichen-schulbus-fuer-roehrenfurth-ab-94368363.html",
      "published_at": "",
      "language": null,
      "source_lang": null,
      "provider": "gdelt_gkg_geojson",
      "themes": [
        "WB_135_TRANSPORT",
        "WB_135_TRANSPORT",
        "WB_135_TRANSPORT",
        "WB_135_TRANSPORT",
        "TAX_ECON_PRICE",
        "EDUCATION",
        "SOC_POINTSOFINTEREST_SCHOOL",
        "TAX_FNCACT_STUDENT",
        "TAX_FNCACT_STUDENT",
        "TAX_FNCACT_STUDENT",
        "SOC_POINTSOFINTEREST_SCHOOLS"
      ]
    },
    {
      "title": "United Kingdom",
      "title_en": null,
      "source": "www.ualrpublicradio.org",
      "url": "https://www.ualrpublicradio.org/npr-news/2026-06-25/when-going-to-camp-meant-roman-military-lodgings-not-summer-fun",
      "published_at": "",
      "language": null,
      "source_lang": null,
      "provider": "gdelt_gkg_geojson",
      "themes": [
        "TAX_ETHNICITY_AMERICAN",
        "URBAN",
        "SOC_POINTSOFINTEREST_UNIVERSITY",
        "MOVEMENT_GENERAL",
        "MANMADE_DISASTER_IMPLIED",
        "EPU_ECONOMY_HISTORIC",
        "WB_695_POVERTY",
        "WB_1153_MIDDLE_CLASS",
        "WB_1152_ECONOMIC_AND_SOCIAL_MOBILITY",
        "WB_707_POVERTY_MEASUREMENT_AND_ANALYSIS",
        "TAX_FNCACT_PROFESSOR"
      ]
    },
    {
      "title": "Vancouver, British Columbia, Canada",
      "title_en": null,
      "source": "www.ualrpublicradio.org",
      "url": "https://www.ualrpublicradio.org/npr-news/2026-06-25/when-going-to-camp-meant-roman-military-lodgings-not-summer-fun",
      "published_at": "",
      "language": null,
      "source_lang": null,
      "provider": "gdelt_gkg_geojson",
      "themes": [
        "TAX_ETHNICITY_AMERICAN",
        "URBAN",
        "SOC_POINTSOFINTEREST_UNIVERSITY",
        "MOVEMENT_GENERAL",
        "MANMADE_DISASTER_IMPLIED",
        "EPU_ECONOMY_HISTORIC",
        "WB_695_POVERTY",
        "WB_1153_MIDDLE_CLASS",
        "WB_1152_ECONOMIC_AND_SOCIAL_MOBILITY",
        "WB_707_POVERTY_MEASUREMENT_AND_ANALYSIS",
        "TAX_FNCACT_PROFESSOR"
      ]
    },
    {
      "title": "Paris, France (General), France",
      "title_en": null,
      "source": "www.ualrpublicradio.org",
      "url": "https://www.ualrpublicradio.org/npr-news/2026-06-25/when-going-to-camp-meant-roman-military-lodgings-not-summer-fun",
      "published_at": "",
      "language": null,
      "source_lang": null,
      "provider": "gdelt_gkg_geojson",
      "themes": [
        "TAX_ETHNICITY_AMERICAN",
        "URBAN",
        "SOC_POINTSOFINTEREST_UNIVERSITY",
        "MOVEMENT_GENERAL",
        "KILL",
        "CRISISLEX_T03_DEAD",
        "MANMADE_DISASTER_IMPLIED",
        "EPU_ECONOMY_HISTORIC",
        "WB_695_POVERTY",
        "WB_1153_MIDDLE_CLASS",
        "WB_1152_ECONOMIC_AND_SOCIAL_MOBILITY",
        "WB_707_POVERTY_MEASUREMENT_AND_ANALYSIS",
        "TAX_FNCACT_PROFESSOR"
      ]
    },
    {
      "title": "Canada",
      "title_en": null,
      "source": "www.ualrpublicradio.org",
      "url": "https://www.ualrpublicradio.org/npr-news/2026-06-25/when-going-to-camp-meant-roman-military-lodgings-not-summer-fun",
      "published_at": "",
      "language": null,
      "source_lang": null,
      "provider": "gdelt_gkg_geojson",
      "themes": [
        "TAX_ETHNICITY_AMERICAN",
        "URBAN",
        "SOC_POINTSOFINTEREST_UNIVERSITY",
        "MOVEMENT_GENERAL",
        "MANMADE_DISASTER_IMPLIED",
        "EPU_ECONOMY_HISTORIC",
        "WB_695_POVERTY",
        "WB_1153_MIDDLE_CLASS",
        "WB_1152_ECONOMIC_AND_SOCIAL_MOBILITY",
        "WB_707_POVERTY_MEASUREMENT_AND_ANALYSIS",
        "TAX_FNCACT_PROFESSOR"
      ]
    },
    {
      "title": "Taiwan",
      "title_en": null,
      "source": "www.setn.com",
      "url": "https://www.setn.com/News.aspx?NewsID=1862507",
      "published_at": "",
      "language": null,
      "source_lang": null,
      "provider": "gdelt_gkg_geojson",
      "themes": [
        "TAX_ECON_PRICE",
        "TAX_FNCACT_WEBMASTER",
        "TAX_FNCACT_WORKERS",
        "TAX_WORLDMAMMALS_CAT",
        "TAX_WORLDMAMMALS_CATS",
        "CRISISLEX_C07_SAFETY"
      ]
    },
    {
      "title": "Milan, Lombardia, Italy",
      "title_en": null,
      "source": "www.zazoom.it",
      "url": "https://www.zazoom.it/2026-06-25/sostenibilita-scotti-coreve-comunicazione-efficace-porta-risultati-migliori/19388478/",
      "published_at": "",
      "language": null,
      "source_lang": null,
      "provider": "gdelt_gkg_geojson",
      "themes": [
        "USPEC_POLICY1",
        "EPU_ECONOMY",
        "EPU_ECONOMY_HISTORIC",
        "UNGP_FORESTS_RIVERS_OCEANS",
        "UNGP_FORESTS_RIVERS_OCEANS",
        "WB_566_ENVIRONMENT_AND_NATURAL_RESOURCES",
        "WB_1786_ENVIRONMENTAL_SUSTAINABILITY",
        "EDUCATION",
        "SOC_POINTSOFINTEREST_UNIVERSITY",
        "EDUCATION",
        "SOC_POINTSOFINTEREST_UNIVERSITY",
        "EDUCATION",
        "SOC_POINTSOFINTEREST_UNIVERSITY",
        "LEADER",
        "TAX_FNCACT_PRESIDENT",
        "USPEC_POLITICS_GENERAL1"
      ]
    },
    {
      "title": "Wojciech, Podlaskie, Poland",
      "title_en": null,
      "source": "www.portalsamorzadowy.pl",
      "url": "https://www.portalsamorzadowy.pl/fundusze-europejskie/podejrzenia-o-korupcje-zablokowaly-450-mln-zl-spolka-tramwajowa-stoi-przed-duzym-problemem,666264.html",
      "published_at": "",
      "language": null,
      "source_lang": null,
      "provider": "gdelt_gkg_geojson",
      "themes": [
        "ALLIANCE",
        "TAX_ECON_PRICE",
        "TAX_FNCACT_KING",
        "USPEC_UNCERTAINTY1",
        "GENERAL_GOVERNMENT",
        "CORRUPTION"
      ]
    },
    {
      "title": "Germany",
      "title_en": null,
      "source": "aif.ru",
      "url": "https://aif.ru/money/economy/vopreki-vsemu-glavnye-produkty-v-rossii-desheveyut-poka-inflyaciya-rastet",
      "published_at": "",
      "language": null,
      "source_lang": null,
      "provider": "gdelt_gkg_geojson",
      "themes": [
        "TAX_FOODSTAPLES_EGGS",
        "TAX_ECON_PRICE",
        "ECON_INFLATION",
        "WB_1104_MACROECONOMIC_VULNERABILITY_AND_DEBT",
        "WB_442_INFLATION",
        "ECON_INFLATION",
        "WB_1104_MACROECONOMIC_VULNERABILITY_AND_DEBT",
        "WB_442_INFLATION",
        "MEDIA_MSM",
        "TAX_ETHNICITY_GERMAN",
        "TAX_WORLDLANGUAGES_GERMAN",
        "TAX_FNCACT_CITIZENS",
        "TAX_FOODSTAPLES_MILK"
      ]
    },
    {
      "title": "Israel",
      "title_en": null,
      "source": "aif.ru",
      "url": "https://aif.ru/money/economy/vopreki-vsemu-glavnye-produkty-v-rossii-desheveyut-poka-inflyaciya-rastet",
      "published_at": "",
      "language": null,
      "source_lang": null,
      "provider": "gdelt_gkg_geojson",
      "themes": [
        "TAX_FOODSTAPLES_EGGS",
        "TAX_FOODSTAPLES_EGGS",
        "TAX_FNCACT_OFFICIAL",
        "USPEC_POLICY1",
        "EPU_ECONOMY",
        "EPU_ECONOMY_HISTORIC",
        "SOC_POINTSOFINTEREST_UNIVERSITY",
        "TAX_FOODSTAPLES_GRAIN",
        "ARMEDCONFLICT",
        "EPU_CATS_NATIONAL_SECURITY",
        "ECON_INFLATION",
        "WB_1104_MACROECONOMIC_VULNERABILITY_AND_DEBT",
        "WB_442_INFLATION",
        "EDUCATION",
        "TAX_FNCACT_PROFESSOR",
        "CRISISLEX_C04_LOGISTICS_TRANSPORT",
        "WB_2433_CONFLICT_AND_VIOLENCE",
        "WB_2432_FRAGILITY_CONFLICT_AND_VIOLENCE"
      ]
    },
    {
      "title": "Sweden",
      "title_en": null,
      "source": "www.excelsior.com.mx",
      "url": "https://www.excelsior.com.mx/finanzas/precio-dolar-hoy-tipo-cambio-bancos-mexico-25-junio-2026",
      "published_at": "",
      "language": null,
      "source_lang": null,
      "provider": "gdelt_gkg_geojson",
      "themes": [
        "ECON_STOCKMARKET",
        "USPEC_POLICY1",
        "EPU_ECONOMY",
        "EPU_ECONOMY_HISTORIC",
        "WB_698_TRADE",
        "TAX_ECON_PRICE",
        "ECON_WORLDCURRENCIES_DOLLAR",
        "ECON_WORLDCURRENCIES_DOLLAR",
        "WB_444_MONETARY_POLICY",
        "WB_439_MACROECONOMIC_AND_STRUCTURAL_POLICIES",
        "EPU_POLICY_MONETARY_POLICY",
        "EPU_CATS_MONETARY_POLICY",
        "EPU_POLICY_POLICY"
      ]
    },
    {
      "title": "Mexico",
      "title_en": null,
      "source": "www.excelsior.com.mx",
      "url": "https://www.excelsior.com.mx/finanzas/precio-dolar-hoy-tipo-cambio-bancos-mexico-25-junio-2026",
      "published_at": "",
      "language": null,
      "source_lang": null,
      "provider": "gdelt_gkg_geojson",
      "themes": [
        "ECON_STOCKMARKET",
        "USPEC_POLICY1",
        "EPU_ECONOMY",
        "EPU_ECONOMY_HISTORIC"
      ]
    },
    {
      "title": "Italy",
      "title_en": null,
      "source": "www.adnkronos.com",
      "url": "https://www.adnkronos.com/economia/indagine-bain-e-company-aniasa-italiani-non-rinunciano-ad-auto-ma-rinviano-acquisto_6Mwa17x8EkO2UTmkvYvFuK",
      "published_at": "",
      "language": null,
      "source_lang": null,
      "provider": "gdelt_gkg_geojson",
      "themes": [
        "EPU_ECONOMY",
        "EPU_ECONOMY_HISTORIC",
        "SHORTAGE",
        "ECON_INFLATION",
        "WB_1104_MACROECONOMIC_VULNERABILITY_AND_DEBT",
        "WB_442_INFLATION"
      ]
    },
    {
      "title": "London, London, City Of, United Kingdom",
      "title_en": null,
      "source": "www.biznews.com",
      "url": "https://www.biznews.com/global-citizen/why-youre-better-off-in-jozi",
      "published_at": "",
      "language": null,
      "source_lang": null,
      "provider": "gdelt_gkg_geojson",
      "themes": [
        "ECON_COST_OF_LIVING",
        "TAX_ECON_PRICE",
        "MEDICAL"
      ]
    },
    {
      "title": "South Africa",
      "title_en": null,
      "source": "www.biznews.com",
      "url": "https://www.biznews.com/global-citizen/why-youre-better-off-in-jozi",
      "published_at": "",
      "language": null,
      "source_lang": null,
      "provider": "gdelt_gkg_geojson",
      "themes": [
        "ECON_COST_OF_LIVING",
        "TAX_ECON_PRICE",
        "MEDICAL"
      ]
    },
    {
      "title": "Lebanon",
      "title_en": null,
      "source": "www.diariodeburgos.es",
      "url": "https://www.diariodeburgos.es/noticia/ze4deabae-bda9-4cf9-ab5fb5012dbe77d7/202606/mueren-tres-personas-en-un-ataque-de-israel-contra-el-libano",
      "published_at": "",
      "language": null,
      "source_lang": null,
      "provider": "gdelt_gkg_geojson",
      "themes": [
        "CEASEFIRE",
        "SOC_EXPRESSREGRET",
        "TAX_FNCACT_AUTHORITIES",
        "EPU_POLICY_AUTHORITIES",
        "MILITARY",
        "CRISISLEX_CRISISLEXREC",
        "KILL",
        "CRISISLEX_T03_DEAD",
        "ECON_MOU"
      ]
    },
    {
      "title": "Colombia",
      "title_en": null,
      "source": "www.diariodelsur.com.co",
      "url": "https://www.diariodelsur.com.co/gentrificacion-en-colombia-por-que-el-problema-va-mucho-mas-alla-del-turismo/",
      "published_at": "",
      "language": null,
      "source_lang": null,
      "provider": "gdelt_gkg_geojson",
      "themes": [
        "TAX_WORLDLANGUAGES_LATIN",
        "ECON_HOUSING_PRICES",
        "URBAN",
        "URBAN",
        "GENTRIFICATION",
        "TAX_ETHNICITY_INDIAN",
        "TOURISM",
        "WB_825_TOURISM",
        "WB_1921_PRIVATE_SECTOR_DEVELOPMENT",
        "WB_346_COMPETITIVE_INDUSTRIES",
        "WB_818_INDUSTRY_POLICY_AND_REAL_SECTORS"
      ]
    },
    {
      "title": "South Korea",
      "title_en": null,
      "source": "techno.viva.co.id",
      "url": "https://techno.viva.co.id/platform/30763-gila-harga-hp-bakal-naik-lagi-sampai-2030-bos-nvidia-buka-suara",
      "published_at": "",
      "language": null,
      "source_lang": null,
      "provider": "gdelt_gkg_geojson",
      "themes": [
        "TAX_FNCACT_EMPLOYEES",
        "TAX_ECON_PRICE",
        "TAX_ECON_PRICE",
        "ECON_STOCKMARKET",
        "ECON_STOCKMARKET",
        "USPEC_POLITICS_GENERAL1",
        "CRISISLEX_CRISISLEXREC"
      ]
    },
    {
      "title": "California, United States",
      "title_en": null,
      "source": "www.europapress.es",
      "url": "https://www.europapress.es/comunicados/empresas-00908/noticia-comunicado-cada-vez-mas-personas-barcelona-eligen-masaje-californiano-frente-masajes-tradicionales-20260625164725.html",
      "published_at": "",
      "language": null,
      "source_lang": null,
      "provider": "gdelt_gkg_geojson",
      "themes": [
        "USPEC_POLICY1",
        "EPU_POLICY_REGULATION",
        "EPU_CATS_REGULATION",
        "IDEOLOGY",
        "IDEOLOGY",
        "WB_1614_NUTRITIONAL_PROGRAMS",
        "WB_1609_FOOD_AND_IN_KIND_TRANSFERS",
        "WB_1615_THERAPEUTIC",
        "WB_1466_SOCIAL_ASSISTANCE",
        "WB_697_SOCIAL_PROTECTION_AND_LABOR",
        "ECON_ENTREPRENEURSHIP"
      ]
    },
    {
      "title": "Brazil",
      "title_en": null,
      "source": "www.chinanationalnews.com",
      "url": "http://www.chinanationalnews.com/news/279147107/pacific-avenue-capital-partners-announces-investment-committee-appointment-new-ai-initiative-and-team-expansion",
      "published_at": "",
      "language": null,
      "source_lang": null,
      "provider": "gdelt_gkg_geojson",
      "themes": [
        "EPU_POLICY_POLITICAL",
        "SCIENCE",
        "LEADER",
        "TAX_FNCACT_PRESIDENT",
        "TAX_FNCACT_VICE_PRESIDENT",
        "TAX_FNCACT_MANAGER",
        "TAX_FNCACT_MANAGER",
        "EPU_ECONOMY_HISTORIC"
      ]
    },
    {
      "title": "Clearlake, California, United States",
      "title_en": null,
      "source": "www.chinanationalnews.com",
      "url": "http://www.chinanationalnews.com/news/279147107/pacific-avenue-capital-partners-announces-investment-committee-appointment-new-ai-initiative-and-team-expansion",
      "published_at": "",
      "language": null,
      "source_lang": null,
      "provider": "gdelt_gkg_geojson",
      "themes": [
        "EPU_POLICY_POLITICAL",
        "SCIENCE",
        "TAX_FNCACT_MANAGER",
        "TAX_FNCACT_MANAGER",
        "SOC_POINTSOFINTEREST_UNIVERSITY",
        "EPU_ECONOMY_HISTORIC"
      ]
    },
    {
      "title": "Netherlands",
      "title_en": null,
      "source": "www.capital.gr",
      "url": "https://www.capital.gr/diethni/4000671/germania-nauagise-to-sxedio-gia-tis-ollandikes-fregates/",
      "published_at": "",
      "language": null,
      "source_lang": null,
      "provider": "gdelt_gkg_geojson",
      "themes": [
        "TAX_WEAPONS_BATTLESHIPS",
        "TAX_ETHNICITY_DUTCH",
        "TAX_WORLDLANGUAGES_DUTCH",
        "TAX_ETHNICITY_DUTCH",
        "TAX_WORLDLANGUAGES_DUTCH",
        "TAX_ECON_PRICE",
        "UNREST_BELLIGERENT",
        "MILITARY",
        "TAX_FNCACT_NAVY",
        "USPEC_POLICY1",
        "EPU_POLICY_BUDGET",
        "UNGP_FORESTS_RIVERS_OCEANS"
      ]
    },
    {
      "title": "Port Washington, Wisconsin, United States",
      "title_en": null,
      "source": "www.eenews.net",
      "url": "https://www.eenews.net/articles/tech-heavyweight-oracle-challenges-wisconsin-data-center-rules-2/",
      "published_at": "",
      "language": null,
      "source_lang": null,
      "provider": "gdelt_gkg_geojson",
      "themes": [
        "TAX_ECON_PRICE",
        "TRIAL",
        "NATURAL_DISASTER_CHILL",
        "WB_135_TRANSPORT",
        "WB_1803_TRANSPORT_INFRASTRUCTURE",
        "WB_167_PORTS"
      ]
    },
    {
      "title": "Wisconsin, United States",
      "title_en": null,
      "source": "www.eenews.net",
      "url": "https://www.eenews.net/articles/tech-heavyweight-oracle-challenges-wisconsin-data-center-rules-2/",
      "published_at": "",
      "language": null,
      "source_lang": null,
      "provider": "gdelt_gkg_geojson",
      "themes": [
        "TAX_ECON_PRICE",
        "TRIAL",
        "NATURAL_DISASTER_CHILL",
        "WB_135_TRANSPORT",
        "WB_1803_TRANSPORT_INFRASTRUCTURE",
        "WB_167_PORTS",
        "CRISISLEX_C07_SAFETY"
      ]
    },
    {
      "title": "Turkey",
      "title_en": null,
      "source": "www.bloomberght.com",
      "url": "https://www.bloomberght.com/emlak-konut-gyo-da-girisim-sermayesi-yatirim-fonu-karari-3781189",
      "published_at": "",
      "language": null,
      "source_lang": null,
      "provider": "gdelt_gkg_geojson",
      "themes": [
        "WB_566_ENVIRONMENT_AND_NATURAL_RESOURCES",
        "WB_590_ECOSYSTEMS",
        "UNGP_FORESTS_RIVERS_OCEANS",
        "WB_336_NON_BANK_FINANCIAL_INSTITUTIONS",
        "WB_341_INVESTMENT_FUNDS",
        "WB_1920_FINANCIAL_SECTOR_DEVELOPMENT",
        "WB_332_CAPITAL_MARKETS",
        "WB_336_NON_BANK_FINANCIAL_INSTITUTIONS",
        "WB_341_INVESTMENT_FUNDS",
        "WB_1920_FINANCIAL_SECTOR_DEVELOPMENT",
        "WB_332_CAPITAL_MARKETS",
        "ECON_ENTREPRENEURSHIP",
        "ECON_HOUSING_PRICES",
        "ECON_HOUSING_PRICES",
        "ECON_HOUSING_PRICES",
        "ECON_HOUSING_PRICES"
      ]
    },
    {
      "title": "Istanbul, Istanbul, Turkey",
      "title_en": null,
      "source": "www.bloomberght.com",
      "url": "https://www.bloomberght.com/emlak-konut-gyo-da-girisim-sermayesi-yatirim-fonu-karari-3781189",
      "published_at": "",
      "language": null,
      "source_lang": null,
      "provider": "gdelt_gkg_geojson",
      "themes": [
        "WB_566_ENVIRONMENT_AND_NATURAL_RESOURCES",
        "WB_590_ECOSYSTEMS",
        "UNGP_FORESTS_RIVERS_OCEANS",
        "WB_336_NON_BANK_FINANCIAL_INSTITUTIONS",
        "WB_341_INVESTMENT_FUNDS",
        "WB_1920_FINANCIAL_SECTOR_DEVELOPMENT",
        "WB_332_CAPITAL_MARKETS",
        "WB_336_NON_BANK_FINANCIAL_INSTITUTIONS",
        "WB_341_INVESTMENT_FUNDS",
        "WB_1920_FINANCIAL_SECTOR_DEVELOPMENT",
        "WB_332_CAPITAL_MARKETS",
        "ECON_ENTREPRENEURSHIP",
        "ECON_HOUSING_PRICES",
        "ECON_HOUSING_PRICES",
        "ECON_HOUSING_PRICES",
        "ECON_HOUSING_PRICES"
      ]
    },
    {
      "title": "Greece",
      "title_en": null,
      "source": "techmaniacs.gr",
      "url": "https://techmaniacs.gr/vodafone-kovei-tin-aperioristi-omilia-sta-mikrotera-paketa/",
      "published_at": "",
      "language": null,
      "source_lang": null,
      "provider": "gdelt_gkg_geojson",
      "themes": [
        "AFFECT",
        "TAX_ECON_PRICE"
      ]
    },
    {
      "title": "Tullamore, Offaly, Ireland",
      "title_en": null,
      "source": "www.westmeathindependent.ie",
      "url": "https://www.westmeathindependent.ie/2026/06/25/sustainable-livestock-village-returns-to-tullamore-show/",
      "published_at": "",
      "language": null,
      "source_lang": null,
      "provider": "gdelt_gkg_geojson",
      "themes": [
        "TAX_FNCACT_FARMERS",
        "EPU_ECONOMY",
        "EPU_ECONOMY_HISTORIC",
        "AGRICULTURE",
        "WB_435_AGRICULTURE_AND_FOOD_SECURITY",
        "WB_177_ANIMAL_PRODUCTION",
        "WB_1949_CLIMATE_SMART_AGRICULTURE",
        "AGRICULTURE",
        "WB_435_AGRICULTURE_AND_FOOD_SECURITY",
        "WB_177_ANIMAL_PRODUCTION",
        "WB_1949_CLIMATE_SMART_AGRICULTURE",
        "UNGP_FORESTS_RIVERS_OCEANS",
        "UNGP_FORESTS_RIVERS_OCEANS",
        "UNGP_FORESTS_RIVERS_OCEANS"
      ]
    },
    {
      "title": "Ukraine",
      "title_en": null,
      "source": "society.comments.ua",
      "url": "https://society.comments.ua/news/warrussia/ukrainu-predupredili-o-strashnom-porazhenii-v-voyne-ozvuchen-potryasayuschiy-prognoz-809624.html",
      "published_at": "",
      "language": null,
      "source_lang": null,
      "provider": "gdelt_gkg_geojson",
      "themes": [
        "ARMEDCONFLICT",
        "EPU_CATS_NATIONAL_SECURITY",
        "TAX_ECON_PRICE",
        "TAX_ETHNICITY_UKRAINIANS",
        "TAX_WORLDLANGUAGES_UKRAINIANS",
        "CRISISLEX_T02_INJURED",
        "TAX_FNCACT_VICTIMS",
        "CRISISLEX_T08_MISSINGFOUNDTRAPPEDPEOPLE",
        "TAX_RELIGION_CHRISTIANITY",
        "RELIGION",
        "TAX_RELIGION_ORTHODOXY",
        "TAX_FNCACT_OFFICIAL"
      ]
    },
    {
      "title": "Crimea, Krym, Avtonomna Respublika, Ukraine",
      "title_en": null,
      "source": "society.comments.ua",
      "url": "https://society.comments.ua/news/warrussia/ukrainu-predupredili-o-strashnom-porazhenii-v-voyne-ozvuchen-potryasayuschiy-prognoz-809624.html",
      "published_at": "",
      "language": null,
      "source_lang": null,
      "provider": "gdelt_gkg_geojson",
      "themes": [
        "TAX_FNCACT_SECRETARY",
        "TAX_ECON_PRICE",
        "CRISISLEX_T02_INJURED",
        "TAX_FNCACT_VICTIMS",
        "CRISISLEX_T08_MISSINGFOUNDTRAPPEDPEOPLE",
        "MEDIA_MSM",
        "TAX_FNCACT_JOURNALIST"
      ]
    },
    {
      "title": "Tehran, Tehran, Iran",
      "title_en": null,
      "source": "www.lifo.gr",
      "url": "https://www.lifo.gr/now/world/o-tramp-zita-disekatommyria-apo-kogkreso-gia-ton-polemo-sto-iran-meta-ti-rixi-me-toys",
      "published_at": "",
      "language": null,
      "source_lang": null,
      "provider": "gdelt_gkg_geojson",
      "themes": [
        "TAX_POLITICAL_PARTY_REPUBLICAN",
        "EPU_CATS_MIGRATION_FEAR_FEAR",
        "WB_1160_SHOCKS_AND_VULNERABILITY",
        "WB_695_POVERTY",
        "AGRICULTURE",
        "TAX_FNCACT_FARMERS",
        "TAX_POLITICAL_PARTY_REPUBLICAN_PARTY",
        "USPEC_POLICY1",
        "EPU_POLICY_BUDGET",
        "ARMEDCONFLICT",
        "EPU_CATS_NATIONAL_SECURITY",
        "TAX_DISEASE_EBOLA",
        "WB_1406_DISEASES",
        "WB_1415_COMMUNICABLE_DISEASE",
        "WB_2663_EBOLA",
        "ECON_STOCKMARKET",
        "ECON_STOCKMARKET",
        "TAX_DISEASE_EPIDEMIC",
        "WB_635_PUBLIC_HEALTH",
        "WB_2165_HEALTH_EMERGENCIES",
        "WB_2166_HEALTH_EMERGENCY_PREPAREDNESS_AND_DISASTER_RESPONSE",
        "WB_621_HEALTH_NUTRITION_AND_POPULATION",
        "WB_2167_PANDEMICS",
        "CEASEFIRE"
      ]
    },
    {
      "title": "Vietnam",
      "title_en": null,
      "source": "baovanhoa.vn",
      "url": "https://baovanhoa.vn/xe/bang-gia-xe-may-dien-honda-thang-62026-co-chiec-giam-den-22-trieu-dong-240269.html",
      "published_at": "",
      "language": null,
      "source_lang": null,
      "provider": "gdelt_gkg_geojson",
      "themes": [
        "TAX_ECON_PRICE",
        "TAX_ECON_PRICE",
        "TAX_ECON_PRICE"
      ]
    },
    {
      "title": "Los Palos Grandes, Miranda, Venezuela",
      "title_en": null,
      "source": "www.oann.com",
      "url": "https://www.oann.com/newsroom/back-to-back-massive-earthquakes-rock-venezuela-devastating-estimated-death-toll/",
      "published_at": "",
      "language": null,
      "source_lang": null,
      "provider": "gdelt_gkg_geojson",
      "themes": [
        "MANMADE_DISASTER_IMPLIED",
        "MANMADE_DISASTER_IMPLIED",
        "EPU_ECONOMY",
        "EPU_ECONOMY_HISTORIC",
        "CRISISLEX_C04_LOGISTICS_TRANSPORT",
        "CRISISLEX_C04_LOGISTICS_TRANSPORT",
        "NATURAL_DISASTER_EARTHQUAKES",
        "CRISISLEX_T01_CAUTION_ADVICE",
        "NATURAL_DISASTER_EARTHQUAKES",
        "CRISISLEX_T01_CAUTION_ADVICE",
        "AFFECT",
        "EVACUATION",
        "AFFECT",
        "EVACUATION",
        "GENERAL_HEALTH",
        "WB_635_PUBLIC_HEALTH",
        "WB_2165_HEALTH_EMERGENCIES",
        "WB_621_HEALTH_NUTRITION_AND_POPULATION",
        "WB_1324_EMERGENCY_MEDICAL_SERVICES",
        "GENERAL_HEALTH",
        "WB_635_PUBLIC_HEALTH",
        "WB_2165_HEALTH_EMERGENCIES",
        "WB_621_HEALTH_NUTRITION_AND_POPULATION",
        "WB_1324_EMERGENCY_MEDICAL_SERVICES",
        "CRISISLEX_CRISISLEXREC",
        "CRISISLEX_CRISISLEXREC"
      ]
    },
    {
      "title": "Cyprus",
      "title_en": null,
      "source": "brtk.net",
      "url": "https://brtk.net/ktamstan-aciklama-gecici-ve-sozlesmeli-personelin-sinavsiz-ust-kademe-yoneticisi-atanmasi-kabul-edilemez/",
      "published_at": "",
      "language": null,
      "source_lang": null,
      "provider": "gdelt_gkg_geojson",
      "themes": [
        "ECON_UNIONS",
        "TAX_FNCACT_PUBLIC_SERVANTS",
        "TAX_FNCACT_SERVANTS",
        "TAX_FNCACT_PUBLIC_SERVANTS",
        "TAX_FNCACT_SERVANTS",
        "TAX_FNCACT_STAGE_MANAGER",
        "TAX_FNCACT_MANAGER",
        "APPOINTMENT",
        "APPOINTMENT",
        "TAX_FNCACT_LABORERS",
        "TAX_FNCACT_MANAGER",
        "TAX_FNCACT_DIRECTOR"
      ]
    },
    {
      "title": "Timis, Romania (General), Romania",
      "title_en": null,
      "source": "www.ziuadevest.ro",
      "url": "https://www.ziuadevest.ro/firma-si-doi-administratori-trimisi-in-judecata-in-timis-pentru-abandonarea-ilegala-a-deseurilor-si-evaziune-fiscala-prejudiciu-de-peste-137-000-de-lei/",
      "published_at": "",
      "language": null,
      "source_lang": null,
      "provider": "gdelt_gkg_geojson",
      "themes": [
        "TRIAL",
        "TAX_FNCACT_PROSECUTORS",
        "WB_1428_INJURY",
        "WB_1406_DISEASES",
        "WB_621_HEALTH_NUTRITION_AND_POPULATION",
        "WB_1427_NON_COMMUNICABLE_DISEASE_AND_INJURY",
        "TAX_FNCACT_ADMINISTRATORS",
        "TAX_FNCACT_ADMINISTRATORS",
        "WB_2024_ANTI_CORRUPTION_AUTHORITIES",
        "WB_696_PUBLIC_SECTOR_MANAGEMENT",
        "WB_840_JUSTICE",
        "WB_2025_INVESTIGATION",
        "WB_831_GOVERNANCE",
        "WB_832_ANTI_CORRUPTION",
        "WB_1014_CRIMINAL_JUSTICE",
        "ECON_TAXATION",
        "USPEC_POLICY1",
        "EPU_POLICY_TAX",
        "EPU_CATS_TAXES",
        "ECON_TAXATION",
        "USPEC_POLICY1",
        "EPU_POLICY_TAX",
        "EPU_CATS_TAXES"
      ]
    },
    {
      "title": "Ayhan, Nevsehir, Turkey",
      "title_en": null,
      "source": "brtk.net",
      "url": "https://brtk.net/basbakan-ustel-yasli-yasam-merkezi-ulke-icin-guzel-bir-yatirim/",
      "published_at": "",
      "language": null,
      "source_lang": null,
      "provider": "gdelt_gkg_geojson",
      "themes": [
        "WB_1609_FOOD_AND_IN_KIND_TRANSFERS",
        "WB_1620_ELDERLY",
        "WB_1466_SOCIAL_ASSISTANCE",
        "WB_1618_FOOD_DISTRIBUTION",
        "WB_697_SOCIAL_PROTECTION_AND_LABOR",
        "TAX_WORLDMAMMALS_HORSE",
        "EPU_ECONOMY_HISTORIC",
        "EPU_ECONOMY_HISTORIC",
        "TAX_FNCACT_DIRECTOR"
      ]
    },
    {
      "title": "Cuba",
      "title_en": null,
      "source": "www.excelsior.com.mx",
      "url": "https://www.excelsior.com.mx/internacional/diaz-canel-acusa-estados-unidos-guerra-despiadada-contra-cuba",
      "published_at": "",
      "language": null,
      "source_lang": null,
      "provider": "gdelt_gkg_geojson",
      "themes": [
        "TAX_FNCACT_SECRETARY",
        "LEADER",
        "TAX_FNCACT_PRESIDENT",
        "USPEC_POLITICS_GENERAL1",
        "EPU_ECONOMY",
        "EPU_ECONOMY_HISTORIC",
        "ECON_TAXATION",
        "USPEC_POLICY1",
        "EPU_POLICY_TAX",
        "EPU_CATS_TAXES",
        "TAX_FNCACT_SECRETARY_OF_STATE"
      ]
    },
    {
      "title": "Peru",
      "title_en": null,
      "source": "www.zazoom.it",
      "url": "https://www.zazoom.it/2026-06-25/in-peru-tutto-ruota-intorno-ai-fujimori/19388520/",
      "published_at": "",
      "language": null,
      "source_lang": null,
      "provider": "gdelt_gkg_geojson",
      "themes": [
        "TAX_FNCACT_SUPPORTERS",
        "EPU_ECONOMY",
        "EPU_ECONOMY_HISTORIC",
        "TAX_FNCACT_CANDIDATE",
        "TAX_FNCACT_FATHER",
        "TERROR",
        "WB_2467_TERRORISM",
        "WB_2433_CONFLICT_AND_VIOLENCE",
        "WB_2432_FRAGILITY_CONFLICT_AND_VIOLENCE",
        "WB_2462_POLITICAL_VIOLENCE_AND_WAR",
        "EPU_CATS_NATIONAL_SECURITY",
        "TAX_FNCACT_DICTATOR",
        "SLFID_DICTATORSHIP",
        "ELECTION",
        "ELECTION",
        "CORRUPTION"
      ]
    },
    {
      "title": "Afghanistan",
      "title_en": null,
      "source": "www.bostonglobe.com",
      "url": "https://www.bostonglobe.com/2026/06/25/nation/graham-platner-susan-collins/",
      "published_at": "",
      "language": null,
      "source_lang": null,
      "provider": "gdelt_gkg_geojson",
      "themes": [
        "TAX_POLITICAL_PARTY_REPUBLICAN",
        "TAX_FNCACT_OFFICIALS",
        "EPU_ECONOMY_HISTORIC",
        "TAX_FNCACT_SENATOR",
        "TAX_FNCACT_SENATOR",
        "GENERAL_GOVERNMENT",
        "EPU_POLICY_CONGRESS",
        "TAX_FNCACT_VETERAN",
        "EPU_POLICY_LEGISLATION"
      ]
    },
    {
      "title": "Florida, United States",
      "title_en": null,
      "source": "www.bostonglobe.com",
      "url": "https://www.bostonglobe.com/2026/06/25/nation/graham-platner-susan-collins/",
      "published_at": "",
      "language": null,
      "source_lang": null,
      "provider": "gdelt_gkg_geojson",
      "themes": [
        "TAX_POLITICAL_PARTY_REPUBLICAN",
        "TAX_FNCACT_OFFICIALS",
        "EPU_ECONOMY_HISTORIC",
        "TAX_FNCACT_SENATOR",
        "TAX_FNCACT_SENATOR",
        "GENERAL_GOVERNMENT",
        "EPU_POLICY_CONGRESS",
        "TAX_FNCACT_VETERAN",
        "EPU_POLICY_LEGISLATION"
      ]
    },
    {
      "title": "Iraq",
      "title_en": null,
      "source": "www.bostonglobe.com",
      "url": "https://www.bostonglobe.com/2026/06/25/nation/graham-platner-susan-collins/",
      "published_at": "",
      "language": null,
      "source_lang": null,
      "provider": "gdelt_gkg_geojson",
      "themes": [
        "TAX_POLITICAL_PARTY_REPUBLICAN",
        "TAX_FNCACT_OFFICIALS",
        "EPU_ECONOMY_HISTORIC",
        "TAX_FNCACT_SENATOR",
        "TAX_FNCACT_SENATOR",
        "GENERAL_GOVERNMENT",
        "EPU_POLICY_CONGRESS",
        "TAX_FNCACT_VETERAN",
        "EPU_POLICY_LEGISLATION"
      ]
    },
    {
      "title": "Slovak Republic",
      "title_en": null,
      "source": "hnonline.sk",
      "url": "https://hnonline.sk/slovensko/96288485-prieskum-ipsosu-hlas-sa-prepadol-aliancia-si-po-rokovaniach-s-progresivcami-polepsila",
      "published_at": "",
      "language": null,
      "source_lang": null,
      "provider": "gdelt_gkg_geojson",
      "themes": [
        "TAX_POLITICAL_PARTY_DEMOCRATS",
        "USPEC_POLITICS_GENERAL1",
        "ALLIANCE",
        "ECON_STOCKMARKET",
        "ECON_STOCKMARKET",
        "TAX_WORLDLANGUAGES_SLOVAK"
      ]
    },
    {
      "title": "Hungary",
      "title_en": null,
      "source": "hnonline.sk",
      "url": "https://hnonline.sk/slovensko/96288485-prieskum-ipsosu-hlas-sa-prepadol-aliancia-si-po-rokovaniach-s-progresivcami-polepsila",
      "published_at": "",
      "language": null,
      "source_lang": null,
      "provider": "gdelt_gkg_geojson",
      "themes": [
        "TAX_POLITICAL_PARTY_DEMOCRATS",
        "USPEC_POLITICS_GENERAL1",
        "ALLIANCE",
        "ECON_STOCKMARKET",
        "ECON_STOCKMARKET",
        "TAX_WORLDLANGUAGES_SLOVAK"
      ]
    },
    {
      "title": "Athens, AttikíR, Greece",
      "title_en": null,
      "source": "metro.co.uk",
      "url": "https://metro.co.uk/2026/06/25/shady-spyware-firm-linked-hacking-journalists-held-talks-uk-officials-28917089/",
      "published_at": "",
      "language": null,
      "source_lang": null,
      "provider": "gdelt_gkg_geojson",
      "themes": [
        "SURVEILLANCE",
        "TAX_FNCACT_EXECUTIVES",
        "TAX_FNCACT_BUSINESS_EXECUTIVES",
        "TAX_FNCACT_DEVELOPER",
        "EPU_ECONOMY_HISTORIC",
        "TAX_FNCACT_SPY",
        "SLFID_DICTATORSHIP",
        "CYBER_ATTACK",
        "GENERAL_GOVERNMENT",
        "TAX_FNCACT_SALESMEN",
        "TAX_FNCACT_EMPLOYEE",
        "TAX_FNCACT_OFFICIALS"
      ]
    },
    {
      "title": "Hong Kong",
      "title_en": null,
      "source": "www.legaldaily.com.cn",
      "url": "http://www.legaldaily.com.cn/index_article/content/2026-06/25/content_9412843.html",
      "published_at": "",
      "language": null,
      "source_lang": null,
      "provider": "gdelt_gkg_geojson",
      "themes": [
        "TAX_FNCACT_CHAIRMAN",
        "TAX_FNCACT_CHAIRMAN",
        "CONSTITUTIONAL",
        "LEGISLATION",
        "EPU_POLICY_LAW",
        "LEGISLATION",
        "EPU_POLICY_LAW",
        "WB_135_TRANSPORT",
        "WB_1803_TRANSPORT_INFRASTRUCTURE",
        "WB_167_PORTS",
        "WB_135_TRANSPORT",
        "WB_1803_TRANSPORT_INFRASTRUCTURE",
        "WB_167_PORTS",
        "USPEC_POLICY1",
        "EPU_ECONOMY",
        "EPU_ECONOMY_HISTORIC",
        "WB_678_DIGITAL_GOVERNMENT",
        "WB_670_ICT_SECURITY",
        "WB_2372_AUTHENTICATION_AND_AUTHORIZATION",
        "WB_133_INFORMATION_AND_COMMUNICATION_TECHNOLOGIES",
        "USPEC_POLITICS_GENERAL1",
        "USPEC_POLITICS_GENERAL1",
        "TAX_FNCACT_ACCOUNTANT"
      ]
    },
    {
      "title": "Huanggang, Jiangxi, China",
      "title_en": null,
      "source": "www.legaldaily.com.cn",
      "url": "http://www.legaldaily.com.cn/index_article/content/2026-06/25/content_9412843.html",
      "published_at": "",
      "language": null,
      "source_lang": null,
      "provider": "gdelt_gkg_geojson",
      "themes": [
        "TAX_FNCACT_CHAIRMAN",
        "TAX_FNCACT_CHAIRMAN",
        "TAX_FNCACT_CHAIRMAN",
        "CONSTITUTIONAL",
        "TAX_FNCACT_DEPUTY",
        "LEGISLATION",
        "EPU_POLICY_LAW",
        "LEGISLATION",
        "EPU_POLICY_LAW",
        "WB_135_TRANSPORT",
        "WB_1803_TRANSPORT_INFRASTRUCTURE",
        "WB_167_PORTS",
        "WB_135_TRANSPORT",
        "WB_1803_TRANSPORT_INFRASTRUCTURE",
        "WB_167_PORTS",
        "USPEC_POLICY1",
        "EPU_ECONOMY",
        "EPU_ECONOMY_HISTORIC",
        "WB_678_DIGITAL_GOVERNMENT",
        "WB_670_ICT_SECURITY",
        "WB_2372_AUTHENTICATION_AND_AUTHORIZATION",
        "WB_133_INFORMATION_AND_COMMUNICATION_TECHNOLOGIES",
        "USPEC_POLITICS_GENERAL1",
        "USPEC_POLITICS_GENERAL1",
        "TAX_FNCACT_ACCOUNTANT"
      ]
    },
    {
      "title": "Baia Formosa, Rio Grande Do Norte, Brazil",
      "title_en": null,
      "source": "g1.globo.com",
      "url": "https://g1.globo.com/rn/rio-grande-do-norte/noticia/2026/06/25/cuidadora-marido-suspeitos-furto-cartoes-idosos.ghtml",
      "published_at": "",
      "language": null,
      "source_lang": null,
      "provider": "gdelt_gkg_geojson",
      "themes": [
        "TAX_FNCACT_CRIMINAL",
        "DELAY",
        "USPEC_UNCERTAINTY1",
        "TRIAL",
        "CORRUPTION",
        "ECON_MONEYLAUNDERING",
        "WB_2076_MONEY_LAUNDERING",
        "WB_1920_FINANCIAL_SECTOR_DEVELOPMENT",
        "WB_328_FINANCIAL_INTEGRITY",
        "TAX_FNCACT_BUSINESSMAN",
        "WB_1160_SHOCKS_AND_VULNERABILITY",
        "WB_695_POVERTY",
        "ARMEDCONFLICT",
        "EPU_CATS_MIGRATION_FEAR_FEAR"
      ]
    },
    {
      "title": "North Korea",
      "title_en": null,
      "source": "biz.heraldcorp.com",
      "url": "https://biz.heraldcorp.com/article/10788607",
      "published_at": "",
      "language": null,
      "source_lang": null,
      "provider": "gdelt_gkg_geojson",
      "themes": [
        "WB_696_PUBLIC_SECTOR_MANAGEMENT",
        "WB_723_PUBLIC_ADMINISTRATION",
        "CRISISLEX_C07_SAFETY",
        "TAX_FNCACT_PRESIDENT",
        "USPEC_POLITICS_GENERAL1",
        "TAX_FNCACT_STUDENTS",
        "TAX_FNCACT_STUDENTS",
        "TAX_FNCACT_MINISTER",
        "ECON_STOCKMARKET",
        "TAX_FNCACT_GOVERNOR",
        "APPOINTMENT",
        "TAX_FNCACT_FATHER",
        "TAX_FNCACT_OFFICIALS",
        "TAX_ETHNICITY_KOREAN",
        "TAX_WORLDLANGUAGES_KOREAN"
      ]
    },
    {
      "title": "Iceland",
      "title_en": null,
      "source": "www.somersetlive.co.uk",
      "url": "https://www.somersetlive.co.uk/whats-on/whats-on-news/win-all-shook-up-picnic-11030611",
      "published_at": "",
      "language": null,
      "source_lang": null,
      "provider": "gdelt_gkg_geojson",
      "themes": [
        "ECON_STOCKMARKET"
      ]
    },
    {
      "title": "Veneto, Veneto, Italy",
      "title_en": null,
      "source": "www.bellunopress.it",
      "url": "https://www.bellunopress.it/2026/06/25/massimiliano-paglini-e-il-nuovo-reggente-della-cisl-belluno-treviso/",
      "published_at": "",
      "language": null,
      "source_lang": null,
      "provider": "gdelt_gkg_geojson",
      "themes": [
        "EPU_ECONOMY_HISTORIC",
        "EPU_ECONOMY_HISTORIC",
        "ECON_UNIONS",
        "WB_1668_LABOR_STANDARDS",
        "WB_855_LABOR_MARKETS",
        "WB_1670_TRADE_UNIONS",
        "WB_697_SOCIAL_PROTECTION_AND_LABOR",
        "TAX_FNCACT_SECRETARY",
        "TAX_FNCACT_SECRETARY",
        "UNGP_FORESTS_RIVERS_OCEANS",
        "TAX_FNCACT_SECRETARY_GENERAL",
        "WB_698_TRADE"
      ]
    },
    {
      "title": "Shanghai, Shanghai, China",
      "title_en": null,
      "source": "finance.sina.com.cn",
      "url": "https://finance.sina.com.cn/tech/csj/2026-06-25/doc-inieryen5517441.shtml",
      "published_at": "",
      "language": null,
      "source_lang": null,
      "provider": "gdelt_gkg_geojson",
      "themes": [
        "EPU_ECONOMY_HISTORIC"
      ]
    },
    {
      "title": "China",
      "title_en": null,
      "source": "finance.sina.com.cn",
      "url": "https://finance.sina.com.cn/tech/csj/2026-06-25/doc-inieryen5517441.shtml",
      "published_at": "",
      "language": null,
      "source_lang": null,
      "provider": "gdelt_gkg_geojson",
      "themes": [
        "EPU_ECONOMY_HISTORIC"
      ]
    },
    {
      "title": "Bratislava, Bratislavsky Kraj, Slovak Republic",
      "title_en": null,
      "source": "www.teraz.sk",
      "url": "https://www.teraz.sk/ekonomika/analytik-ceny-pohonnych-latok-v-sr-za/973239-clanok.html",
      "published_at": "",
      "language": null,
      "source_lang": null,
      "provider": "gdelt_gkg_geojson",
      "themes": [
        "NEGOTIATIONS",
        "WB_696_PUBLIC_SECTOR_MANAGEMENT",
        "WB_840_JUSTICE",
        "WB_2473_DIPLOMACY_AND_NEGOTIATIONS",
        "WB_939_NEGOTIATION",
        "WB_2470_PEACE_OPERATIONS_AND_CONFLICT_MANAGEMENT",
        "WB_936_ALTERNATIVE_DISPUTE_RESOLUTION",
        "WB_2432_FRAGILITY_CONFLICT_AND_VIOLENCE",
        "WB_843_DISPUTE_RESOLUTION",
        "WB_2471_PEACEKEEPING",
        "GENERAL_GOVERNMENT",
        "TAX_FNCACT_ECONOMIST",
        "TAX_WORLDLANGUAGES_SLOVAK",
        "TAX_WORLDLANGUAGES_SLOVAK",
        "TAX_ECON_PRICE",
        "TAX_ECON_PRICE",
        "TAX_ECON_PRICE",
        "ENV_OIL"
      ]
    },
    {
      "title": "Tembisa, Gauteng, South Africa",
      "title_en": null,
      "source": "www.nigeriasun.com",
      "url": "http://www.nigeriasun.com/news/279146965/calls-for-peace-social-cohesion-resonate-in-south-african-townships-ahead-of-anti-immigration-protests",
      "published_at": "",
      "language": null,
      "source_lang": null,
      "provider": "gdelt_gkg_geojson",
      "themes": [
        "EPU_ECONOMY_HISTORIC"
      ]
    },
    {
      "title": "Diepsloot, Mpumalanga, South Africa",
      "title_en": null,
      "source": "www.nigeriasun.com",
      "url": "http://www.nigeriasun.com/news/279146965/calls-for-peace-social-cohesion-resonate-in-south-african-townships-ahead-of-anti-immigration-protests",
      "published_at": "",
      "language": null,
      "source_lang": null,
      "provider": "gdelt_gkg_geojson",
      "themes": [
        "DISCRIMINATION_IMMIGRATION_ANTIIMMIGRATION",
        "EPU_ECONOMY_HISTORIC"
      ]
    },
    {
      "title": "Soweto, Gauteng, South Africa",
      "title_en": null,
      "source": "www.nigeriasun.com",
      "url": "http://www.nigeriasun.com/news/279146965/calls-for-peace-social-cohesion-resonate-in-south-african-townships-ahead-of-anti-immigration-protests",
      "published_at": "",
      "language": null,
      "source_lang": null,
      "provider": "gdelt_gkg_geojson",
      "themes": [
        "EPU_ECONOMY_HISTORIC"
      ]
    },
    {
      "title": "Johannesburg, Gauteng, South Africa",
      "title_en": null,
      "source": "www.nigeriasun.com",
      "url": "http://www.nigeriasun.com/news/279146965/calls-for-peace-social-cohesion-resonate-in-south-african-townships-ahead-of-anti-immigration-protests",
      "published_at": "",
      "language": null,
      "source_lang": null,
      "provider": "gdelt_gkg_geojson",
      "themes": [
        "WB_738_SOCIAL_COHESION",
        "WB_134_SOCIAL_DEVELOPMENT",
        "DISCRIMINATION_IMMIGRATION_ANTIIMMIGRATION",
        "EPU_ECONOMY",
        "EPU_ECONOMY_HISTORIC"
      ]
    },
    {
      "title": "Australia",
      "title_en": null,
      "source": "www.thetottenhamindependent.co.uk",
      "url": "https://www.thetottenhamindependent.co.uk/news/national/26227595.uk-needs-boldness-tackle-underinvestment-uk-firms---former-bank-economist/",
      "published_at": "",
      "language": null,
      "source_lang": null,
      "provider": "gdelt_gkg_geojson",
      "themes": [
        "WB_611_PENSION_FUNDS",
        "WB_611_PENSION_FUNDS",
        "TAX_ETHNICITY_CANADIAN",
        "ECON_TAXATION",
        "USPEC_POLICY1",
        "EPU_POLICY_TAX",
        "EPU_CATS_TAXES",
        "GENERAL_GOVERNMENT",
        "EPU_POLICY_GOVERNMENT",
        "RETIREMENT",
        "RETIREMENT",
        "RETIREMENT",
        "RETIREMENT",
        "RETIREMENT",
        "TAX_ETHNICITY_AUSTRALIAN"
      ]
    },
    {
      "title": "Lecce, Puglia, Italy",
      "title_en": null,
      "source": "www.corrieredelsud.it",
      "url": "https://www.corrieredelsud.it/nsite/2016-07-15-06-15-37/puglia/lecce/34499-coldiretti-puglia-le-donne-dei-campi-a-lecce-fanno-rete-contro-la-violenza.html",
      "published_at": "",
      "language": null,
      "source_lang": null,
      "provider": "gdelt_gkg_geojson",
      "themes": [
        "ALLIANCE",
        "TAX_FNCACT_COURIER",
        "WB_2433_CONFLICT_AND_VIOLENCE",
        "WB_2432_FRAGILITY_CONFLICT_AND_VIOLENCE",
        "UNGP_CRIME_VIOLENCE",
        "WB_2433_CONFLICT_AND_VIOLENCE",
        "WB_2432_FRAGILITY_CONFLICT_AND_VIOLENCE",
        "UNGP_CRIME_VIOLENCE",
        "EPU_ECONOMY",
        "EPU_ECONOMY_HISTORIC",
        "TAX_FNCACT_VICTIMS",
        "CRISISLEX_CRISISLEXREC",
        "CRISISLEX_T08_MISSINGFOUNDTRAPPEDPEOPLE",
        "TAX_FNCACT_WOMEN",
        "TAX_FNCACT_WOMEN",
        "TAX_FNCACT_WOMEN",
        "TAX_FNCACT_WOMEN"
      ]
    },
    {
      "title": "Chile",
      "title_en": null,
      "source": "www.hkcd.com",
      "url": "https://www.hkcd.com/hkcdweb/content/2026/06/25/content_8761758.html",
      "published_at": "",
      "language": null,
      "source_lang": null,
      "provider": "gdelt_gkg_geojson",
      "themes": [
        "TAX_ETHNICITY_ZHUANG",
        "TAX_WORLDLANGUAGES_ZHUANG",
        "TAX_ETHNICITY_ZHUANG",
        "TAX_WORLDLANGUAGES_ZHUANG",
        "EPU_ECONOMY_HISTORIC",
        "TAX_FNCACT_CHAIRMAN",
        "TAX_FNCACT_CHAIRMAN",
        "UNGP_FORESTS_RIVERS_OCEANS",
        "TAX_FNCACT_SECRETARY",
        "USPEC_POLITICS_GENERAL1"
      ]
    },
    {
      "title": "Fan Ying, Jiangsu, China",
      "title_en": null,
      "source": "www.hkcd.com",
      "url": "https://www.hkcd.com/hkcdweb/content/2026/06/25/content_8761758.html",
      "published_at": "",
      "language": null,
      "source_lang": null,
      "provider": "gdelt_gkg_geojson",
      "themes": [
        "SCIENCE",
        "SCIENCE",
        "EPU_ECONOMY"
      ]
    },
    {
      "title": "Dongxing, Jilin, China",
      "title_en": null,
      "source": "www.hkcd.com",
      "url": "https://www.hkcd.com/hkcdweb/content/2026/06/25/content_8761758.html",
      "published_at": "",
      "language": null,
      "source_lang": null,
      "provider": "gdelt_gkg_geojson",
      "themes": [
        "ENV_METALS",
        "WB_2936_GOLD",
        "WB_507_ENERGY_AND_EXTRACTIVES",
        "WB_895_MINING_SYSTEMS",
        "WB_1699_METAL_ORE_MINING",
        "SEIZE",
        "USPEC_POLICY1",
        "EPU_POLICY_POLICY",
        "EPU_ECONOMY"
      ]
    },
    {
      "title": "Guangxi, Guangxi, China",
      "title_en": null,
      "source": "www.hkcd.com",
      "url": "https://www.hkcd.com/hkcdweb/content/2026/06/25/content_8761758.html",
      "published_at": "",
      "language": null,
      "source_lang": null,
      "provider": "gdelt_gkg_geojson",
      "themes": [
        "TAX_ETHNICITY_ZHUANG",
        "TAX_WORLDLANGUAGES_ZHUANG",
        "EPU_ECONOMY_HISTORIC",
        "EPU_ECONOMY_HISTORIC",
        "WB_678_DIGITAL_GOVERNMENT",
        "WB_694_BROADCAST_AND_MEDIA",
        "WB_133_INFORMATION_AND_COMMUNICATION_TECHNOLOGIES",
        "SEIZE",
        "WB_2601_TRADE_LINKAGES_SPILLOVERS_AND_CONNECTIVITY",
        "WB_772_TRADE_FACILITATION_AND_LOGISTICS",
        "WB_699_URBAN_DEVELOPMENT",
        "WB_866_CONNECTIVITY_AND_LAGGING_REGIONS",
        "WB_698_TRADE",
        "WB_797_NATIONAL_URBAN_POLICIES",
        "GENERAL_GOVERNMENT",
        "EPU_POLICY_GOVERNMENT",
        "TAX_FNCACT_ORGANIZER"
      ]
    },
    {
      "title": "Spain",
      "title_en": null,
      "source": "www.hkcd.com",
      "url": "https://www.hkcd.com/hkcdweb/content/2026/06/25/content_8761758.html",
      "published_at": "",
      "language": null,
      "source_lang": null,
      "provider": "gdelt_gkg_geojson",
      "themes": [
        "TAX_FNCACT_REPRESENTATIVE",
        "TAX_FNCACT_REPRESENTATIVE",
        "EPU_ECONOMY_HISTORIC",
        "TAX_ECON_PRICE",
        "TAX_FNCACT_CHAIRMAN",
        "WB_286_TELECOMMUNICATIONS_AND_BROADBAND_ACCESS"
      ]
    },
    {
      "title": "Jaipur, Rajasthan, India",
      "title_en": null,
      "source": "www.khaskhabar.com",
      "url": "https://www.khaskhabar.com/local/rajasthan/jaipur-news/news-rajasthan-achievements-received-appreciation-at-the-national-cooperative-conference-held-in-srinagar-news-hindi-1-824143-KKN.html",
      "published_at": "",
      "language": null,
      "source_lang": null,
      "provider": "gdelt_gkg_geojson",
      "themes": [
        "EPU_ECONOMY_HISTORIC",
        "TAX_FNCACT_SECRETARY",
        "USPEC_POLITICS_GENERAL1"
      ]
    },
    {
      "title": "Burgundy, France (General), France",
      "title_en": null,
      "source": "www.voici.fr",
      "url": "https://www.voici.fr/celebrites/dette-de-2-millions-d-euros-pour-chantal-goya-elle-revele-ce-qui-s-est-passe-et-ce-qu-elle-a-deja-rembourse-825523",
      "published_at": "",
      "language": null,
      "source_lang": null,
      "provider": "gdelt_gkg_geojson",
      "themes": [
        "ECON_DEBT",
        "WB_1104_MACROECONOMIC_VULNERABILITY_AND_DEBT",
        "WB_450_DEBT",
        "TAX_FNCACT_SINGER",
        "WB_2670_JOBS",
        "WB_696_PUBLIC_SECTOR_MANAGEMENT",
        "WB_2048_COMPENSATION_CAREERS_AND_INCENTIVES",
        "WB_723_PUBLIC_ADMINISTRATION",
        "WB_724_HUMAN_RESOURCES_FOR_PUBLIC_SECTOR",
        "ECON_TAXATION",
        "USPEC_POLICY1",
        "EPU_POLICY_TAX",
        "EPU_CATS_TAXES"
      ]
    },
    {
      "title": "Rawalpindi, Punjab, Pakistan",
      "title_en": null,
      "source": "www.voici.fr",
      "url": "https://www.voici.fr/celebrites/dette-de-2-millions-d-euros-pour-chantal-goya-elle-revele-ce-qui-s-est-passe-et-ce-qu-elle-a-deja-rembourse-825523",
      "published_at": "",
      "language": null,
      "source_lang": null,
      "provider": "gdelt_gkg_geojson",
      "themes": [
        "ECON_DEBT",
        "WB_1104_MACROECONOMIC_VULNERABILITY_AND_DEBT",
        "WB_450_DEBT",
        "TAX_FNCACT_SINGER",
        "WB_2670_JOBS",
        "WB_696_PUBLIC_SECTOR_MANAGEMENT",
        "WB_2048_COMPENSATION_CAREERS_AND_INCENTIVES",
        "WB_723_PUBLIC_ADMINISTRATION",
        "WB_724_HUMAN_RESOURCES_FOR_PUBLIC_SECTOR"
      ]
    },
    {
      "title": "Long Lu, Guangdong, China",
      "title_en": null,
      "source": "n.yam.com",
      "url": "https://n.yam.com/Article/20260625927420",
      "published_at": "",
      "language": null,
      "source_lang": null,
      "provider": "gdelt_gkg_geojson",
      "themes": [
        "NATURAL_DISASTER_HEAVY_RAIN",
        "CRISISLEX_O01_WEATHER",
        "CRISISLEX_T01_CAUTION_ADVICE",
        "LEGISLATION",
        "EPU_POLICY_LAW",
        "NATURAL_DISASTER_FLOOD",
        "WB_990_DRAINAGE",
        "WB_151_IRRIGATION_AND_DRAINAGE",
        "WB_140_AGRICULTURAL_WATER_MANAGEMENT",
        "WB_990_DRAINAGE",
        "WB_151_IRRIGATION_AND_DRAINAGE",
        "WB_140_AGRICULTURAL_WATER_MANAGEMENT",
        "WB_990_DRAINAGE",
        "WB_151_IRRIGATION_AND_DRAINAGE",
        "WB_140_AGRICULTURAL_WATER_MANAGEMENT",
        "WB_990_DRAINAGE",
        "WB_151_IRRIGATION_AND_DRAINAGE",
        "WB_140_AGRICULTURAL_WATER_MANAGEMENT",
        "WB_990_DRAINAGE",
        "WB_151_IRRIGATION_AND_DRAINAGE",
        "WB_140_AGRICULTURAL_WATER_MANAGEMENT",
        "WB_990_DRAINAGE",
        "WB_151_IRRIGATION_AND_DRAINAGE",
        "WB_140_AGRICULTURAL_WATER_MANAGEMENT",
        "ECON_INFLATION",
        "WB_1104_MACROECONOMIC_VULNERABILITY_AND_DEBT",
        "WB_442_INFLATION",
        "TAX_FNCACT_WRITER",
        "WB_137_WATER",
        "WB_137_WATER",
        "WB_137_WATER",
        "WB_137_WATER",
        "CRISISLEX_CRISISLEXREC",
        "USPEC_POLICY1"
      ]
    },
    {
      "title": "Cauvery River, India (General), India",
      "title_en": null,
      "source": "www.khaskhabar.com",
      "url": "https://www.khaskhabar.com/local/karnataka/mandya-news/news-muthathi-tragedy-family-members-drowned-one-by-one-while-trying-to-save-a-girl-five-dead-news-hindi-1-824146-KKN.html",
      "published_at": "",
      "language": null,
      "source_lang": null,
      "provider": "gdelt_gkg_geojson",
      "themes": [
        "ECON_TAXATION",
        "USPEC_POLICY1",
        "EPU_POLICY_TAX",
        "EPU_CATS_TAXES",
        "TAX_FNCACT_CHILD"
      ]
    },
    {
      "title": "Karnataka, Karnataka, India",
      "title_en": null,
      "source": "www.khaskhabar.com",
      "url": "https://www.khaskhabar.com/local/karnataka/mandya-news/news-muthathi-tragedy-family-members-drowned-one-by-one-while-trying-to-save-a-girl-five-dead-news-hindi-1-824146-KKN.html",
      "published_at": "",
      "language": null,
      "source_lang": null,
      "provider": "gdelt_gkg_geojson",
      "themes": [
        "CRISISLEX_T11_UPDATESSYMPATHY",
        "TOURISM",
        "WB_825_TOURISM",
        "WB_1921_PRIVATE_SECTOR_DEVELOPMENT",
        "WB_346_COMPETITIVE_INDUSTRIES",
        "WB_818_INDUSTRY_POLICY_AND_REAL_SECTORS",
        "ECON_TAXATION",
        "USPEC_POLICY1",
        "EPU_POLICY_TAX",
        "EPU_CATS_TAXES",
        "CRISISLEX_CRISISLEXREC",
        "CRISISLEX_CRISISLEXREC"
      ]
    },
    {
      "title": "Belarus",
      "title_en": null,
      "source": "society.comments.ua",
      "url": "https://society.comments.ua/news/warrussia/putina-otkrovenno-slivayut-chto-poshlo-ne-po-planu-kremlya-v-voyne-protiv-ukrainy-809630.html",
      "published_at": "",
      "language": null,
      "source_lang": null,
      "provider": "gdelt_gkg_geojson",
      "themes": [
        "WB_2433_CONFLICT_AND_VIOLENCE",
        "WB_2432_FRAGILITY_CONFLICT_AND_VIOLENCE",
        "ARMEDCONFLICT",
        "EPU_CATS_NATIONAL_SECURITY",
        "ARMEDCONFLICT",
        "EPU_CATS_NATIONAL_SECURITY",
        "EPU_ECONOMY_HISTORIC",
        "EPU_ECONOMY_HISTORIC",
        "EPU_ECONOMY_HISTORIC"
      ]
    },
    {
      "title": "Manavgat, Antalya, Turkey",
      "title_en": null,
      "source": "www.yeniakit.com.tr",
      "url": "https://www.yeniakit.com.tr/haber/spiral-makinesi-ile-demir-keserken-koca-ilceyi-yakiyordu-gozaltina-alindi-2009428.html",
      "published_at": "",
      "language": null,
      "source_lang": null,
      "provider": "gdelt_gkg_geojson",
      "themes": [
        "WB_566_ENVIRONMENT_AND_NATURAL_RESOURCES",
        "WB_1777_FORESTS",
        "WB_590_ECOSYSTEMS",
        "UNGP_FORESTS_RIVERS_OCEANS",
        "WB_566_ENVIRONMENT_AND_NATURAL_RESOURCES",
        "WB_1777_FORESTS",
        "WB_590_ECOSYSTEMS",
        "UNGP_FORESTS_RIVERS_OCEANS",
        "WB_566_ENVIRONMENT_AND_NATURAL_RESOURCES",
        "WB_1777_FORESTS",
        "WB_590_ECOSYSTEMS",
        "UNGP_FORESTS_RIVERS_OCEANS",
        "DISASTER_FIRE",
        "CRISISLEX_T01_CAUTION_ADVICE",
        "TAX_FNCACT_LECTURERS",
        "GENERAL_GOVERNMENT",
        "EPU_ECONOMY_HISTORIC",
        "WB_137_WATER",
        "WB_2931_IRON",
        "WB_507_ENERGY_AND_EXTRACTIVES",
        "WB_895_MINING_SYSTEMS",
        "WB_1699_METAL_ORE_MINING",
        "TAX_FNCACT_MANAGER",
        "ARREST",
        "CRISISLEX_C07_SAFETY"
      ]
    },
    {
      "title": "Antalya, Antalya, Turkey",
      "title_en": null,
      "source": "www.yeniakit.com.tr",
      "url": "https://www.yeniakit.com.tr/haber/spiral-makinesi-ile-demir-keserken-koca-ilceyi-yakiyordu-gozaltina-alindi-2009428.html",
      "published_at": "",
      "language": null,
      "source_lang": null,
      "provider": "gdelt_gkg_geojson",
      "themes": [
        "WB_566_ENVIRONMENT_AND_NATURAL_RESOURCES",
        "WB_1777_FORESTS",
        "WB_590_ECOSYSTEMS",
        "UNGP_FORESTS_RIVERS_OCEANS",
        "WB_566_ENVIRONMENT_AND_NATURAL_RESOURCES",
        "WB_1777_FORESTS",
        "WB_590_ECOSYSTEMS",
        "UNGP_FORESTS_RIVERS_OCEANS",
        "WB_566_ENVIRONMENT_AND_NATURAL_RESOURCES",
        "WB_1777_FORESTS",
        "WB_590_ECOSYSTEMS",
        "UNGP_FORESTS_RIVERS_OCEANS",
        "DISASTER_FIRE",
        "CRISISLEX_T01_CAUTION_ADVICE",
        "TAX_FNCACT_LECTURERS",
        "GENERAL_GOVERNMENT",
        "EPU_ECONOMY_HISTORIC",
        "WB_137_WATER",
        "WB_137_WATER",
        "WB_2931_IRON",
        "WB_507_ENERGY_AND_EXTRACTIVES",
        "WB_895_MINING_SYSTEMS",
        "WB_1699_METAL_ORE_MINING",
        "MARITIME",
        "TAX_FNCACT_MANAGER",
        "ARREST",
        "CRISISLEX_C07_SAFETY"
      ]
    },
    {
      "title": "Armenia",
      "title_en": null,
      "source": "www.panarmenian.net",
      "url": "https://www.panarmenian.net/eng/news/334538/",
      "published_at": "",
      "language": null,
      "source_lang": null,
      "provider": "gdelt_gkg_geojson",
      "themes": [
        "TAX_ETHNICITY_ARMENIAN",
        "TAX_WORLDLANGUAGES_ARMENIAN",
        "TAX_FNCACT_FOREIGN_MINISTER",
        "TAX_FNCACT_MINISTER",
        "TAX_FNCACT_DEPUTY",
        "EPU_ECONOMY_HISTORIC",
        "TAX_FNCACT_DELEGATE",
        "WB_775_TRADE_POLICY_AND_INTEGRATION",
        "WB_776_TRADE_POLICY",
        "WB_698_TRADE",
        "WB_2575_TRADE_POLICY_AND_INVESTMENT_AGREEMENTS",
        "TAX_FNCACT_MINISTER"
      ]
    },
    {
      "title": "Jermuk, Vayots' Dzor, Armenia",
      "title_en": null,
      "source": "www.panarmenian.net",
      "url": "https://www.panarmenian.net/eng/news/334538/",
      "published_at": "",
      "language": null,
      "source_lang": null,
      "provider": "gdelt_gkg_geojson",
      "themes": [
        "BAN",
        "TAX_ETHNICITY_ARMENIAN",
        "TAX_WORLDLANGUAGES_ARMENIAN",
        "WB_2601_TRADE_LINKAGES_SPILLOVERS_AND_CONNECTIVITY",
        "WB_772_TRADE_FACILITATION_AND_LOGISTICS",
        "WB_699_URBAN_DEVELOPMENT",
        "WB_866_CONNECTIVITY_AND_LAGGING_REGIONS",
        "WB_797_NATIONAL_URBAN_POLICIES",
        "WB_137_WATER",
        "TAX_WORLDLANGUAGES_RUSSIA",
        "TAX_WORLDLANGUAGES_RUSSIA",
        "EPU_ECONOMY",
        "TAX_ECON_FREETRADEAGREEMENTS_EURASIAN_ECONOMIC_UNION",
        "AGRICULTURE"
      ]
    },
    {
      "title": "Bishkek, Bishkek, Kyrgyzstan",
      "title_en": null,
      "source": "knews.kg",
      "url": "https://knews.kg/2026/06/25/v-bishkeke-vyyavleny-narusheniya-pri-stroitelstve-obshhezhitiya-osoo-yantszy-oshtrafovano/",
      "published_at": "",
      "language": null,
      "source_lang": null,
      "provider": "gdelt_gkg_geojson",
      "themes": [
        "USPEC_POLICY1",
        "EPU_ECONOMY",
        "EPU_ECONOMY_HISTORIC",
        "WB_1921_PRIVATE_SECTOR_DEVELOPMENT",
        "WB_405_BUSINESS_CLIMATE",
        "WB_2531_INSPECTIONS_LICENSING_AND_PERMITS",
        "WB_2530_BUSINESS_ENVIRONMENT",
        "LEGISLATION",
        "EPU_POLICY_LAW",
        "URBAN"
      ]
    },
    {
      "title": "Malaysia",
      "title_en": null,
      "source": "www.malaysiasun.com",
      "url": "http://www.malaysiasun.com/news/279146697/malaysia-posts-1st-services-trade-surplus-since-2011",
      "published_at": "",
      "language": null,
      "source_lang": null,
      "provider": "gdelt_gkg_geojson",
      "themes": [
        "ECON_WORLDCURRENCIES_DOLLARS",
        "USPEC_POLICY1",
        "WB_698_TRADE",
        "WB_698_TRADE",
        "TAX_FNCACT_OFFICIAL"
      ]
    },
    {
      "title": "Kuala Lumpur, Kuala Lumpur, Malaysia",
      "title_en": null,
      "source": "www.malaysiasun.com",
      "url": "http://www.malaysiasun.com/news/279146697/malaysia-posts-1st-services-trade-surplus-since-2011",
      "published_at": "",
      "language": null,
      "source_lang": null,
      "provider": "gdelt_gkg_geojson",
      "themes": [
        "ECON_WORLDCURRENCIES_DOLLARS",
        "USPEC_POLICY1",
        "WB_698_TRADE",
        "WB_698_TRADE",
        "TAX_FNCACT_OFFICIAL"
      ]
    },
    {
      "title": "Westport, Mayo, Ireland",
      "title_en": null,
      "source": "www.con-telegraph.ie",
      "url": "https://www.con-telegraph.ie/2026/06/25/long-awaited-progress-on-getting-tea-back-on-the-mayo-train/",
      "published_at": "",
      "language": null,
      "source_lang": null,
      "provider": "gdelt_gkg_geojson",
      "themes": [
        "TAX_ETHNICITY_IRISH",
        "TAX_WORLDLANGUAGES_IRISH",
        "TAX_ETHNICITY_IRISH",
        "TAX_WORLDLANGUAGES_IRISH",
        "TAX_FNCACT_PILOT",
        "TAX_FNCACT_PILOT",
        "TAX_FNCACT_PILOT",
        "TAX_ECON_PRICE"
      ]
    },
    {
      "title": "Dublin, Dublin, Ireland",
      "title_en": null,
      "source": "www.con-telegraph.ie",
      "url": "https://www.con-telegraph.ie/2026/06/25/long-awaited-progress-on-getting-tea-back-on-the-mayo-train/",
      "published_at": "",
      "language": null,
      "source_lang": null,
      "provider": "gdelt_gkg_geojson",
      "themes": [
        "TAX_DISEASE_COVID",
        "TAX_ETHNICITY_IRISH",
        "TAX_WORLDLANGUAGES_IRISH",
        "TAX_FNCACT_DEPUTY",
        "TAX_FNCACT_PILOT",
        "TAX_FNCACT_PILOT",
        "TAX_ECON_PRICE",
        "PUBLIC_TRANSPORT",
        "PUBLIC_TRANSPORT",
        "WB_137_WATER"
      ]
    },
    {
      "title": "Ireland",
      "title_en": null,
      "source": "www.con-telegraph.ie",
      "url": "https://www.con-telegraph.ie/2026/06/25/long-awaited-progress-on-getting-tea-back-on-the-mayo-train/",
      "published_at": "",
      "language": null,
      "source_lang": null,
      "provider": "gdelt_gkg_geojson",
      "themes": [
        "TAX_DISEASE_COVID",
        "TAX_ETHNICITY_IRISH",
        "TAX_WORLDLANGUAGES_IRISH",
        "TAX_ETHNICITY_IRISH",
        "TAX_WORLDLANGUAGES_IRISH",
        "TAX_FNCACT_DEPUTY",
        "TAX_FNCACT_PILOT",
        "TAX_FNCACT_PILOT",
        "TAX_ECON_PRICE",
        "PUBLIC_TRANSPORT",
        "PUBLIC_TRANSPORT",
        "WB_137_WATER"
      ]
    }
  ]
}